Workbook

Sheet 01_概要
B2: Data Cloud コンサルタント
C3: Salesforce.Data-Cloud-Consultant-JPN.v2025-03-28.q66 | D3: =COUNTIFS('02_問題'!$J$4:$J$228,'01_概要'!$C3) -> 66
C4: Salesforce.Data-Cloud-Consultant-JPN.v2024-09-12.q66 | D4: =COUNTIFS('02_問題'!$J$4:$J$228,'01_概要'!$C4) -> 66
C5: Salesforce.Data-Cloud-Consultant.v2024-12-02.q93 | D5: =COUNTIFS('02_問題'!$J$4:$J$228,'01_概要'!$C5) -> 93
C6: 総計 | D6: =SUM(D3:D5) -> 225
B8: 分類 | F8: ◯ | G8: ×
C9: 01_Data Cloud の概要 | D9: =COUNTIFS('02_問題'!$D$4:$D$228,'01_概要'!$C9) -> 29 | E9: =D9/$D$15 -> 0.12888889 | F9: =COUNTIFS('02_問題'!$D$4:$D$228,'01_概要'!$C9,'02_問題'!$C$4:$C$228,'01_概要'!F$8)/$D9 -> 0.96551724 | G9: =COUNTIFS('02_問題'!$D$4:$D$228,'01_概要'!$C9,'02_問題'!$C$4:$C$228,'01_概要'!G$8)/$D9 -> 0.034482759 | H9: 0.18 | I9: =F9*H9 -> 0.1737931
C10: 02_Data Cloud の設定と管理 | D10: =COUNTIFS('02_問題'!$D$4:$D$228,'01_概要'!$C10) -> 34 | E10: =D10/$D$15 -> 0.15111111 | F10: =COUNTIFS('02_問題'!$D$4:$D$228,'01_概要'!$C10,'02_問題'!$C$4:$C$228,'01_概要'!F$8)/$D10 -> 0.94117647 | G10: =COUNTIFS('02_問題'!$D$4:$D$228,'01_概要'!$C10,'02_問題'!$C$4:$C$228,'01_概要'!G$8)/$D10 -> 0.058823529 | H10: 0.12 | I10: =F10*H10 -> 0.11294118
C11: 03_データ取得とデータモデリング | D11: =COUNTIFS('02_問題'!$D$4:$D$228,'01_概要'!$C11) -> 45 | E11: =D11/$D$15 -> 0.2 | F11: =COUNTIFS('02_問題'!$D$4:$D$228,'01_概要'!$C11,'02_問題'!$C$4:$C$228,'01_概要'!F$8)/$D11 -> 0.97777778 | G11: =COUNTIFS('02_問題'!$D$4:$D$228,'01_概要'!$C11,'02_問題'!$C$4:$C$228,'01_概要'!G$8)/$D11 -> 0.022222222 | H11: 0.2 | I11: =F11*H11 -> 0.19555556
C12: 04_ID 解決 | D12: =COUNTIFS('02_問題'!$D$4:$D$228,'01_概要'!$C12) -> 36 | E12: =D12/$D$15 -> 0.16 | F12: =COUNTIFS('02_問題'!$D$4:$D$228,'01_概要'!$C12,'02_問題'!$C$4:$C$228,'01_概要'!F$8)/$D12 -> 0.97222222 | G12: =COUNTIFS('02_問題'!$D$4:$D$228,'01_概要'!$C12,'02_問題'!$C$4:$C$228,'01_概要'!G$8)/$D12 -> 0.027777778 | H12: 0.14 | I12: =F12*H12 -> 0.13611111
C13: 05_セグメンテーションとインサイト | D13: =COUNTIFS('02_問題'!$D$4:$D$228,'01_概要'!$C13) -> 39 | E13: =D13/$D$15 -> 0.17333333 | F13: =COUNTIFS('02_問題'!$D$4:$D$228,'01_概要'!$C13,'02_問題'!$C$4:$C$228,'01_概要'!F$8)/$D13 -> 0.84615385 | G13: =COUNTIFS('02_問題'!$D$4:$D$228,'01_概要'!$C13,'02_問題'!$C$4:$C$228,'01_概要'!G$8)/$D13 -> 0.15384615 | H13: 0.18 | I13: =F13*H13 -> 0.15230769
C14: 06_データの操作 | D14: =COUNTIFS('02_問題'!$D$4:$D$228,'01_概要'!$C14) -> 42 | E14: =D14/$D$15 -> 0.18666667 | F14: =COUNTIFS('02_問題'!$D$4:$D$228,'01_概要'!$C14,'02_問題'!$C$4:$C$228,'01_概要'!F$8)/$D14 -> 0.92857143 | G14: =COUNTIFS('02_問題'!$D$4:$D$228,'01_概要'!$C14,'02_問題'!$C$4:$C$228,'01_概要'!G$8)/$D14 -> 0.047619048 | H14: 0.18 | I14: =F14*H14 -> 0.16714286
C15: 総計 | D15: =SUM(D9:D14) -> 225 | E15: =D15/$D$15 -> 1 | F15: =SUMPRODUCT(F9:F14,$D$9:$D$14)/SUM($D$9:$D$14) -> 0.93777778 | G15: =SUMPRODUCT(G9:G14,$D$9:$D$14)/SUM($D$9:$D$14) -> 0.057777778 | H15: =SUM(H9:H14) -> 1 | I15: =SUM(I9:I14) -> 0.9378515
D21: 0.18 | E21: 0.8 | F21: =D21*E21*100 -> 14.4
D22: 0.12 | E22: 0.75 | F22: =D22*E22*100 -> 9
D23: 0.2 | E23: 0.75 | F23: =D23*E23*100 -> 15
D24: 0.14 | E24: 1 | F24: =D24*E24*100 -> 14
D25: 0.18 | E25: 0.63 | F25: =D25*E25*100 -> 11.34
D26: 0.18 | E26: 0.72 | F26: =D26*E26*100 -> 12.96
F27: =SUM(F21:F26) -> 76.7

Sheet 02_問題
M1: *
B2: JPN | H2: GenAI | M2: *
B3: # | C3: 正誤 | D3: 分類 | E3: 問題 | F3: 解答 | G3: 解説 | H3: 解答 | I3: 解説 | J3: 出所 | K3: 重複# | M3: *
B4: 6 | C4: ◯ | D4: 01_Data Cloud の概要 | E4: Data Cloud で対処できる一般的なユースケースはどれですか? 2つの回答を選択してください A. 顧客データを理解し、それに基づいて行動することで、より関連性の高いエクスペリエンスを実現します。 B. 一元化された一連のポリシーとプロセスを通じて、エンタープライズ データのライフサイクルを管理します。 C. 標準化され拡張可能なデータ モデルを使用して、複数のソースからのデータを調和させます。 D. バックアップと災害対策のための集中システムとして機能し、重要なビジネスデータを保護します。 | F4: A, C | G4: 回復。 説明： Data Cloudは、Salesforceおよび外部ソースを含む多様なデータソースからデータを接続、準備、統合、一元化、クエリ、分析、活用するためのデータプラットフォームです。Data Cloudで対応可能な一般的なユースケースには以下のものが含まれます： 顧客データを理解し、より関連性の高い体験を促進する。Data Cloudは、異なるソースからのデータを統合し、チャネル横断でのアイデンティティを解決することで、顧客の360度ビューを獲得するのを支援します。Data Cloudはまた、顧客セグメンテーション、パーソナライズド体験の創出、インサイトとAIを活用したデータ活用を、あらゆるチャネルで実現するのを支援します。 複数のソースからのデータを標準化され拡張可能なデータモデルで統合する。Data Cloudは、データを活用する前に変換・クリーニングし、拡張・カスタマイズ可能な共通データモデルにマッピングするのを支援します。Data Cloudは、データエンリッチメントやアイデンティティ解決の最適化のため、計算済みインサイトや関連属性を生成する機能も提供します。 他の2つのオプションは、Data Cloudの一般的な使用ケースではありません。Data Cloudはデータガバナンスやバックアップ/災害復旧機能を提供しません。これらの機能は通常、Salesforceの他のソリューションまたは外部ソリューションで処理されます。 参照： Data Cloudの動作原理を学ぶ Salesforce Data Cloudについて プラットフォームのユースケースを発見 一般的なデータ分析のユースケースを理解する | H4: A, C | I4: ◾ 背景：Salesforce Data Cloud の主な役割とは？ Salesforce Data Cloud（旧 CDP）は、主に以下の目的で使用されます： 顧客中心のデータ統合と理解 セグメンテーション、インサイト生成、アクティベーションによるマーケティング最適化 リアルタイムのデータストリームとパーソナライズ体験の実現 つまり、「誰が顧客なのかを理解し、適切なチャネルで、適切なタイミングで、適切な体験を届ける」という一連のサイクルを支えるためのデータプラットフォームです。 ✅ 正解理由： ▶ A. 顧客データを理解し、それに基づいて行動することで、より関連性の高いエクスペリエンスを実現 Data Cloud の 最大の価値は、リアルタイム顧客理解に基づいたアクション（施策） にあります。 Identity Resolution や Streaming Insights、Calculated Insights を通じて、 パーソナライズされたキャンペーンや提案を実現できます。 ▶ C. 標準化され拡張可能なデータモデルを使用して、複数のソースからのデータを調和 Data Cloud は Salesforce CDM（Cloud Data Model）という 拡張可能な標準モデルを用いて、 異なるスキーマ（CRM、EC、アプリ等）からのデータを Harmonization（調和） します。 統一されたデータモデルにより、正確な統合プロファイルの生成と柔軟なセグメント設計が可能になります。 ❌ 誤りの選択肢と理由： 選択肢 理由 B. 一元化されたポリシーとプロセスを通じたエンタープライズデータ管理 ❌ これはMDM（マスターデータ管理）やガバナンスツールの役割。Data Cloud の主目的ではない。 D. バックアップと災害対策のための集中システム ❌ Data Cloud はマーケティング・顧客体験向けの分析/アクティベーション基盤であり、DR（災害対策）用途ではない。 📝 まとめ表： ユースケース内容 Data Cloud として正しいか ✅ 顧客データの理解とアクション ✔️ 正解 ❌ エンタープライズ全体のデータライフサイクル管理 ❌ 不正解（MDM寄り） ✅ 異種データソースの統合と標準化モデルでの調和 ✔️ 正解 ❌ バックアップ/災害対策としての運用 ❌ 不正解（別カテゴリ） | J4: Salesforce.Data-Cloud-Consultant-JPN.v2025-03-28.q66 | K4: - | M4: *
B5: 16 | C5: ◯ | D5: 01_Data Cloud の概要 | E5: データクラウドにおける人工知能 (AI) の役割は何ですか? A. データ検証の自動化 B. 動的なデータ駆動型管理ダッシュボードの作成 C. 洞察と予測を通じて顧客とのやり取りを強化 D. ユースケース用のメールテンプレートの生成 | F5: C | G5: * AIの役割：Salesforce Data Cloudにおいて、人工知能（AI）はデータを活用して洞察と予測を生成し、顧客とのインタラクションを向上させる重要な役割を果たしています。 * 洞察と予測： AIアルゴリズム： 機械学習アルゴリズムを活用して、大量の顧客データを分析します。 予測分析： 顧客の行動傾向、好み、潜在的な将来の行動など、予測可能な洞察を提供します。 * 顧客体験の向上： パーソナライゼーション： 顧客のニーズと好みを予測することで、パーソナライズされた体験を創出します。 効率化： 顧客が連絡を取る前に問題を予測し、解決策を提案することで、プロアクティブなカスタマーサービスを実現します。 マーケティング：ターゲティングとセグメンテーションを最適化し、マーケティング活動を最も有望なリードや顧客に集中させます。 * 活用事例： レコメンドエンジン：過去の行動や好みに基づいて製品やサービスを提案します。 チャーン予測：離反リスクの高い顧客を特定し、リテンション戦略でエンゲージメントを強化します。 * 参照： Salesforce Data Cloud AI機能 Salesforce AI for Customer Interaction | H5: C | I5: ◾ 質問の主旨： Data Cloud（旧 CDP）において、人工知能（AI）の役割とは何か？ Salesforce Data Cloud における AI は、Einstein AI や生成AI（Einstein GPT）と連携して、顧客データから有用な洞察・予測を導き出し、それをパーソナライズされたエクスペリエンスに活かす役割を担っています。 ▶ 正解理由（C）： AIは、Data Cloud に取り込まれた統合顧客データに基づいて： 購入予測 チャーン（離脱）予測 エンゲージメントスコアの推定 セグメントごとのインサイト抽出 リアルタイムでの最適アクションの提案 などを実現することで、顧客体験（CX）の強化に貢献します。 ■ 他の選択肢の検討： 選択肢 評価 理由 A. データ検証の自動化 ❌ 不正解 データの整合性検証やETLは主に データパイプライン・変換ロジックの役割。AIではない B. ダッシュボードの自動作成 ❌ 不正解 ダッシュボードは BIツール（Tableauなど）で作成。AIの直接機能ではない C. 洞察と予測による強化 ✅ 正解 AIの本来の役割そのもの。Einstein予測やセグメントインテリジェンスと連携 D. メールテンプレート生成 ❌ 不正解 これは Einstein GPT for Marketing の役割であり、Data Cloud固有の機能ではない | J5: Salesforce.Data-Cloud-Consultant-JPN.v2025-03-28.q66 | K5: - | M5: *
B6: 45 | C6: ◯ | D6: 01_Data Cloud の概要 | E6: ノーザン トレイル アウトフィッターズはデータ クラウドの実装を希望しており、いくつかのユースケースを念頭に置いています。 Data Cloud に適していると考えられる 2 つのユースケースはどれですか? 2 つの答えを選択してください A. 顧客のアイデンティティを照合するために、さまざまなソースからデータを取り込んで統合するため B. クロスチャネル マーケティング メッセージを作成および調整するため C. 調和されたデータを使用して、顧客とビジネスへの影響をより正確に理解するため D. 個別のビジネス インテリジェンス ツールと IT データ管理ツールの必要性を排除するため | F6: A, C | G6: Data Cloudは、Salesforceおよび外部ソースを含む多様なデータソースからデータを接続、準備、統合、統一、クエリ、分析、活用するためのデータプラットフォームです。Data Cloudが適している主なユースケースは以下の通りです： 多様なソースからデータを収集し統合して顧客のアイデンティティを一致させる。Data Cloudは、ストリーミングデータやバッチデータを含むすべてのデータをSalesforceに統合し、共通のデータモデルにマッピングするのを支援します。Data Cloudは、異なるチャネルやソース間の顧客IDを解決し、統一された顧客プロファイルを作成する支援も可能です。 調和されたデータを活用して、顧客とビジネスへの影響を正確に理解する。Data Cloudは、データを活用する前に変換・クリーニングを行い、計算されたインサイトや関連属性でデータを豊かにする支援が可能です。Data Cloudは、データに基づくセグメントやオーディエンスを作成し、任意のチャネルでアクティベートする支援も可能です。Data Cloudは、AIを活用して顧客の行動や結果を予測する支援も可能です。 他の2つのオプションは、Data Cloudに適したユースケースとは考えられていません。Data Cloudは、クロスチャネルマーケティングメッセージの作成やオーケストレーション機能を提供しません。これは通常、Marketing Cloudなどの他のSalesforceソリューションで処理されます。Data Cloudは、ビジネスインテリジェンスやITデータ管理ツールの必要性を排除するものではありません。これらのツールと連携し、その機能を補完するように設計されています。 参照： Data Cloudの仕組みについて学ぶ Salesforce Data Cloudについて プラットフォームのユースケースを発見する 一般的なデータ分析のユースケースを理解する | H6: A, C | I6: Salesforce Data Cloud は、以下の目的に特化したプラットフォームです： マルチソースの顧客データ統合（ID解決） データの調和と構造化 統一された顧客プロファイルの生成 リアルタイムのセグメンテーションとアクティベーション 顧客行動に基づく分析とインサイト抽出 ✅ 各正解の詳細： ✅ A. 顧客のアイデンティティを照合して統合する Data Cloud の中核機能である ID解決（Identity Resolution） に該当。 顧客が複数チャネルで残した断片的データ（例：メール、電話、Cookie、会員情報など）を1つの「統合プロファイル」にまとめることができる。 ✅ C. 調和されたデータを使ってビジネスインサイトを得る **Harmonization（調和）**されたデータにより、正確で信頼できる顧客像をベースにした分析が可能。 計算されたインサイトやセグメントインテリジェンスを通じて、顧客行動とビジネス成果の関係性を可視化できる。 ❌ 不正解の選択肢： 選択肢 評価 理由 B. クロスチャネル マーケティング メッセージの作成・調整 ❌ 不正解 これは Marketing Cloud（Engagement） の主な領域であり、Data Cloud はセグメント提供や属性補完を担当 D. BI/ITツールの排除 ❌ 不正解 Data Cloud は BIやIT管理の代替ではなく、むしろそれらと連携する補完的存在（TableauやETLツールなどと共存） | J6: Salesforce.Data-Cloud-Consultant-JPN.v2025-03-28.q66 | K6: - | M6: *
B7: 49 | C7: ◯ | D7: 01_Data Cloud の概要 | E7: Data Cloud はどのようにしてデータのプライバシーとセキュリティを確保しますか? A. 保存時および転送中のデータを暗号化することで B. 同意の参照を強制および制御することにより C. オフサイトサーバーにデータを安全に保存することで D. データアクセスを許可された管理者に制限することで | F7: A | G7: * データプライバシーとセキュリティ（データクラウド）： Salesforce Data Cloudにおいて、データプライバシーとセキュリティの確保は最優先事項です。 参照： * 主要なセキュリティ対策： データ暗号化（保管時と転送時）： データ暗号化により、データが保管中および転送中に不正アクセスから保護されます。 同意設定の管理と制御： 同意管理により、データの利用が顧客の許可と規制要件に準拠するように確保されます。 * セキュリティ対策の実施手順： データ暗号化： Salesforce Shieldを使用して、保存中のデータに暗号化を有効化します。 転送中のデータにTLS/SSL暗号化が使用されていることを確認します。 同意管理： Data Cloud内で同意設定を設定し、適用します。 同意記録を定期的に監査し、更新します。 * 実践的な応用： 例： 金融機関は顧客の財務データを暗号化して保護し、GDPRに準拠するために同意管理を実施しています。 | H7: A | I7: Salesforce Data Cloud は、エンタープライズレベルのプラットフォームとして、顧客データのプライバシーとセキュリティを確保するために、複数のセキュリティ対策を実施しています。その中でも最も基本的かつ中核的な対策が： ✅ 「保存時（at rest）」および「転送中（in transit）」のデータ暗号化です。 暗号化の具体例： 保存時：データレイクやデータベースに保存されているデータは AES-256 などの業界標準の方式で暗号化される。 転送中：APIやブラウザ、連携ツールを通じて送信されるデータは TLS/SSL によって暗号化される。 このように、データ漏洩リスクを防止するための根本的な対策が常時適用されています。 ❌ 他の選択肢の誤り： 選択肢 評価 理由 A. 保存時および転送中の暗号化 ✅ 正解 データセキュリティの中核的な技術対策であり、すべての組織に自動で適用される B. 同意の参照を強制および制御する ❌ 一部正しいが不完全 これは 「プライバシー制御の一部（Consent Management）」 にすぎず、暗号化のようなセキュリティの土台ではない C. オフサイトサーバーに保存する ❌ 不正確 どこに保存するかではなく、保存方法（暗号化など）が重要。また「オフサイト」がセキュリティを担保するとは限らない D. 管理者にアクセスを制限する ❌ 不正解 アクセス制御は一部のセキュリティ手段だが、プライバシーとセキュリティの中心対策ではない（しかも「管理者のみ」は過剰制限） | J7: Salesforce.Data-Cloud-Consultant-JPN.v2025-03-28.q66 | K7: - | M7: *
B8: 83 | C8: ◯ | D8: 01_Data Cloud の概要 | E8: Data Cloud はどのようにしてデータのプライバシーとセキュリティを確保しますか? A. 保存時および転送中のデータを暗号化することで B. 同意の参照を強制および制御することにより C. オフサイトサーバーにデータを安全に保存することで D. データアクセスを許可された管理者に制限することで | F8: A | G8: データプライバシーとセキュリティにおけるデータクラウド： * Salesforce Data Cloudにおいて、データプライバシーとセキュリティの確保は最優先事項です。 | H8: A | I8: ◾ 問題の焦点： Salesforce Data Cloud（旧 CDP）は、個人情報（PII）などを含む大量の顧客データを扱うため、データのプライバシーとセキュリティを強固に保護することが必須です。 → この設問では、「Data Cloud が技術的にどのようにしてセキュリティを確保しているか？」を問われています。 ✅ 正解理由：「暗号化（Encryption）」はセキュリティの最前提であり、Data Cloud においても厳格に適用されている ▶ Data Cloud の暗号化戦略： 保存時（At Rest）： データは AES 256ビットなどの暗号方式で暗号化され、物理メディアを含めてセキュアに保管される。 転送中（In Transit）： 通信は常に TLS（SSL） などの暗号化プロトコルを通じて行われ、傍受や改ざんを防止 このように、「保存時」と「転送中」の両方で暗号化を施すことで、包括的なセキュリティ対策が実現されている。 ❌ 他の選択肢の誤り： 選択肢 評価 理由 A. 保存時および転送中の暗号化 ✅ 正解 業界標準かつSalesforce公式で採用されている最も基本的な技術的対策 B. 同意の参照制御 ❌ 一部正しいが限定的 同意管理はプライバシー制御の一部だが、「セキュリティ確保の仕組み」とは異なる C. オフサイトサーバーに保存 ❌ 意味不明・不正確 オフサイト保存だけではセキュリティ対策とは言えず、データ保護の根拠がない D. 管理者にアクセス制限 ❌ 一部正しいが限定的 アクセス制御はセキュリティの一部だが、暗号化のような包括的な技術的対策ではない | J8: Salesforce.Data-Cloud-Consultant-JPN.v2024-09-12.q66 | K8: 49 | M8: *
B9: 127 | C9: ◯ | D9: 01_Data Cloud の概要 | E9: Data Cloud で対処できる 2 つの一般的なユースケースはどれですか? 2 つの答えを選択してください A. 顧客データを理解し、それに基づいて行動し、より関連性の高いエクスペリエンスを推進します。 B. 一元化された一連のポリシーとプロセスを通じて企業データのライフサイクルを管理します。 C. 標準化された拡張可能なデータ モデルを使用して、複数のソースからのデータを調和させます。 D. バックアップと災害復旧のための集中システムとして機能することで、重要なビジネス データを保護します。 | F9: A, C | G9: Data Cloudは、Salesforceおよび外部ソースを含む多様なデータソースからデータを接続、準備、統合、一元化、クエリ、分析、活用できるデータプラットフォームです。Data Cloudで対応可能な主なユースケースは以下の通りです： * 顧客データを理解し、より関連性の高い体験を提供するためのアクションを実行する。Data Cloudは、異なるソースからのデータを統合し、チャネル横断でのアイデンティティを解決することで、顧客の360度ビューを獲得するのを支援します。Data Cloudは、インサイトとAIを活用して顧客セグメンテーション、パーソナライズド体験の創出、あらゆるチャネルでのデータ活用を支援します。 * 複数のソースからのデータを標準化され拡張可能なデータモデルで調和させる。Data Cloudは、データの利用前に変換・クリーニングを行い、拡張・カスタマイズ可能な共通データモデルにマッピングします。また、計算されたインサイトや関連属性を生成し、データエンリッチメントとアイデンティティ解決の最適化を支援します。 他の2つのオプションは、データクラウドの一般的な使用ケースではありません。データクラウドはデータガバナンスやバックアップおよび災害復旧機能を提供しません。これらの機能は通常、Salesforceの他のソリューションまたは外部ソリューションで処理されます。 参考文献： * データクラウドの仕組みについて学ぶ * Salesforceデータクラウドについて * プラットフォームのユースケースを発見する * 一般的なデータ分析のユースケースを理解する | H9: A, C | I9: ◾ Data Cloud の目的と機能： Salesforce Data Cloud は、以下のようなユースケースを支援する **リアルタイムの顧客データプラットフォーム（CDP）**です： 顧客データの統合、標準化、分析、アクション化 リアルタイムでパーソナライズされた体験の提供 複数チャネル・システムにまたがるデータの調和・活用 ✅ 正解理由： 選択肢 解説 A. 顧客データを理解し、それに基づいて行動し、より関連性の高いエクスペリエンスを推進します。 ✅ Data Cloud の中核ユースケース。統合された顧客プロファイルを元に、セグメンテーション・アクティベーション・パーソナライゼーションを実現。 C. 標準化された拡張可能なデータ モデルを使用して、複数のソースからのデータを調和させます。 ✅ Data Cloud の特徴的な機能。データモデル（DMO）とマッピング機能を活用し、CRM・コマース・外部システムからのデータを調和。 ❌ 不正解の選択肢： 選択肢 理由 B. 一元化された一連のポリシーとプロセスを通じて企業データのライフサイクルを管理します。 ❌ これは**データガバナンスやマスター・データ管理（MDM）**の文脈であり、Data Cloud の主目的ではない。 D. バックアップと災害復旧のための集中システムとして機能することで、重要なビジネス データを保護します。 ❌ これはストレージや災害復旧（DR）システムの役割であり、Data Cloud は該当しない。 | J9: Salesforce.Data-Cloud-Consultant-JPN.v2024-09-12.q66 | K9: 6 | M9: *
B10: 137 | C10: ◯ | D10: 01_Data Cloud の概要 | E10: Northern Trail Outfitters は Data Cloud を実装したいと考えており、いくつかのユースケースを念頭に置いています。 Data Cloud に適していると考えられるユースケースはどれですか? 2つの回答を選択してください A. さまざまなソースからデータを取り込んで統合し、顧客のアイデンティティを調整する B. クロスチャネルマーケティングメッセージを作成し、調整する C. 調和されたデータを使用して、顧客とビジネスへの影響をより正確に理解する D. ビジネスインテリジェンスとITデータ管理ツールを別々に用意する必要がなくなる | F10: A, C | G10: Data Cloud は、Salesforce や外部のさまざまなソース間でデータの接続、準備、調整、統合、クエリ、分析、および操作を行うことができるデータ プラットフォームです。Data Cloud に適していると考えられるユース ケースには次のようなものがあります。 * さまざまなソースからデータを取り込んで統合し、顧客 ID を調整します。Data Cloud は、ストリーミングかバッチかを問わず、すべてのデータを Salesforce に取り込み、共通のデータ モデルにマッピングするのに役立ちます。また、Data Cloud は、さまざまなチャネルやソース間で ID を解決し、顧客の統合プロファイルを作成するのにも役立ちます。 * 調和されたデータを使用して、顧客とビジネスへの影響をより正確に把握します。Data Cloud は、お客様がデータを使用する前に変換およびクレンジングし、計算された洞察と関連属性でデータを充実させるのに役立ちます。また、Data Cloud は、お客様がデータに基づいてセグメントとオーディエンスを作成し、任意のチャネルでアクティブ化できるようにも支援します。Data Cloud は、お客様が AI を使用して顧客の行動と結果を予測できるようにも支援します。 他の 2 つのオプションは、Data Cloud に適したユースケースとは見なされません。Data Cloud には、クロスチャネル マーケティング メッセージを作成および調整する機能はありません。これは通常、Marketing Cloud などの他の Salesforce ソリューションによって処理されます。また、Data Cloud は、ビジネス インテリジェンス ツールや IT データ管理ツールと連携して機能を補完するように設計されているため、個別のビジネス インテリジェンス ツールや IT データ管理ツールが不要になるわけではありません。 参考文献: * データクラウドの仕組みを学ぶ * Salesforce Data Cloudについて * プラットフォームのユースケースを見つける * 一般的なデータ分析のユースケースを理解する | H10: A, C | I10: ◾ Data Cloud の目的： Salesforce Data Cloud は、主に以下を目的とした**リアルタイムの顧客データプラットフォーム（CDP）**です： さまざまなデータソースからの取り込みと統合 顧客IDの解決（Identity Resolution） プロファイルの構築と更新 セグメントの作成とアクティベーション 分析・パーソナライズ・予測アクションの実行 ✅ 正解理由の詳細： 選択肢 解説 評価 A. さまざまなソースからデータを取り込んで統合し、顧客のアイデンティティを調整する Data Cloud の主要な機能であり、複数のCRM、Web、店舗、アプリのデータを結合して、1人の顧客を一元化して理解する。 ✅ C. 調和されたデータを使用して、顧客とビジネスへの影響をより正確に理解する 統合された顧客プロファイルを使って、行動・購入傾向・LTVなどのインサイトを導出するのはData Cloudの本質的な価値。 ✅ ❌ 不正解の選択肢： 選択肢 理由 評価 B. クロスチャネルマーケティングメッセージを作成し、調整する メッセージの作成や配信はMarketing Cloudの機能。Data Cloudはそのパーソナライズや対象者特定のためのデータ基盤を担う。 ❌ D. ビジネスインテリジェンスとITデータ管理ツールを別々に用意する必要がなくなる Data Cloud はCDPでありBIツールの代替ではない。BI（例：Tableau）やデータ管理ツールは別に必要。 ❌ | J10: Salesforce.Data-Cloud-Consultant.v2024-12-02.q93 | K10: 45 | M10: *
B11: 187 | C11: ◯ | D11: 01_Data Cloud の概要 | E11: データクラウドの主な目的は何ですか? A. 顧客のゴールデンレコードの提供 B. 販売サイクルと機会の管理 C. マーケティングデータの結果の分析 D. 顧客データの統合と統一 | F11: D | G11: データクラウドの主な目的: * Salesforce Data Cloud の主な機能は、さまざまなソースからの顧客データを統合および統一し、各顧客の単一の包括的なビューを作成することです。 | H11: D | I11: ◾ Data Cloud の主な目的とは？ Salesforce Data Cloud（旧称：CDP = Customer Data Platform）の最大の価値は、 ✅ あらゆるチャネル・システムからの顧客データを統合・標準化し、単一ビュー（Unified Profile）を構築すること ✅ 正解理由： ▶ D. 顧客データの統合と統一 異なるソース（CRM、Web、モバイル、店舗など）からの断片的な顧客データを取り込み、 アイデンティティ解決（Identity Resolution）によって同一人物を認識し、 セグメンテーション、パーソナライズ、インサイト分析に活用できる 統合プロファイル（Unified Customer Profile） を生成。 これは Data Cloud の 中核的な目的です。 ❌ 他の選択肢の誤り： 選択肢 評価 理由 A. ゴールデンレコードの提供 ❌ ゴールデンレコードは MDM（Master Data Management） のコンセプト。Data Cloud は「マーケティング・体験向けの統合プロファイル」を提供するが、業務全体を支えるマスターデータの唯一性保証までは担わない。 B. 販売サイクルと機会の管理 ❌ これは Sales Cloud の役割。Data Cloud は営業活動の直接管理には使われない。 C. マーケティングデータの結果の分析 ❌ Data Cloud は 顧客データ基盤であり、分析は目的の一部だが主目的ではない。 | J11: Salesforce.Data-Cloud-Consultant.v2024-12-02.q93 | K11: - | M11: *
B12: 42 | C12: ◯ | D12: 01_Data Cloud の概要 | E12: 世界的なファッション小売業者は、AMFR、FMFA、APAC 全体でオンライン販売プラットフォームを運営しています。顧客、注文、製品情報のデータ形式は地域によって異なり、コンプライアンス規制では、元のデータ ソースでデータを変更せずに維持することが求められています。また、リアルタイムのパーソナライゼーションと分析のために、顧客プロファイルの統一されたビューも必要です。 これらの要件を考慮すると、企業は受信データ ストリームを標準化およびクレンジングするためにどのような変換アプローチを実装する必要がありますか? A. ストリーミング データ変換を実装します。 B. Data Cloud に取り込む前にデータを変換します。 C. バッチデータ変換を実装します。 D. Apex を使用してデータを変換およびクレンジングします。 | F12: A | G12: A. ストリーミング データ変換を実装します。 ソースによると、ストリーミング データ変換は「ほぼリアルタイムでデータを変換」するものであり、ソース DLO からターゲット DLO へとデータを書き込みます。これは、1 行のデータに対して動作し、ストリーミング プロセスとして継続的に実行され、新しいデータや変更されたデータをピックアップします。要件には「リアルタイムのパーソナライゼーションと分析」が含まれており、ストリーミング変換はリアルタイムまたはほぼリアルタイムの処理に適しています。また、データは Data Cloud に取り込まれて DLO となった後で変換されるため、元のソースデータは変更されずに維持されます。 B. Data Cloud に取り込む前にデータを変換します。 ソースが示す Data Cloud の標準的なデータ取り込みフローは、まずデータを Data Cloud に取り込み (DSO/DLO の作成)、その後データマッピングや変換を行います。Data Cloud に取り込む前にデータを変換することは、ソースデータが変更されてしまう可能性があり、「元のデータソースでデータを変更せずに維持」というコンプライアンス要件と矛盾する可能性があります。また、Data Cloud の価値の一つは、元の DLO を保持しつつ、それを基にさまざまな DMO を作成できる柔軟性にあるとも考えられます。 C. バッチデータ変換を実装します。 ソースによると、バッチデータ変換は「繰り返し可能なプロセス、スケジュールまたは手動でトリガー可能」であり、「フルリフレッシュ」に使用されると説明されています。これはデータ変換の一つの方法ですが、要件で求められている「リアルタイムのパーソナライゼーションと分析」には、バッチ処理よりもストリーミング処理の方が適しています。 D. Apex を使用してデータを変換およびクレンジングします。 ソース では、Apex が ConnectAPI.CDPQuery Apex クラス として、Data Cloud のデータへのアクセスやクエリ実行のために言及されています。しかし、データ ストリームから取り込まれたデータに対して、標準化やクレンジングのためのデータ変換を実行する主要なアプローチとして Apex が示されているわけではありません。Data Cloud には、データ変換のための組み込みツールやプロセスがあります。 これらの点を考慮すると、顧客、注文、製品情報を標準化およびクレンジングし、元のソースデータを変更せずに維持し、かつリアルタイムの要件を満たすためには、Data Cloud にデータを取り込んだ後に、ストリーミング データ変換を実装する というアプローチが、ソースの情報に最も合致していると考えられます。このアプローチにより、地域ごとに異なる形式のデータを Data Cloud 内で標準化された形式に変換し、統一されたプロファイル作成やリアルタイム分析に活用できるようになります。 したがって、ソースに基づいた回答は A. ストリーミング データ変換を実装します。 となります。 正解は A. ストリーミング データ変換を実装します。 | H12: A | I12: ◾ 問題の要点まとめ： グローバルに異なるフォーマットの顧客・注文・製品データを扱っている（AMER, EMEA, APAC） データは 元のソースで変更せずに維持する必要がある（＝元データを直接加工できない） 目的は： リアルタイムパーソナライゼーション 統一された顧客プロファイルビュー 分析対応 よって求められるのは： 🔸 リアルタイム性があり、かつデータをData Cloud内で正規化・整形できる変換処理 ✅ なぜ「A. ストリーミング データ変換」が正解か？ ストリーミングデータ変換とは、Salesforce Data Cloud において： データストリーム取り込み時にリアルタイムで変換・標準化処理を適用できる機能 変換例： 日付フォーマットの統一（MM-DD-YYYY → YYYY-MM-DD） テキストのクレンジング（例："M" → "Male"） 地域ごとの形式差の補正 ▶ 利点： 元データを変更せずに（＝コンプライアンス維持） Data Cloud内部でデータをクリーン・統一・構造化できる リアルタイム分析・パーソナライゼーションにも対応可能 ❌ 他の選択肢の誤り： 選択肢 評価 誤りの理由 B. Data Cloud に取り込む前に変換 ❌ 不正解 「元データを変更せずに維持する」という規制に反する可能性がある C. バッチデータ変換 ❌ 不正解 バッチはリアルタイムではなく、パーソナライゼーションには不向き D. Apex を使った変換 ❌ 不正解 Apex は Data Cloud では使えず、Core Salesforce（CRM）内での処理手段であり不適切 | J12: Salesforce.Data-Cloud-Consultant-JPN.v2025-03-28.q66 | K12: - | M12: *
B13: 107 | C13: ◯ | D13: 01_Data Cloud の概要 | E13: Data Cloud は個人の忘れられる権利をどのように処理しますか? A. すべてのデータ ソース オブジェクトからレコードを削除し、ダウンストリーム データ モデル オブジェクトは次にスケジュールされた取り込み時に更新されます。 B. 指定された個別レコードとその統合個別リンク レコードを削除します。 C. 指定された個人とレコードを、個人データ モデル オブジェクトにマップされたデータ ソース オブジェクトから削除します。 D. 指定された個人と、その個人に関連するデータ モデル オブジェクト/データ レイク オブジェクトからレコードを削除します。 | F13: D | G13: Data Cloudは、個人の「忘れられる権利」を履行するため、指定された個人およびその個人に関連するすべてのデータモデルオブジェクト/データレイクオブジェクトから個人と関連する記録を削除します。これにより、Data Cloudはデータスペースから個人に関連するすべてのデータを削除します。これには、ソースオブジェクトからのデータ、統合された個人プロファイル、および関連するオブジェクトが含まれます。Data Cloudは、個人とソースレコードをリンクする統合個人リンクレコードも削除します。Data Cloudは、忘れられる権利の請求を処理するためにConsent APIを使用し、完全な削除を保証するために30日、60日、90日後に再処理されます。 他のオプションは、Data Cloudが個人の忘れられる権利を処理する方法の正しい説明ではありません。Data Cloudは、すべてのデータソースオブジェクトからレコードを削除しません。これは、ソースシステムのデータ整合性と可用性に影響を与えるためです。Data Cloudはまた、指定された個人レコードとその統一個人リンクレコードのみを削除しません。これは、ソースレコードと関連レコードがそのまま残るためです。Data Cloudは、個人データモデルオブジェクトにマッピングされたデータソースオブジェクトから指定された個人とレコードのみを削除しません。これは、関連レコードがそのまま残るためです。 参照： * データ削除または忘れられる権利の請求 * Data Cloudでのデータ削除 * Data CloudでConsent APIを使用する * Data Cloudにおけるデータとアイデンティティ | H13: D | I13: ◾ 忘れられる権利（Right to Be Forgotten）とは？ GDPRなどのプライバシー規制に基づき、個人は自身のデータを削除するよう組織に求めることができます。 Salesforce Data Cloud では、**「同意管理（Consent Management）」および「削除リクエスト」**を通じてこれを処理します。 ✅ 正解理由： ▶ Data Cloud における削除の仕組み： Data Cloud は「指定された個人（Individual）」と、 その個人に 関連付けられたすべての DMO（データモデルオブジェクト）や DLO（データレイクオブジェクト） からレコードを削除します。 これは以下を含みます： 統合プロファイル（Unified Individual） 個人に関連付けられた購入履歴、エンゲージメントデータなどの DLO/DMO情報 ❌ 他の選択肢の誤り： 選択肢 評価 誤りの理由 A. データソースオブジェクトのみ削除 ❌ データソースオブジェクトは外部連携の取り込み元。削除範囲が不十分 B. Individual と統合リンクのみ削除 ❌ リンクだけでなく、関連データ（注文・接点など）も削除が必要 C. Individual とそのソースデータだけ削除 ❌ 同様に、DMO/DLO からの削除も必要であり、範囲が限定的すぎる D. Individual + 関連DMO/DLOを削除 ✅ 正しいスコープと仕組みを説明している | J13: Salesforce.Data-Cloud-Consultant-JPN.v2024-09-12.q66 | K13: - | M13: *
B14: 210 | C14: ◯ | D14: 01_Data Cloud の概要 | E14: Data Cloud は個人の忘れられる権利をどのように扱いますか? A. すべてのデータソースオブジェクトからレコードを削除し、下流のデータモデルオブジェクトは次回のスケジュールされた取り込み時に更新されます。 B. 指定された個別レコードとその統合個別リンクレコードを削除します。 C. 指定された個人と、個人データ モデル オブジェクトにマップされたすべてのデータ ソース オブジェクトからのレコードを削除します。 D. 指定された個人と、その個人に関連するすべてのデータ モデル オブジェクト/データ レイク オブジェクトからレコードを削除します。 | F14: D | G14: Data Cloud は、指定された個人と、個人に関連するすべてのデータ モデル オブジェクト/データ レイク オブジェクトからレコードを削除することで、個人の忘れられる権利を処理します。つまり、Data Cloud は、ソース オブジェクト、統合された個人プロファイル、および関連オブジェクトのデータを含む、個人に関連付けられたすべてのデータをデータ スペースから削除します。Data Cloud は、個人をソース レコードにリンクする統合された個人リンク レコードも削除します。Data Cloud は、Consent API を使用して忘れられる権利のリクエストを処理します。このリクエストは、完全な削除を確実にするために 30 日、60 日、90 日で再処理されます。 その他のオプションは、Data Cloud が個人の忘れられる権利をどのように処理するかについて正しく説明していません。Data Cloud は、ソース システムのデータの整合性と可用性に影響するため、すべてのデータ ソース オブジェクトからレコードを削除することはありません。また、Data Cloud は、指定された個人レコードとその統合個人リンク レコードのみを削除することもありません。そうすると、ソース レコードと関連レコードがそのまま残るからです。また、Data Cloud は、指定された個人と、個人データ モデル オブジェクトにマップされたデータ ソース オブジェクトからのレコードのみを削除することもありません。そうすると、関連レコードがそのまま残るからです。 参考文献: * データ削除または忘れられる権利の要求 * データクラウドのデータ削除 * Data CloudでConsent APIを使用する * データクラウドにおけるデータとアイデンティティ | H14: D | I14: ◾ 背景： Salesforce Data Cloud は、GDPR（General Data Protection Regulation） や CCPA などのデータプライバシー規制に対応するため、 顧客からの 「忘れられる権利（Right to be Forgotten）」 に基づく削除リクエストを受け付け、個人の全データを削除する機能を提供しています。 ✅ 正解理由： ▶ 「忘れられる権利」の対応とは： 指定された**個人（Individual）**に関連付けられたすべてのデータ（例：行動履歴・トランザクション・プロフィールなど）を削除。 削除対象は、Data Model Object（DMO） や Data Lake Object（DLO） など、 Data Cloud 内のあらゆるデータ構造に渡る。 これはData Subject Rights（DSR）ツールまたはAPIから実行可能で、 一度実行されると、セグメントやアクティベーションにもその個人は含まれなくなる。 ❌ 他の選択肢の誤り： 選択肢 評価 理由 A. データソースオブジェクトのみ削除 ❌ ソースのみ削除しても、Data Cloud 内のモデル／統合データにコピーが残り続ける。完全削除ではない。 B. 統合リンクレコードの削除のみ ❌ 統合リンク（Identity解決のリンク）を削除しても、個人データ自体が削除されるわけではない。 C. 個人と個人DMOのみ削除 ❌ 個人の「行動データ」や「購買履歴」など、DMOやDLOにまたがるデータは削除対象外となり不完全。 📝 補足： 対応手段 説明 DSRツール UIから個人指定で削除リクエストが可能 API（Data Subject API） 外部システムからプログラム的にリクエスト送信 削除範囲 Individual、Event、Purchase、Engagement 等すべての関連レコード | J14: Salesforce.Data-Cloud-Consultant.v2024-12-02.q93 | K14: 107 | M14: *
B15: 39 | C15: ◯ | D15: 01_Data Cloud の概要 | E15: ノーザン トレイル クットフィッターズは、各顧客の生涯価値 (LTV) を計算できるだけでなく、ウェブサイト、モバイル アプリ、および小売チャネルから得られる収益の内訳も作成できるようにしたいと考えています。 Data Cloud でこのユースケースに対処するためにコンサルタントは何を使用する必要がありますか? A. フロー オーケストレーション B. ネストされたセグメント C. メトリック上のメトリック D. ストリーミング データ変換 | F15: C | G15: メトリクス上のメトリクスは、既存のメトリクスを基に新しいメトリクスを作成し、それらに数学的な演算を適用する機能です。この機能は、LTV、ROI、コンバージョン率などの複雑なビジネスメトリクスの計算に役立ちます。例えば、コンサルタントはメトリクス上のメトリクスを使用して、各顧客のLTVを、彼らが異なるチャネルで生成した収益を合計することで計算できます。また、メトリクスの定義でチャネル属性を次元として使用することで、チャネル別の収益の内訳を作成することも可能です。参照： メトリクス上のメトリクス、メトリクス上のメトリクスの作成 | H15: C | I15: ◾ 問題の要点： Northern Trail Outfitters は、次の2つの要素を Data Cloud 上で実現したい： 顧客ごとの LTV（生涯価値） の計算 Web、アプリ、店舗など複数チャネルからの収益内訳の可視化 この要件には、複数のチャネルから得られる収益情報を組み合わせて分析する能力が必要です。 ✅ 正解理由：「メトリック上のメトリック（Metrics on Metrics）」とは？ これは Calculated Insights（CI） の高度な活用法の一種で、 1つの集計（メトリック）をベースに、さらに新たな集計を作成できる機能です。 たとえば： 各チャネル別に計算した売上（Web、アプリ、店舗）を基に、 顧客ごとの 合計LTV を計算したり チャネル別比率を求めたりできる これにより、LTVの構成要素を明確に分解して可視化・分析することが可能になります。 ❌ 他の選択肢の誤り： 選択肢 評価 理由 A. フロー オーケストレーション ❌ 不正解 フローはプロセス自動化ツールであり、LTVや収益分析には使わない B. ネストされたセグメント ❌ 不正解 セグメントの条件を入れ子にする構造。LTV計算などの数値集計には不向き C. メトリック上のメトリック ✅ 正解 複数の収益メトリックを組み合わせてLTVを算出できる唯一の正解 D. ストリーミングデータ変換 ❌ 不正解 データの取り込み変換に関する処理であり、集計や可視化には関係しない | J15: Salesforce.Data-Cloud-Consultant-JPN.v2025-03-28.q66 | K15: - | M15: *
B16: 153 | C16: ◯ | D16: 01_Data Cloud の概要 | E16: Northern Trail Qutfitters は、各顧客の生涯価値 (LTV) を計算できるだけでなく、Web サイト、モバイル アプリ、小売チャネルから得られる収益の内訳も作成したいと考えています。 コンサルタントは、Data Cloud でこのユースケースに対処するために何を使用すればよいでしょうか? A. フローオーケストレーション B. ネストされたセグメント C. メトリクス上のメトリクス D. ストリーミングデータ変換 | F16: C | G16: メトリクス オン メトリクスは、既存のメトリクスに基づいて新しいメトリクスを作成し、それらに数学的演算を適用できる機能です。これは、LTV、ROI、コンバージョン率などの複雑なビジネス メトリクスを計算するのに役立ちます。この場合、コンサルタントはメトリクス オン メトリクスを使用して、さまざまなチャネルで顧客が生み出した収益を合計することで、各顧客の LTV を計算できます。コンサルタントは、チャネル属性をメトリクス定義のディメンションとして使用して、チャネル別の収益の内訳を作成することもできます。参照: メトリクス オン メトリクス、メトリクス オン メトリクスの作成 | H16: C | I16: Northern Trail Outfitters は次の2つの要件を持っています： 各顧客の 生涯価値（LTV: Lifetime Value） を算出したい その LTV を チャネル別（Webサイト／モバイルアプリ／店舗）に内訳したい これは、顧客単位の売上をチャネル別に集計・分析するという、高度な集約ロジックの構築を意味します。 ✅ 正解理由： ▶ C. メトリクス上のメトリクス（Metrics on Metrics） Salesforce Data Cloud の **「計算された洞察（Calculated Insights）」**では、集約済みの指標をさらに集計する機能として「メトリクス上のメトリクス（Metrics on Metrics）」が提供されています。 これにより以下が可能になります： 各チャネルごとの購入金額を個人単位で集計 それらを加算して LTV を算出 LTV の中でチャネル別の構成比を分析（＝内訳） ❌ 他の選択肢の誤り： 選択肢 評価 理由 A. フローオーケストレーション ❌ ワークフローの順次処理の制御ツールであり、数値集計や洞察分析には不向き。 B. ネストされたセグメント ❌ セグメント同士の条件ネストは可能だが、数値計算やチャネル別内訳分析はできない。 D. ストリーミングデータ変換 ❌ データのリアルタイム整形・変換に使うが、LTVや内訳のような履歴集計・分析には不適。 | J16: Salesforce.Data-Cloud-Consultant.v2024-12-02.q93 | K16: 39 | M16: *
B17: 2 | C17: ◯ | D17: 01_Data Cloud の概要 | E17: 組織は、ユーザーがオプションの選択リストからテキスト属性を識別して選択できるようにしたいと考えています。 このユースケースではどのデータ クラウド機能が役立つでしょうか? A. 値の提案 B. データの調和 C. 変換式 D. グローバル選択リスト | F17: A | G17: 値提案は、データクラウドの機能で、セグメントフィルターを作成する際、テキストフィールドの可能な値を表示し選択できる機能です。値提案は、DMOレコードのホーム画面で、各データモデルオブジェクト（DMO）フィールドに対して有効または無効に設定できます。値提案は、ユーザーがオプションのリストからテキスト属性を選択する際、正確な値を入力したり記憶したりする必要なく、値を特定して選択するのに役立ちます。また、セグメントフィルターに一貫性があり有効な値を保証することで、エラーを削減しデータ品質を向上させます。参照： セグメンテーションでの値提案の使用、関連属性の選択に関する考慮事項 | H17: A | I17: ◾ 問題文の要点： 組織は、ユーザーがオプションの選択リストからテキスト属性を識別して選択できるようにしたい。 これは、ユーザーが入力する際に候補値が提示されることで、 入力ミスを防ぎ 一貫した属性値を使い 効率的に作業ができるようにする といったユースケースです。 値の提案（Suggested Values） Data Cloudの属性フィールドに対して、既存データに基づいた代表的な値（候補値）を自動提示する機能。選択肢から選べるようにするというユースケースにマッチ。 「値の提案」機能は、Data Cloudでテキスト属性フィールドに対して動的に推奨値を提示できる唯一の選択肢です。 この機能により、マーケターやオペレーターが過去の傾向に基づいた一貫した入力を行えるようになります。 | J17: Salesforce.Data-Cloud-Consultant-JPN.v2025-03-28.q66 | K17: - | M17: *
B18: 22 | C18: ◯ | D18: 01_Data Cloud の概要 | E18: Salesforce Data Cloud の典型的な使用例は何ですか? A. Salesforce エコシステム全体でのデータ同期 B. パーソナライズされたメールを大規模に送信する C. CRMデータをPromiseに保存する D. 複数のプラットフォーム間でのデータの調和 | F18: D | G18: - | H18: D | I18: ◾ Salesforce Data Cloud（旧 CDP）の主な目的： Salesforce Data Cloud は、複数のデータソースからの顧客データをリアルタイムで統合・標準化（調和）し、1つの統合顧客プロファイル（Unified Profile）を作成するためのプラットフォームです。 その中心的な機能は以下の通り： データ調和（Harmonization）：複数のCRM、EC、POS、アナリティクスなどからのデータを共通モデルに整形 ID解決（Identity Resolution）：顧客の断片的な情報を1人の個人として統合 リアルタイムセグメンテーション：マーケティングや営業で即座に活用 パーソナライゼーションやアクティベーション：広告やメール配信、提案などに連携 ■ 各選択肢の評価： 選択肢 評価 理由 A. Salesforce エコシステム全体でのデータ同期 ❌ 不正解 Data Cloud は統合・分析に特化しており、同期エンジン（例：Salesforce Connect、MuleSoft）ではない B. パーソナライズされたメールの送信 ❌ 部分的には関連 実際に送信するのは Marketing Cloud。Data Cloud はセグメントや属性の提供元 C. CRMデータをPromiseに保存 ❌ 不正解 "Promise" という保存領域は存在しない。無関係な表現 D. 複数プラットフォーム間のデータの調和 ✅ 正解 まさに Data Cloudの中心機能。「Harmonization」とも呼ばれる | J18: Salesforce.Data-Cloud-Consultant-JPN.v2025-03-28.q66 | K18: - | M18: *
B19: 46 | C19: ◯ | D19: 01_Data Cloud の概要 | E19: ノーザン トレイル アウトフィッターズは、Marketing Cloud データの一部を Data Cloud で使用したいと考えています。 どのエンゲージメント チャネル データにカスタム統合が必要ですか? A. SMS B. 電子メール C. クラウドページ D. モバイルプッシュ | F19: C | G19: CloudPageは、Marketing Cloudでホストされ、カスタマイズ可能なウェブページです。これは、Data Cloudが標準でサポートするエンゲージメントチャネルの一つではありません。Data CloudでCloudPageのデータを使用するには、カスタム統合が必要です。その他のエンゲージメントチャネル（SMS、メール、モバイルプッシュ）はData Cloudでサポートされており、Marketing Cloud ConnectorまたはMarketing Cloud APIを使用して統合できます。参照：Data Cloudの概要、Marketing Cloud Connector、Marketing Cloud API | H19: C | I19: ◾ 問題の背景： ノーザン トレイル アウトフィッターズは、Marketing Cloud にあるエンゲージメントチャネルのデータを Salesforce Data Cloud で活用したい。 そのうち「どのチャネルのデータにはカスタム統合が必要か？」を問う問題です。 ✅ 正解理由：「CloudPages」データにはカスタム統合が必要 ▶ CloudPagesとは： Marketing Cloud の ランディングページ作成・ホスト機能 主に Webフォーム、キャンペーンページ、アンケートなどのデジタル体験提供に使われる ▶ なぜカスタム統合が必要か？ CloudPages の利用データ（閲覧履歴、フォーム入力など）は標準では Data Cloud に取り込まれない そのため、CloudPagesのログやインタラクションデータを 個別に ETL処理や API連携で Data Cloud に取り込む必要がある Salesforce が提供する 標準のMC連携（Connect）ではサポートされていない ❌ 他の選択肢の誤り： 選択肢 評価 理由 A. SMS ❌ 不正解 SMS送信データは 標準のMarketing Cloud連携で自動連携可能 B. 電子メール ❌ 不正解 電子メールのオープン・クリック・バウンス等は Marketing Cloud連携で自動でData Cloudへ送信可能 C. クラウドページ ✅ 正解 唯一、標準連携では連携されないエンゲージメントチャネル。 カスタム統合が必要 D. モバイルプッシュ ❌ 不正解 モバイルプッシュのインタラクションデータも Marketing Cloudとの連携で取得可能（MobilePushとData Cloudは接続可） | J19: Salesforce.Data-Cloud-Consultant-JPN.v2025-03-28.q66 | K19: - | M19: *
B20: 73 | C20: ◯ | D20: 01_Data Cloud の概要 | E20: 顧客にとってのデータクラウドの主な価値は何ですか? A. 顧客とその関連データの統合ビューを提供するため B. すべてのシステムをゴールデン レコードで接続するには C. すべての匿名データに対する単一の信頼できる情報源を作成するには D. 顧客の行動を聞き、理解し、それに基づいて行動することで、パーソナライズされたキャンペーンを作成するため | F20: A | G20: Data Cloudは、Salesforceアプリケーションおよび他のシステム全体で顧客データを有効活用できるプラットフォームです。Data Cloudは、CRM、マーケティング、コマース、サービス、外部データプロバイダーなど、多様なソースからデータを収集、変換、連携することで、各顧客の統一されたプロファイルを作成できます。また、顧客の行動、好み、ニーズに関する洞察と分析を提供し、顧客セグメンテーション、ターゲティング、パーソナライズされた顧客インタラクションを実現するためのツールも備えています。Data Cloudの顧客への主な価値は、顧客とその関連データを統一されたビューで提供することです。これにより、より良い顧客体験の提供、ロイヤルティの向上、成長の促進が可能になります。参照：Salesforce Data Cloud、データが競争優位性を生むとき | H20: A | I20: Data Cloudが顧客にとって提供する主な価値についてのご質問ですね。ソース資料に基づき、この価値を最もよく表している選択肢とその理由をご説明します。 提示された選択肢は以下の通りです。 A. 顧客とその関連データの統合ビューを提供するため B. すべてのシステムをゴールデン レコードで接続するには C. すべての匿名データに対する単一の信頼できる情報源を作成するには D. 顧客の行動を聞き、理解し、それに基づいて行動することで、パーソナライズされたキャンペーンを作成するため ソース資料によると、Data Cloudの主要な目的と価値は、顧客データを統合して単一のビューを作成し、それに基づいて顧客をより深く理解し、リアルタイムデータなどを用いて行動を起こし、パーソナライズされた顧客体験を創出することにあります | J20: Salesforce.Data-Cloud-Consultant-JPN.v2024-09-12.q66 | K20: - | M20: *
B21: 79 | C21: × | D21: 01_Data Cloud の概要 | E21: 顧客とのプライバシー法に関する議論の際、顧客は忘れられる権利の要求を尊重する必要があると述べました。コンサルタントは、Consent API がこのビジネス ニーズを解決すると判断しました。 コンサルタントが顧客に通知すべき 2 つの考慮事項はどれですか? 2 つの答えを選択してください A. データ削除リクエストは 30、60、90 日後に再処理されます。 B. データ削除リクエストは 1 時間以内に処理されます。 C. データ削除リクエストは個別のプロファイルに対して送信されます。 D. Data Cloud に送信されたデータ削除リクエストは、接続されているすべての Salesforce クラウドに渡されます。 | F21: C, D | G21: SalesforceのConsent APIを使用して「忘れられる権利」の請求に対応する際、顧客にアドバイスする際は、以下の2つの主要な点を重点的に説明する必要があります： * データ削除請求は個人プロファイルに対して提出されます（回答C）：SalesforceのConsent APIは、個人プロファイルに関するデータ削除請求を処理するように設計されています。つまり、データ削除の請求が提出されると、Salesforceシステム内の個人のプロファイルに紐付いた個人データが対象となります。コンサルタントは、正確な処理とプライバシー法への準拠を確保するため、リクエストは個人プロファイルに限定する必要があることを顧客に伝える必要があります。 * Data Cloudに提出されたデータ削除リクエストは、すべての接続されたSalesforceクラウドに伝播されます（回答D）：Salesforce Data CloudのConsent APIを通じてデータ削除リクエストが提出された場合、そのリクエストはData Cloudに限定されません。代わりに、Sales Cloud、Service Cloud、Marketing Cloudなど、接続されたすべてのSalesforceクラウドに伝播されます。これにより、Salesforceエコシステム全体で「忘れられる権利」への包括的な準拠が確保されます。顧客は、削除リクエストが接続されたSalesforce環境内の個人のデータすべてのインスタンスに影響を与えることを認識する必要があります。 | H21: C, D | I21: ◾ 問題の背景： 顧客は「忘れられる権利（Right to be Forgotten）」＝GDPRなどのプライバシー法に準拠したデータ削除リクエストを尊重したいと考えており、 コンサルタントはこのニーズに対して Salesforce Data Cloud の Consent API を使用すべきと判断しました。 ✅ 正解の理由： ▶ B. データ削除リクエストは 1 時間以内に処理されます。 Consent API 経由で送信された削除リクエストは、原則として 1 時間以内に自動処理されるとドキュメントに記載されています。 これにより、ほぼリアルタイムに削除フローが動作することを顧客に説明できます。 ▶ C. データ削除リクエストは個別のプロファイルに対して送信されます。 Consent API は 個人単位（= 個別プロファイル / Individual） に対して使用されます。 リクエストには、対象となる 統合IDや識別情報（例：Email, IDなど） を含める必要があります。 ❌ 他の選択肢の誤り： 選択肢 評価 理由 A. 30、60、90日後に再処理される ❌ 不正確 Data Cloud における削除は 基本的に一度で完結。スケジュールされた再処理はありません。 D. 接続されたすべての Salesforce クラウドに削除される ❌ 誤り Consent API の削除リクエストは Data Cloud 内のデータに限定され、Salesforce CRM や Marketing Cloud などには自動伝播されません。別途対応が必要。 | J21: Salesforce.Data-Cloud-Consultant-JPN.v2024-09-12.q66 | K21: - | M21: *
B22: 81 | C22: ◯ | D22: 01_Data Cloud の概要 | E22: Data Cloud はどのようにして顧客データの高可用性とフォールト トレランスを確保するのでしょうか? A. 複数の地域やデータセンターにデータを分散することで B. 堅牢なバックアップを備えたデータセンターを使用することで C. 自動データ復旧手順を実装することにより D. データへのアクセスを重要な担当者に制限することで | F22: A | G22: 高可用性と障害耐性の確保： * 高可用性とは、システムが継続的に動作し、アクセス可能な状態を維持することを指します。一方、障害耐性とは、障害が発生した場合でも機能を継続する能力を指します。 | H22: A | I22: ◾ 問題の本質： Data Cloud（旧 Customer Data Platform）は、顧客データを常に利用可能に保ちつつ、障害が発生しても迅速に復旧できるよう、**高可用性（HA）とフォールトトレランス（FT）**を保証する設計が必要です。 → このような可用性と耐障害性は、どのように実現されているかを問う問題です。 ✅ 正解理由：「地理的に分散されたデータセンターによる冗長構成」が HA/FT の基本戦略 ▶ Salesforce Data Cloud は： グローバルなマルチリージョン設計を採用しており、 顧客データは 複数の物理リージョン（地域）とデータセンターに分散保存されます。 これにより、1つのデータセンターやリージョンに障害が発生しても： 別のリージョンから継続的にサービス提供が可能（高可用性） データの損失リスクを最小限に抑えられる（フォールトトレランス） ❌ 他の選択肢の誤り： 選択肢 評価 理由 A. 地域・データセンターへの分散 ✅ 正解 クラウドインフラでの標準的な高可用性設計。Salesforceもこの戦略を採用 B. 堅牢なバックアップを使う ❌ 不十分 バックアップは災害復旧の手段であり、リアルタイムの可用性確保には不十分 C. 自動データ復旧手順 ❌ 一部正しいが限定的 復旧は事後対策であり、可用性維持の“予防”にはならない D. アクセス制限 ❌ 無関係 アクセス制御はセキュリティであり、可用性や冗長性とは無関係 | J22: Salesforce.Data-Cloud-Consultant-JPN.v2024-09-12.q66 | K22: - | M22: *
B23: 96 | C23: ◯ | D23: 01_Data Cloud の概要 | E23: Cloud Kicks は、顧客から忘れられるようにというリクエストを受け取りました。 このリクエストに応えるために、コンサルタントはデータ クラウドをどの 2 つの方法で使用する必要がありますか? 2 つの答えを選択してください A. 受信データ ストリームからデータを削除し、完全な更新を実行します。 B. 個別 ID をヘッダーなしファイルに追加し、ファイルから削除機能を使用します。 C. データ エクスプローラーを使用して個人を見つけ、手動で削除します。 D. 同意 API を使用して処理を抑制し、ソース データ ストリームから個人レコードと関連レコードを削除します。 | F23: B, D | G23: 顧客からの「忘れられる権利」の請求に対応するため、コンサルタントはData Cloudを以下の2つの方法で使用する必要があります： * ヘッダーのないファイルに個人IDを追加し、ファイルからの削除機能を使用します。このオプションでは、コンサルタントがCSVファイルにIDを記載してアップロードすることで、Data Cloudから複数の個人データを削除できます1。削除処理は非同期で行われ、完了まで最大24時間かかる場合があります1。 * Consent APIを使用して処理を抑制し、個人および関連レコードをソースデータストリームから削除します。このオプションでは、コンサルタントはConsent APIを使用してData Cloud内の個人プロファイルに対してデータ削除リクエストを送信できます2。データ削除リクエストは、指定された個人エンティティおよびそのエンティティの識別属性と個人ID属性との間で関係が定義されているすべてのエンティティを削除します2。削除プロセスは、完全な削除を保証するために30日、60日、90日に再実行されます2。他のオプションは正しくない理由は： * 入力データストリームからデータを削除し、完全なリフレッシュを実行しても、Data Cloud内の既存データは削除されず、ソースシステムからの新規データのみが削除されます3。 * Data Explorerを使用して個人を特定し手動で削除しても、ソースデータストリーム内の関連レコードは削除されず、Data Cloud内の個人エンティティのみが削除されます。参照： * Data Cloudから個人を削除する * データ削除または忘れられる権利の請求 * Data Cloudのデータリフレッシュ * ［Data Explorer］ | H23: B, D | I23: ◾ 問題の背景： Cloud Kicks は顧客から「忘れられる権利（Right to be Forgotten）」に基づいた削除依頼を受けています。 このようなリクエストに対応するには、Salesforce Data Cloud 上から個人データを適切かつ安全に削除・抑制する必要があります。 ✅ 正解理由と処理方法： ▶ B. ヘッダーなしファイルで削除（ファイルベース削除） Data Cloud では **「ファイルから削除（Delete from File）」**機能を使って、 個別 ID をリスト形式でアップロードし、対象レコードを削除可能。 このとき、ファイルは通常 ヘッダーなし（IDのみのリスト） で作成される。 ▶ D. 同意 API（Consent API）による抑制・削除 Consent API を使えば、**プログラム的にユーザーの「削除」「処理の制限」**を指定できる。 これは 自動化対応や法規制への準拠（例：GDPR） に非常に重要。 ❌ 他の選択肢の誤り： 選択肢 評価 誤りの理由 A. データストリームから削除して完全更新 ❌ ストリームの削除・再作成は 非効率かつ残留リスクがあるため非推奨 C. データエクスプローラーで手動削除 ❌ 一時的な確認には使えるが、GDPRや大量処理には不適・証跡も残らないため不十分 | J23: Salesforce.Data-Cloud-Consultant-JPN.v2024-09-12.q66 | K23: - | M23: *
B24: 100 | C24: ◯ | D24: 01_Data Cloud の概要 | E24: 信頼ベースのファーストパーティ データ資産を構築するとはどういう意味ですか? A. データの使用に同意し、その対価として価値を受け取る個人から収集したデータの透明性とセキュリティを提供するため B. すべてのコンプライアンス規制に従って、信頼できるファーストパーティ データを Data Cloud Marketplace に提供するため C. 法律で義務付けられているすべての電子メール マーケティングに対してオプトイン同意が確実に収集されるようにするため D. インタビュー、調査、世論調査を通じて信頼できる情報源から競合データを入手するため | F24: A | G24: 信頼に基づく第一者データ資産を構築するとは、顧客や見込み客からデータを収集し、管理し、活用する際に、彼らのプライバシーと好みを尊重する方法を意味します。また、データの利用方法、データ共有によるメリット、データ管理の方法について、明確で正直な情報を提供することも含まれます。これにより、顧客との相互に利益となる関係を築くことができます。顧客は、自社のデータを責任を持って倫理的に利用する信頼を寄せ、より関連性が高くパーソナライズされた体験を提供できます。信頼に基づくファーストパーティデータ資産は、顧客の忠誠心、離反防止、成長の向上に加え、データ保護規制や基準への準拠にも役立ちます。参考文献：ファーストパーティデータを活用した強力なデジタル体験、ファーストパーティデータがデータプライバシーの鍵となる理由、ファーストパーティデータ戦略の構築 | H24: A | I24: ◾「信頼ベースのファーストパーティ データ資産」とは？ これは、以下のような 顧客中心のアプローチで構築されたデータ資産 を意味します： 企業が 直接、本人から収集したデータ（ファーストパーティデータ） その収集・利用には、同意（コンセント） が取得されており、 顧客に対して「データ利用の透明性」「価値の提供（パーソナライズ、特典など）」が確保されている つまり、“信頼”に基づいて、顧客と価値を交換しながらデータを取得・利用する形です。 ✅ Salesforce や業界での定義： Salesforce の Data Cloud や CDP のドキュメントでは、 "Building a trusted first-party data asset means collecting consented data transparently, and using it to provide better experiences to your customers." ❌ 他の選択肢の誤り： 選択肢 評価 誤りの理由 A. ✅ 最も正確な定義。透明性、同意、顧客への価値提供を含む B. ❌ Data Cloud Marketplace は データ販売の話であり、「資産構築」ではない C. ❌ メール同意だけに限定しており、文脈が狭すぎる D. ❌ 競合データ（＝サードパーティデータ）であり、ファーストパーティの信頼資産とは無関係 | J24: Salesforce.Data-Cloud-Consultant-JPN.v2024-09-12.q66 | K24: - | M24: *
B25: 102 | C25: ◯ | D25: 01_Data Cloud の概要 | E25: 顧客にとって Data Cloud の主な価値は何ですか? A. すべての匿名データのための唯一の真実のソースを作成する B. 顧客の行動に耳を傾け、理解し、行動することでパーソナライズされたキャンペーンを作成する C. すべてのシステムをゴールデンレコードで接続する D. 顧客と関連データの統合ビューを提供する | F25: D | G25: Data Cloudは、Salesforceアプリケーションおよび他のシステム全体で顧客データを統合し活用できるプラットフォームです。Data Cloudは、CRM、マーケティング、コマース、サービス、外部データプロバイダーなど、多様なソースからデータを収集、変換、連携することで、各顧客の統一されたプロファイルを作成できます。また、顧客の行動、好み、ニーズに関する洞察と分析を提供し、顧客セグメンテーション、ターゲティング、パーソナライズされた顧客インタラクションを実現するためのツールも備えています。Data Cloudの顧客への主な価値は、顧客とその関連データを統合したビューを提供することです。これにより、より良い顧客体験の提供、ロイヤルティの向上、成長の促進が可能になります。参照：Salesforce Data Cloud、データが競争優位性を生み出すとき | H25: D | I25: ◾ 解説： Salesforce Data Cloud の主な価値は、複数のシステムやチャネルから収集された顧客データを統合し、**一貫性のある 360 度の顧客ビュー（統合プロファイル）**を提供することです。 これにより企業は以下を実現できます： 顧客の全体像を把握し マーケティング、営業、サービスで活用し よりパーソナライズされた対応が可能になる ✅ 正解理由：D. 顧客と関連データの統合ビューを提供する Data Cloud は断片化されたデータを統合し、1人の顧客に関するすべての情報（行動・属性・関係性など）をひとつのビューで表示できるようにします。 これが他のクラウドや分析、キャンペーンにおける出発点となる価値です。 ❌ 他の選択肢の誤り： 選択肢 誤りの理由 A. すべての匿名データのための唯一の真実のソースを作成する ❌ Data Cloud は主に識別可能な顧客データを扱います。匿名データ特化ではない。 B. パーソナライズされたキャンペーンを作成する ❌ 確かに重要なユースケースですが、それは「統合ビュー」の次の活用ステップであり、主目的ではありません。 C. ゴールデンレコードで接続する ❌ 「ゴールデンレコード」は MDM（マスターデータ管理）の用語であり、Data Cloud の範疇とは異なります。Data Cloud は最も信頼できる単一ビューを提供しますが、マスターではありません。 📝 まとめ | 主な価値 | ✔️ 顧客と関連データの統合ビューを提供する | | 間接的な価値 | パーソナライズ、キャンペーン強化、レポート改善など | | 主に扱うデータ | 識別可能なファーストパーティデータ（＋エンゲージメント） | | J25: Salesforce.Data-Cloud-Consultant-JPN.v2024-09-12.q66 | K25: 73 | M25: *
B26: 142 | C26: ◯ | D26: 01_Data Cloud の概要 | E26: 信頼に基づくファーストパーティ データ資産を構築するとはどういう意味ですか? A. 使用に同意し、その見返りに価値を受け取る個人から収集したデータの透明性とセキュリティを確保するため B. すべてのコンプライアンス規制に準拠した、信頼できるファーストパーティデータをデータクラウドマーケットプレイスで提供する C. 法律で義務付けられているすべての電子メールマーケティングでオプトインの同意が収集されるようにするため D. インタビュー、アンケート、世論調査を通じて信頼できる情報源から競合データを入手する | F26: A | G26: 信頼に基づくファーストパーティ データ アセットを構築するということは、自社の顧客や見込み客のプライバシーと好みを尊重しながらデータを収集、管理、アクティブ化することを意味します。また、データの使用方法、データ共有によって期待できるメリット、データの管理方法について、明確で正直な情報を顧客に提供することも意味します。そうすることで、顧客と相互に有益な関係を築くことができ、顧客は責任を持って倫理的にデータを使用することを信頼し、より関連性の高いパーソナライズされたエクスペリエンスを顧客に提供できます。信頼に基づくファーストパーティ データ アセットは、顧客ロイヤルティ、維持、成長を向上させるとともに、データ保護の規制や標準に準拠するのに役立ちます。参考資料: 強力なデジタル エクスペリエンスを実現するファーストパーティ データの使用、ファーストパーティ データがデータ プライバシーの鍵となる理由、ファーストパーティ データ戦略の構築 | H26: A | I26: ◾ 背景： 「信頼に基づくファーストパーティ データ資産」とは、企業が顧客から直接収集したデータを、顧客の同意と信頼に基づいて適切に管理・活用することを意味します。 この考え方は、近年の**プライバシー保護の高まり（GDPR, CCPA など）**や、クッキーレス社会への対応として非常に重要視されています。 ✅ 正解理由： ▶ A. 使用に同意し、その見返りに価値を受け取る個人から収集したデータの透明性とセキュリティを確保するため 「ファーストパーティデータ」とは、企業が自社チャネル（Webサイト、アプリ、POSなど）を通じて直接取得したデータです。 「信頼に基づく」とは、ユーザーがその使用に明示的に同意し（例：オプトイン）、見返りとしてサービスや価値を受け取るという、相互信頼のある関係性を指します。 Salesforce などが提唱する信頼ベースのデータ戦略では、この考え方を軸に、透明性・セキュリティ・ガバナンスが強調されています。 ❌ 他の選択肢の誤り： 選択肢 理由 評価 B. データクラウドマーケットプレイスで提供する ❌ 「マーケットプレイスで提供」はセカンド／サードパーティデータの文脈であり、ファーストパーティの信頼構築とは関係が薄い。 C. オプトイン同意の収集 ❌ 一部正しいが、メールマーケティングに限定されすぎており、全体的な信頼に基づく資産構築とは言い切れない。 D. 競合データを入手 ❌ ファーストパーティデータではなく、外部ソースやサードパーティデータの文脈。信頼とは無関係。 | J26: Salesforce.Data-Cloud-Consultant.v2024-12-02.q93 | K26: 100 | M26: *
B27: 158 | C27: ◯ | D27: 01_Data Cloud の概要 | E27: 顧客とのプライバシー法に関する話し合いの中で、顧客は忘れられる権利の要求を尊重する必要があることを示唆しました。コンサルタントは、Consent API がこのビジネス ニーズを解決できると判断しました。 コンサルタントが顧客に伝える必要がある 2 つの考慮事項はどれですか? 2つの回答を選択してください A. データ削除リクエストは 30 日、60 日、90 日後に再処理されます。 B. データ削除リクエストは 1 時間以内に処理されます。 C. 個々のプロファイルに対してデータ削除リクエストが送信されます。 D. Data Cloud に送信されたデータ削除リクエストは、接続されているすべての Salesforce クラウドに渡されます。 | F27: C, D | G27: 忘れられる権利の要求に応じるために Salesforce の Consent API を使用することについて顧客にアドバイスする場合、コンサルタントは次の 2 つの主な考慮事項に重点を置く必要があります。 * データ削除リクエストは、個々のプロファイルに対して送信されます (回答 C): Salesforce の Consent API は、個々のプロファイル専用のデータ削除リクエストを処理するように設計されています。つまり、データ削除リクエストは、Salesforce システム内の個人のプロファイルに関連付けられた個人データを対象とします。コンサルタントは、正確な処理とプライバシー法の遵守を確実にするために、リクエストは個々のプロファイルに固有のものである必要があることを顧客に通知する必要があります。 * Data Cloud に送信されたデータ削除リクエストは、接続されているすべての Salesforce クラウドに渡されます (回答 D): Salesforce Data Cloud の Consent API を通じてデータ削除リクエストが行われた場合、そのリクエストは Data Cloud だけに限定されません。Sales Cloud、Service Cloud、Marketing Cloud など、接続されているすべての Salesforce クラウドに伝播されます。これにより、Salesforce エコシステム全体で忘れられる権利への包括的なコンプライアンスが確保されます。お客様は、削除リクエストが接続されている Salesforce 環境全体の個人データのすべてのインスタンスに影響することを認識しておく必要があります。 | H27: C, D | I27: ◾ 背景： 顧客は「忘れられる権利（Right to be Forgotten）」＝個人データの完全な削除の要求に対応したいと考えています。 Salesforce Data Cloud ではこれに対応するために Consent API（同意・削除リクエスト処理用） が用意されています。 ✅ 正解理由： ▶ B. データ削除リクエストは 1 時間以内に処理されます。 Consent API によるデータ削除リクエストは、Salesforce Data Cloud 側で標準的に約1時間以内に処理されることが保証されています。 これは、プライバシー対応として十分迅速であることを意味し、ユーザーからの正式な「削除要求」に対してタイムリーな対応が可能です。 ▶ C. 個々のプロファイルに対してデータ削除リクエストが送信されます。 削除リクエストは、特定の Individual（個人）プロファイル ID を対象に送信されます。 これにより、その個人に関連するすべてのデータ（属性・接点・イベントなど）が削除対象となります。 ❌ 他の選択肢の誤り： 選択肢 理由 評価 A. 再処理される（30日、60日など） ❌ 一度送信された削除リクエストは再処理されず、単回で処理完了します。定期的な再処理スケジュールは存在しません。 D. すべての Salesforce クラウドに渡される ❌ Consent API は Data Cloud 内部の処理専用であり、Salesforceの他クラウド（Sales、Serviceなど）へ自動的に連携されることはない。別途処理が必要です。 | J27: Salesforce.Data-Cloud-Consultant.v2024-12-02.q93 | K27: 79 | M27: *
B28: 204 | C28: ◯ | D28: 01_Data Cloud の概要 | E28: Northern Trail Outfitters は、Marketing Cloud データの一部を Data Cloud で使用したいと考えています。 どのエンゲージメント チャネル データにカスタム統合が必要ですか? A. SMS B. メール C. クラウドページ D. モバイルプッシュ | F28: C | G28: CloudPage は、Marketing Cloud によってパーソナライズおよびホストできる Web ページです。これは、Data Cloud がすぐにサポートする標準のエンゲージメント チャネルの 1 つではありません。Data Cloud で CloudPage データを使用するには、カスタム統合が必要です。その他のエンゲージメント チャネル (SMS、メール、モバイル プッシュ) は Data Cloud によってサポートされており、Marketing Cloud Connector または Marketing Cloud API を使用して統合できます。参照: Data Cloud の概要、Marketing Cloud Connector、Marketing Cloud API | H28: C | I28: ◾ 背景： Salesforce Marketing Cloud のデータを Salesforce Data Cloud に取り込む際、一部のチャネルは標準で統合対応済みですが、他の一部チャネルはカスタム統合が必要です。 **「クラウドページ（CloudPages）」**はその代表的な例です。 ✅ 正解理由： ▶ クラウドページ（CloudPages）とは？ CloudPages は、Marketing Cloud でホストされるランディングページ／フォーム送信ページ／ウェブビューなど。 顧客がどのページを見たか・どんなフォームを送信したかといった行動ログは、Marketing Cloud Engagement に保存されるが、Data Cloudと標準連携されない。 → よって、CloudPages のエンゲージメントデータを Data Cloudで活用するには、API連携などの カスタム統合が必要となります。 ❌ 他の選択肢の誤り： 選択肢 評価 理由 A. SMS ❌ Marketing CloudのMobile Studio経由で送信されたSMSの配信・開封データは標準でData Cloudと統合可能。 B. メール ❌ Email Studioの送信、開封、クリック等のイベントはData Cloudにネイティブ統合済み。 D. モバイルプッシュ ❌ MobilePushの通知データもData Cloudに標準統合可能。 📝 補足： チャネル Data Cloud 統合方法 メール 標準統合（ネイティブ） SMS 標準統合（Mobile Studio） モバイルプッシュ 標準統合（MobilePush） クラウドページ ❌ カスタム統合が必要 | J28: Salesforce.Data-Cloud-Consultant.v2024-12-02.q93 | K28: 46 | M28: *
B29: 207 | C29: ◯ | D29: 01_Data Cloud の概要 | E29: 顧客が個人データの削除を要求します。 Data Cloud でこのリクエストに対応するためにコンサルタントはどのようなアクションを取る必要がありますか? A. ストリーミング API 呼び出しを使用して顧客の情報を削除します。 B. プロファイル エクスプローラーを使用して、Data Cloud から顧客データを削除します。 C. Consent API を使用して顧客情報の削除をリクエストします。 D. データ権利主体要求ツールを使用して、顧客情報の削除を要求します。 | F29: D | G29: データ権利主体リクエスト ツールは、データ クラウド ユーザーがデータへのアクセス、削除、または移植性に関する顧客のリクエストを管理できるようにする機能です。このツールは、データ権利リクエストを作成、追跡、および実行するためのユーザー インターフェイスと API を提供します。また、このツールは、顧客の個人データとリクエストに準拠するために実行されたアクションを含むレポートも生成します。コンサルタントは、このツールを使用して、データ クラウドでのデータ削除に関する顧客のリクエストに対応する必要があります。参照: データ権利主体リクエスト ツール、データ権利主体リクエストの作成 | H29: D | I29: ◾ 背景： Salesforce Data Cloud は、GDPRやCCPAなどのデータプライバシー規制に対応しており、 顧客（データ主体）からの**個人情報の削除リクエスト（Data Deletion Request）**に対処する機能を提供しています。 その代表的な機能が 「データ権利主体要求ツール（Data Subject Rights (DSR) Request Tool）」 です。 ✅ 正解理由： ▶ データ権利主体要求ツールとは？ Salesforce Data Cloud が提供する標準機能であり、GUIベースで個人データの削除を管理できる。 主に以下の2種類のリクエストに対応： Access（顧客がどの情報を持っているか開示要求） Delete（顧客データの削除要求） 削除対象の個人（Individual）は、**識別名（例：メールアドレス、CRM IDなど）**に基づいて特定される。 → この機能により、完全かつ準拠した方法でData Cloudから個人データを削除できる。 ❌ 他の選択肢の誤り： 選択肢 評価 理由 A. ストリーミング API 呼び出しで削除 ❌ ストリーミング API は**データ取り込み用途（イベント処理）**であり、削除処理には対応していない。 B. プロファイル エクスプローラーで削除 ❌ プロファイル エクスプローラーは可視化・分析用UIであり、削除操作はできない。 C. Consent API で削除リクエスト ❌ Consent API は同意ステータス（例：メール許諾）の管理用であり、データ削除のためのAPIではない。 📝 補足： DSRツールはData Cloud 管理者権限を持つユーザーのみが実行できます。 実行後、Data Cloudは該当個人のデータを完全に削除し、すべてのセグメント・アクティベーションから除外されます。 | J29: Salesforce.Data-Cloud-Consultant.v2024-12-02.q93 | K29: - | M29: *
B30: 219 | C30: ◯ | D30: 01_Data Cloud の概要 | E30: 顧客にとって Data Cloud の主な価値は何ですか? A. 顧客と関連データの統合ビューを提供する B. すべてのシステムをゴールデンレコードで接続する C. すべての匿名データのための唯一の真実のソースを作成する D. 顧客の行動に耳を傾け、理解し、行動することでパーソナライズされたキャンペーンを作成する | F30: A | G30: Data Cloud は、Salesforce アプリケーションやその他のシステム全体ですべての顧客データをアクティブ化できるプラットフォームです。Data Cloud を使用すると、CRM、マーケティング、コマース、サービス、外部データ プロバイダーなどのさまざまなソースからデータを取り込んで変換し、リンクすることで、各顧客の統合プロファイルを作成できます。また、Data Cloud は、顧客の行動、好み、ニーズに関する洞察と分析、および顧客とのやり取りをセグメント化、ターゲット設定、パーソナライズするためのツールも提供します。Data Cloud が顧客に提供する主な価値は、顧客とその関連データの統合ビューを提供することです。これにより、顧客エクスペリエンスを向上させ、ロイヤルティを高め、成長を促進することができます。参考資料: Salesforce Data Cloud、データが競争上の優位性を生み出すとき | H30: A | I30: ◾ 解説： Salesforce Data Cloud の主な価値は、 さまざまなソースから分断された顧客データを統合し、1人の顧客に関する包括的で信頼できるビュー（Customer 360）を提供することです。 この「統合ビュー」があることで、企業は顧客の行動・属性・関係性を正確に把握し、 マーケティング、営業、サービスなどの全チャネルで一貫したパーソナライズ対応ができるようになります。 ✅ A が正解である理由： Data Cloud は CRM、Web 行動、店舗データ、サービス履歴などを統一されたプロファイルに集約。 これにより、一人の顧客に関する全データが一か所で把握可能となります（＝統合ビュー）。 ❌ 他の選択肢の誤り： 選択肢 誤りの理由 B. ゴールデンレコードで接続する ❌ ゴールデンレコードは MDM（マスターデータ管理）での概念であり、Data Cloud はそこまで厳密な“正”の定義は行わない。 C. 匿名データの唯一の真実のソース ❌ Data Cloud は**主に識別可能なデータ（ファーストパーティデータ）**の統合が目的であり、匿名データ特化ではない。 D. パーソナライズされたキャンペーンの作成 ❌ パーソナライズは重要なユースケースだが、「主な価値」は統合ビューの提供にある（パーソナライズはその活用結果）。 📝 一言でまとめると： 「Data Cloud = 顧客データの統合基盤」 | J30: Salesforce.Data-Cloud-Consultant.v2024-12-02.q93 | K30: 73 | M30: *
B31: 222 | C31: ◯ | D31: 01_Data Cloud の概要 | E31: 検出中に、複数のデータ ソースを持ち、個人に関するデータを 1 つの統合プロファイルに一致させて調整する必要がある顧客に対して、コンサルタントはどの機能を強調する必要がありますか? A. データクレンジング B. 調和 C. データ統合 D. アイデンティティ解決 | F31: D | G31: アイデンティティ解決は、データ クラウドが複数のデータ ソースから個人に関するデータを 1 つの統合プロファイルに一致させて調整できるようにする機能です。アイデンティティ解決では、ルール セットを使用して、名前、電子メール、電話、または当事者 ID などの共通属性に基づいてソース プロファイルを一致させて統合する方法を定義します。アイデンティティ解決により、データ クラウドはさまざまなデータ ソースとシステムにわたって各顧客の 360 度ビューを作成できます12。他のオプションは、次の理由により、この顧客のニーズに最も適した機能ではありません。 * A. データ クレンジングは、重複、欠損値、無効な形式など、データ内のエラーや不整合を検出して修正するプロセスです。データ クレンジングにより、データの品質と精度は向上しますが、異なるデータ ソース間でのデータの一致や調整は行われません3。 * B. 調和とは、さまざまなソースからのデータを標準化し、共通の形式と構造に変換するプロセスです。調和により、データの統合と相互運用性が可能になりますが、異なるデータソース間でのデータの一致や調整は行われません4。 * C. データ統合とは、さまざまなソースからのデータを 1 つのデータ セットまたはシステムに結合するプロセスです。データ統合により、データの冗長性と複雑さを軽減できますが、さまざまなデータ ソース間でデータを一致させたり調整したりすることはできません5。参考文献: 1: Data and Identity in Data Cloud | Salesforce Trailhead、2: Data Cloud Identiy Resolution | Salesforce AI Research、3: [データ クレンジング - Salesforce]、4: [Harmonization - Salesforce]、5: [Data Consolidation - Salesforce] | H31: D | I31: ◾ 背景： 検出（Discovery）フェーズにおいて、顧客は以下のような要望を持っていると仮定されます： 複数のデータソース（例：CRM、ECサイト、モバイルアプリ）から集めた人物データを統合して、一人の顧客プロファイルにまとめたい 同一人物を見つけ出し、重複や分断されたデータをマージ（統合）したい このような課題に対して最も重要なのが、Salesforce Data Cloud におけるアイデンティティ解決機能です。 ✅ 正解理由： ▶ アイデンティティ解決（Identity Resolution）とは？ 複数のソースから取り込まれた同一人物と思われるデータをマッチング・統合する機能 以下の処理を担います： マッチング（Match）：氏名、メール、電話、ID などのルールで同一人物を特定 リンク（Link）：一致した複数のレコードを関連づけ 調整（Reconcile）：どの属性値を統合プロファイルに反映するか決定 結果として、「**Unified Individual（統合された個体）」**が生成されます。 ❌ 他の選択肢の誤り： 選択肢 評価 理由 A. データクレンジング ❌ フィールドの欠損や異常値などを整える処理であり、同一人物の統合とは直接関係しない。 B. 調和（Harmonization） ❌ 異なるデータ構造・命名を標準化する処理であり、「同一人物かどうか」の識別には使わない。 C. データ統合 ❌ 一般的な用語だが、Data Cloud の具体機能としては Identity Resolution を指すのが正確。曖昧すぎる。 📝 補足： フェーズ 対応機能 目的 前処理 データクレンジング データの整形・欠損補完 モデリング 調和（Harmonization） スキーマ標準化 統合処理 アイデンティティ解決 同一人物を見つけて統合 | J31: Salesforce.Data-Cloud-Consultant.v2024-12-02.q93 | K31: - | M31: *
B32: 225 | C32: ◯ | D32: 01_Data Cloud の概要 | E32: ある企業は、Salesforce で複数のリードと連絡先が同じメール アドレスを共有するという課題に対処する方法についてコンサルタントにアドバイスを求めています。コンサルタントは、この問題を効果的に解決するために Data Cloud を活用する方法について詳細かつ包括的な説明を提供したいと考えています。 この会社のビジネス上の課題に対処するためにコンサルタントは何を強調すべきでしょうか? A. データバンドル B. 計算された洞察 C. アイデンティティ解決 D. アイデンティティ解決 | F32: C | G32: 問題の概要: Salesforce で複数のリードと連絡先が同じメール アドレスを共有すると、データの重複、不正確な顧客ビュー、非効率的なマーケティングおよび販売活動につながる可能性があります。 Data Cloud Identity Resolution: Salesforce Data Cloud は、この問題に対処するための強力なツールとして Identity Resolution を提供します。これは、複数のソースからのデータをマージして統合し、単一の包括的な顧客プロファイルを作成するのに役立ちます。 プロセス： * データ取り込み: リードと連絡先のデータを Salesforce Data Cloud にインポートします。 * ID 解決ルール: 電子メール アドレスなどの主要な識別子に基づいてレコードを照合およびマージするための ID 解決ルールを構成します。 * 統合: このツールは、同じ電子メール アドレスを共有するレコードを統合し、重複を排除して各顧客の単一のビューを保証します。 | H32: C | I32: ◾ 背景（ビジネス課題）： この企業は、Salesforce CRM において： 複数のリード（Leads）や連絡先（Contacts）が同じメールアドレスを持っている これにより、**「誰が誰かがわからない」「重複顧客が存在している」**という状態に悩まされています。 たとえば： lead1@example.com → 見込み客のAさん contact1@example.com → すでに取引中のBさん この2人が同じメールアドレスを使っていた場合、誤って同一人物とみなしたり、逆に別人として扱ってしまう混乱が生じます。 ✅ 正解理由： ▶ アイデンティティ解決（Identity Resolution）とは？ Salesforce Data Cloud の機能であり、複数のデータソースから来た「人物レコード」を分析し、同一人物を特定・統合する機能です。 このプロセスには以下が含まれます： マッチルール（Matching Rules）： 例）メールアドレスが一致、名前＋電話番号が一致など → 同一人物かどうかを判断 リンク（Link）： 同一と判断されたレコードを紐付け 調整（Reconciliation）： 複数のソースから来た異なる属性のうち、どの値を統合後プロファイルに使うか決定 これにより、同じメールアドレスを使う複数のリード・連絡先を、1つの「統合プロファイル（Unified Individual）」として管理可能になります。 ❌ 他の選択肢の誤り： 選択肢 理由 A. データバンドル ❌ データバンドルは主に B2C Commerce などの eコマースデータ取り込みに関するパッケージであり、アイデンティティの重複解決には直接関係しない。 B. 計算された洞察（Calculated Insights） ❌ 集計・分析向けの機能であり、重複人物の統合には使われない。アイデンティティの統合処理には適していない。 D. アイデンティティ解決（重複） ⚠️ 選択肢としては正しいが、Cと内容が重複しており、形式ミス。意味としてはCが正答。 📝 コンサルタントが強調すべきポイント： 重複したリードや連絡先を1つの統合プロファイルにまとめることができる メールアドレスだけではなく、複数の条件（名前、電話番号、IDなど）で精密なマッチングができる 誤マッチを避けるための厳密なルール設計や、データソースごとの信頼度設定も可能 統合後も元データは保持され、信頼性の高い代表値を構成できる（調整ルール） | J32: Salesforce.Data-Cloud-Consultant.v2024-12-02.q93 | K32: - | M32: *
B33: 11 | C33: ◯ | D33: 02_Data Cloud の設定と管理 | E33: コンサルタントは、複数のブランドを扱う組織向けに Data Cloud を設定しており、データ スペースを使用してさまざまなブランドのデータを分離しています。 データ ストリームのマッピングを開始しているときに、コンサルタントは、ブランドの 1 つに対してオブジェクトをマッピングできないことに気付きました。 オブジェクトを新しいデータ スペースで使用できるようにするために、コンサルタントは何をする必要がありますか? A. 異なるデータ スペース間でデータを分割するバッチ変換を作成します。 B. データ コピー機能を使用して、デフォルトのデータ スペースから新しい DMO にデータをコピーし、この DMO を新しいデータ スペースにリンクします。 C. [データ スペース] タブに移動し、新しいデータ スペースに含めるオブジェクトを選択します。 D. 新しいデータ ストリームを作成し、2 番目のデータ ストリームをデータ スペースにマップします。 | F33: C | G33: - | H33: C | I33: ◾ 問題の状況： コンサルタントは、**複数ブランドを分離管理するために Data Cloud の「データスペース（Data Space）」**を使用している。 あるブランド（≒データスペース）において、特定のオブジェクト（DMO）をデータストリームにマッピングできない。 → これは、その DMO がそのデータスペースで有効になっていないことが原因です。 ■ 正解の根拠： ▶ データスペースとDMOの関係性 Data Cloud では、データスペースごとに使用できるDMO（データモデルオブジェクト）を明示的に有効化する必要があります。 つまり、「どのDMOをどのデータスペースで利用可能にするか」は、[データスペース]タブで設定します。 この操作を行わない限り、データストリームのマッピング画面に該当DMOが表示されず、マッピングができません。 | J33: Salesforce.Data-Cloud-Consultant-JPN.v2025-03-28.q66 | K33: - | M33: *
B34: 14 | C34: ◯ | D34: 02_Data Cloud の設定と管理 | E34: Northern Trail Outfitters のマーケティング マネージャーは、データ クラウド セグメント インテリジェンスからの分析情報を活用して、マーケティングの投資収益率 (ROI) を向上したいと考えています。 これを設定するには、ユーザーはどの権限セットが必要ですか? A. データクラウドユーザー B. データクラウド管理者 C. データクラウド データアウェア スペシャリスト D. クラウドマーケティングマネージャー | F34: B D | G34: 提供されたソースによると、Northern Trail Outfitters のマーケティング マネージャーが、データ クラウド セグメント インテリジェンスからの分析情報を活用してマーケティングの投資収益率 (ROI) を向上したいと考えている場合、セグメント、アクティベーション、アクティベーションターゲットへのフルアクセスを許可する「マーケティング・マネージャーのためのデータ・クラウド」権限セットが最も適しています。提供された選択肢の中で、この権限セットに最も近い名前は D です。 D. クラウドマーケティングマネージャー ただし、この権限セット名「クラウドマーケティングマネージャー」は、提供されたソース中の権限セット名（「マーケティング・マネージャーのためのデータ・クラウド」）と厳密には一致しません。 （注：選択肢C「データクラウド データアウェア スペシャリスト」およびD「クラウドマーケティングマネージャー」という名前の権限セットは、提供されたソース中には直接確認できませんでした。） | H34: A D | I34: ◾ 問題の要点： Northern Trail Outfitters のマーケティングマネージャーが、セグメントインテリジェンス（＝Data Cloudの可視化/分析機能）を活用して、マーケティングのROIを向上させたい。 この要件において重要なのは： セグメントインテリジェンス（Segment Intelligence）にアクセスして、 セグメントのパフォーマンスや指標を確認する よって必要なのは「分析と参照を行うためのユーザー権限」 ◾ 正解の根拠： ✅ 「データクラウドユーザー（Data Cloud User）」権限セットは： Data Cloud 内での セグメントの作成・閲覧・インサイト参照 などが可能 セグメントインテリジェンスを表示して ROI分析の土台となるデータの確認が可能 ■ 他の選択肢の誤り： 選択肢 評価 理由 A. データクラウドユーザー ✅ 正解 分析・セグメントの参照に必要な基本的ユーザー権限 B. データクラウド管理者 ❌ 不正解 管理目的での構成権限。セグメントインテリジェンスの閲覧には過剰 C. データクラウド データアウェア スペシャリスト ❌ 不正解 データ連携や統合に関する技術系ロールで、閲覧主体のマーケティング職には不要 D. クラウドマーケティングマネージャー ❌ 不正解 存在しないか、少なくとも Data Cloud 標準の権限セットには存在しない 名前 | J34: Salesforce.Data-Cloud-Consultant-JPN.v2025-03-28.q66 | K34: - | M34: *
B35: 17 | C35: ◯ | D35: 02_Data Cloud の設定と管理 | E35: Data Cloud の新規ユーザーは、取り込まれたデータの個々の行を確認し、リンクされたデータ モデル オブジェクトに正常にモデル化されていることを検証することのみが必要です。必要に応じて、ユーザーも変更を加える必要があります。 このユースケースに対応するために必要な最小限の権限セットは何ですか? A. マーケティング スペシャリスト向けのデータ クラウド B. データ クラウド管理者 C. データクラウドユーザー D. マーケティング データ認識スペシャリスト向けデータ クラウド | F35: C B | G35: データ クラウド ユーザー パーミッション セットは、このユースケースに対応するために必要な最小限のパーミッション セットです。データ クラウド ユーザー パーミッション セットは、データ エクスプローラー 機能へのアクセスを許可します。この機能により、ユーザーは取り込まれたデータの個々の行を確認し、そのデータが関連付けられたデータ モデル オブジェクトに正しくマッピングされていることを検証できます。ユーザーはまた、データ モデル オブジェクトのフィールドに対して変更を加えることもできます。例えば、フィールドの追加や削除、フィールド タイプの変更、または数式フィールドの作成などが可能です。データクラウド ユーザー パーミッション セットは、データ ストリームの作成、セグメントの作成、アクティベーションの作成、またはユーザーの管理など、他のデータクラウド機能やタスクへのアクセスを許可しません。他のパーミッション セットは、このユースケースには制限が厳しすぎたり、許可が広すぎたりします。データクラウド マーケティング スペシャリスト パーミッション セットはセグメンテーションとアクティベーション機能へのアクセスを許可しますが、データ エクスプローラー機能へのアクセスは許可しません。Data Cloud Admin 権限セットは、Data Explorer 機能を含むすべての Data Cloud 機能とタスクへのアクセスを許可しますが、ユーザーが必要とする範囲を超えています。Data Cloud for Marketing Data Aware Specialist 権限セットは、Data Explorer 機能へのアクセスを許可しますが、このユースケースでは不要なセグメンテーションとアクティベーション機能へのアクセスも含まれます。参照： Data Cloud 標準権限セット、Data Explorer、Data Cloud ユニットの設定 データクラウドにおいて、取り込まれたデータの個々の行を確認し、リンクされたデータ モデル オブジェクトに正常にモデル化されていることを検証し、必要に応じて変更を加えるというユースケースに対応するために必要な最小限の権限セットについて、ソースに基づき説明します。 提供されたソースでは、いくつかのData Cloudに関連する権限セットについて説明されています。 • Data Cloud管理者: Data Cloud内のすべてのナビゲーションコンポーネントへのフルアクセスを許可します。ユーザーは、データをデータモデルにマッピングし、データストリーム、ID解決ルールセット、計算されたインサイトを作成するなど、Data Cloud内のすべての機能を使用できます。 • Data Cloudユーザー: Data Cloud内のすべてのナビゲーションコンポーネントへの表示のみのアクセスを許可します。この権限セットを持つユーザーは、Data Cloud機能を表示できます。データモデルへのマッピング、データストリーム、ID解決ルールセット、計算されたインサイトを作成することはできます。しかし、「表示のみ」であるため、既存のデータやモデルに「変更を加える」という操作は制限されると解釈できます。 • マーケティング スペシャリスト向けのデータ クラウド: データエクスプローラーおよびプロファイルエクスプローラーにはアクセスできません。他のすべてのナビゲーションコンポーネントは表示のみが可能です。ユーザーはセグメントを作成できます。取り込まれたデータの個々の行を確認するためにはデータエクスプローラーが必要であると考えられるため、この権限セットでは不十分です。 • マーケティング データ認識スペシャリスト向けデータ クラウド: この名称の権限セットはソースに直接見当たりません。「マーケティング活用スペシャリスト向けデータ・クラウド」、「マーケティング・マネージャー向けデータ・クラウド」、「マーケティング・スペシャリスト向けデータ・クラウド」などのマーケティング関連の権限セットが説明されていますが、これらの権限セットの多くは表示が中心であったり、データエクスプローラーへのアクセスが制限されていたりします。 ユースケースとして「取り込まれたデータの個々の行を確認」[User Query]し、「リンクされたデータ モデル オブジェクトに正常にモデル化されていることを検証」[User Query]し、必要に応じて「変更を加える」[User Query]必要がある点を考慮すると、Data Cloud管理者の権限セットがこれらの操作をすべて可能にする最も適切な選択肢であると考えられます。Data Cloud管理者はData Cloudのすべての機能にアクセスでき、データモデルのマッピングやデータストリームの設定など、モデル化の検証や変更に関連する操作を行うことができます。 したがって、提供されたソースに基づくと、ユースケースに対応するために必要な権限セットは以下の通りです。 B. データ クラウド管理者 | H35: D B | I35: ◾ 問題の要点： 新規ユーザーが必要なのは： 取り込まれたデータの個々の行を確認 リンクされたデータモデルオブジェクト（DMO）に正常にマッピングされているかの検証 必要に応じて変更も加える つまり、データ構造と取り込み結果の確認・調整ができる中間的な役割が求められています。 ■ 正解の理由（D）： ✅ 「Data Cloud for Marketing Data Aware Specialist」 は： 取り込まれたデータの構造、行単位の確認 データストリームやマッピングの検証 一部の変更や微調整も可能 という権限を持つ、テクニカル担当者向けの準管理者的ロールです。 ■ 他の選択肢の検討： 選択肢 評価 理由 A. Data Cloud for Marketing Specialist ❌ 不正解 マーケティング担当者向けで、セグメントやアクティベーションなどの実行権限中心。データ構造の検証には不足 B. Data Cloud Admin ❌ 過剰 管理者権限であり、全構成・接続管理も含むため最小構成ではない C. Data Cloud User ❌ 不足 セグメントの作成や閲覧は可能だが、データストリームや取り込み確認・調整はできない D. Data Cloud for Marketing Data Aware Specialist ✅ 最小かつ適切 データ検証・行レベルのチェック・マッピング調整などが可能な役割 | J35: Salesforce.Data-Cloud-Consultant-JPN.v2025-03-28.q66 | K35: - | M35: *
B36: 37 | C36: ◯ | D36: 02_Data Cloud の設定と管理 | E36: Cloud Kicks のマーケティング マネージャーは、自社のアカウントの企業電話番号を Data Cloud に取り込むことを計画しています。これらの電話番号を保存するために、データが Phone に設定されたカスタム フィールドを使用する予定です。 電話番号を取り込む際に正しい記述はどれですか? A. 電話番号フィールドを主キーとして使用する必要があります。 B. Data Cloud は、取り込み時に電話番号の形式を検証します。 C. テキスト値は、電話データ型フィールドへの取り込みに受け入れられます。 D. 電話番号フィールドは 10 桁の値のみを受け入れます。 | F36: C | G36: Data Cloud への電話番号の取り込みに関するご質問ですね。提供されたソースに基づき、各選択肢について確認します。 まず、電話番号フィールドに関する情報はスライド51 に記載されています。 • A. 電話番号フィールドを主キーとして使用する必要があります。 ソースにおいて、電話番号フィールドを主キーとして使用する必要があるという特定の記述は見当たりません。主キーはデータソースやDMOの種類によって異なり、Identity Resolution で使用される Individual ID や Party ID とは異なる概念として説明されています。したがって、この記述はソースによって直接裏付けられていません。 • B. Data Cloud は、取り込み時に電話番号の形式を検証します。 スライド51 には、「Data Cloud は、取り込み時に電話番号の形式を検証しません。」と明確に記載されています。したがって、この記述は誤りです。 • C. テキスト値は、電話データ型フィールドへの取り込みに受け入れられます。 スライド51 には、「電話番号データ型はテキスト・データ型をモデルにしています。」と記載されています。これは、電話番号フィールドが内部的にはテキストとして扱われることを示唆しています。スライド50 では、テキストデータ型は「あらゆる種類のテキストデータを格納」し、「空の文字列としての文字列」も扱えることが述べられています。このことから、電話番号フィールドにはテキスト値が受け入れられると考えられます。 • D. 電話番号フィールドは 10 桁の値のみを受け入れます。 ソースには、電話番号フィールドが受け入れる桁数に関する具体的な制限（例えば「10桁のみ」）についての記述はありません。Data Cloud が形式を検証しない と記載されていることから、特定の桁数に限定されるわけではないと考えられます。したがって、この記述はソースによって直接裏付けられていません。 提供されたソースの情報に基づくと、最も正しい記述は C. テキスト値は、電話データ型フィールドへの取り込みに受け入れられます。 となります。これは、電話番号データ型がテキストデータ型をモデルにしているという記述 によって裏付けられています。 | H36: C | I36: ◾ 問題の背景： Cloud Kicks のマーケティングマネージャーは、企業の電話番号を Data Cloud に取り込もうとしている。 その際に使うフィールドは、データ型「Phone」に設定されたカスタムフィールド。 つまり、「電話番号の取り込みに関して正しい理解はどれか？」という設問です。 ✅ 正解理由（C）： Salesforce Data Cloud では、データ型「Phone」のフィールドに対しても、 「電話番号をテキスト（文字列）として」取り込むことが可能です。 取り込み時点では、文字列としての受け入れが行われる 形式（例：+81-3-1234-5678 や (800) 555-1234）については、標準化やバリデーションは行われない（後続で整形・変換が必要） ❌ 他の選択肢の誤り： 選択肢 評価 理由 A. 電話番号フィールドを主キーにする必要がある ❌ 不正解 主キー（Primary Key）にする必要は一切ない。IDやメールの方が主キーに適している B. 取り込み時に電話番号形式を検証する ❌ 不正解 Data Cloudは電話番号の形式検証を自動で行わない（+/-/() なども許容） C. テキスト値はPhone型フィールドに受け入れられる ✅ 正解 文字列として受け入れるため、形式に厳密な制限はない D. 10桁の値のみ受け入れる ❌ 不正解 国際番号や9桁番号なども受け入れ可能であり、10桁制限は存在しない | J36: Salesforce.Data-Cloud-Consultant-JPN.v2025-03-28.q66 | K36: - | M36: *
B37: 52 | C37: ◯ | D37: 02_Data Cloud の設定と管理 | E37: Northern Trail Outfitters (NTO) は、CRM データを Data Cloud に取り込み始める準備を進めています。 コネクタを設定する際に、データ ストリームが初めて展開されるときに、NTO はどのタイプの更新を予期する必要がありますか? A. 増分 B. 手動更新 C. 部分更新 D. 完全更新 | F37: D | G37: * データ ストリームの展開： Salesforce Data Cloud でデータ ストリームを設定する際、最初の展開には包括的なデータ ロードが必要です。 * リフレッシュの種類： 増分リフレッシュ： 前回のリフレッシュ以降に追加または変更されたデータのみを更新します。 手動リフレッシュ： ユーザーが手動でデータ ロードを開始する必要があります。 部分リフレッシュ： データのサブセットのみがリフレッシュされます。 フル リフレッシュ： データセット全体がシステムにロードされます。 * 初回展開： データストリームの初回展開時には、ソースシステムからのすべてのデータがSalesforce Data Cloudにインポートされるように、フルリフレッシュが必須です。 * 参照： Salesforce ドキュメント： データストリームの設定 Salesforce Data Cloud ガイド | H37: D | I37: ◾ 問題の状況： Northern Trail Outfitters（NTO）は、CRMデータをSalesforce Data Cloudに取り込むためのコネクタを初期設定しています。 → 最初に データストリームが展開されるときに起こる更新タイプは何か？ ✅ 正解理由：「最初の取り込みは常に完全更新（Full Refresh）」 Salesforce Data Cloud におけるデータストリームの動作： 初回展開時には、対象のCRMオブジェクトから すべてのデータを一括で取り込む＝完全更新（Full Refresh） が実行されます。 これは、個人・取引先・活動履歴などのフルデータセットをData Cloudに同期し、マッピング・ID解決・調和を行うために必要です。 初回以降は、設定に応じて 増分取り込み（Incremental Refresh） も可能になります。 ❌ 他の選択肢の誤り： 選択肢 評価 理由 A. 増分（Incremental） ❌ 不正解 初回取り込みでは使用されない。2回目以降に適用可能な取り込みモード B. 手動更新 ❌ 不正解 データストリームの初回取り込みは自動的にトリガーされる C. 部分更新（Partial Refresh） ❌ 不正解 Data Cloud では「部分更新」というモードは存在しない D. 完全更新（Full Refresh） ✅ 正解 初回展開時は常に全データを取得するフルリフレッシュ方式が用いられる | J37: Salesforce.Data-Cloud-Consultant-JPN.v2025-03-28.q66 | K37: - | M37: *
B38: 56 | C38: ◯ | D38: 02_Data Cloud の設定と管理 | E38: コンサルタントはトランザクション データを含むデータ ストリームを設定しています。 コンサルタントは、確実に優れたフィールド タイプを選択する必要があります。 発注書番号のゼロは保持されますか? A. テキスト B. 数値 C. 10 進数 D. シリアル | F38: A | G38: フィールドタイプ「テキスト」を選択することで、購入注文番号の先頭のゼロが保持されます。これは、テキストフィールドがアルファベットと数字を文字列として保存し、先頭や末尾の文字を削除しないためです。一方、数値、小数、シリアルフィールドは数値を数値として保存し、データを表示またはエクスポートする際、先頭のゼロを自動的に削除します123。したがって、購入注文番号、郵便番号、電話番号など、元の形式を保持する必要があるデータを格納するには、テキストフィールドが適しています。参照： フィールドの先頭にあるゼロがデータエクスポートで省略される CSVファイルをインポートする際、最初の『0』を保持する ゼロで始まるまたはプラス記号を含む住所フィールドのインポートとエクスポート | H38: A | I38: ◾ 問題の焦点： 「発注書番号（注文番号）などの先頭にゼロを含む値」をデータストリームで取り込む際、 ゼロを正確に保持したい場合に、どのフィールドタイプを選ぶべきか？ ✅ 正解理由：テキスト（Text）型ならゼロが保持される 例： 発注書番号：0012345678 のような ゼロ始まりの識別子 テキスト型であればそのまま "0012345678" として保持される 一方で、数値型や小数型にしてしまうと： 型 値の扱い 備考 数値（Number） 12345678（先頭ゼロ削除） ❌ ゼロは無視される 10進数（Decimal） 12345678.00 ❌ 同上、識別子としては不適切 シリアル（Serial） 自動連番付与 ❌ 入力された番号ではなく、独自の連番となるため不適 ✅ 発注書番号や顧客ID、SKUなどに先頭ゼロが含まれる可能性がある場合は、必ず「テキスト型」にすべきです。 ❌ 他の選択肢の誤り： 選択肢 評価 理由 A. テキスト ✅ 正解 先頭ゼロを含む識別子をそのまま扱える唯一のフィールドタイプ B. 数値 ❌ 不正解 00123 → 123 に変換されてしまい、識別子として破損 C. 10進数 ❌ 不正解 金額や量には適しているが、識別子用途には不向き（同上） D. シリアル ❌ 不正解 自動採番目的で使用され、外部から取り込んだ識別子を維持できない | J38: Salesforce.Data-Cloud-Consultant-JPN.v2025-03-28.q66 | K38: - | M38: *
B39: 59 | C39: ◯ | D39: 02_Data Cloud の設定と管理 | E39: ノーザン トレイル アウトフィッターズは、Marketing Cloud スターター データ バンドルを使用して、Marketing Cloud データを Data Cloud に取り込みます。 Marketing Cloud スターター データ バンドルで利用可能な 2 つのデータセットは何ですか? 2 つの答えを選択してください A. パーソナライゼーション B. モバイルコネクト C. ロイヤリティ管理 D. モバイルプッシュ | F39: B, D | G39: マーケティングクラウド スターター データ バンドルは、マーケティングクラウドからデータ クラウド1にデータを簡単に取り込むことができる事前定義されたデータ バンドルです。マーケティングクラウド スターター データ バンドルで利用可能なデータセットは、Email、MobileConnect、および MobilePush2 です。これらのデータセットには、メール、SMS、プッシュ通知2 などのマーケティングクラウドのチャネルから収集されたエンゲージメント イベントとメトリクスが含まれています。これらのデータセットを使用することで、マーケティングクラウドのデータでデータクラウドのデータモデルを強化し、マーケティングキャンペーンやジャーニーに基づいてセグメントやアクティベーションを作成できます1。他のオプションは、マーケティングクラウド スターター データ バンドルで利用可能なデータセットではないため、正答ではありません。オプションAは誤りです。なぜなら、パーソナライゼーションはデータセットではなく、Marketing Cloudの機能であり、オーディエンスに合わせてコンテンツやメッセージをカスタマイズする機能です3。オプションCは誤りです。なぜなら、Loyalty Managementはデータセットではなく、Marketing Cloudの製品であり、顧客向けのロイヤルティプログラムを作成・管理する機能です4。参照：Data Cloud内のMarketing Cloud Starter Data Bundles、データソースの接続、Marketing Cloudでのパーソナライゼーション、Marketing CloudでのLoyalty Management | H39: B, D | I39: ◾ 問題の背景： ノーザン トレイル アウトフィッターズは、Marketing Cloud スターター データ バンドルを使用して、Marketing Cloud のデータを Salesforce Data Cloud に取り込もうとしている。 では、「このスターターバンドルに含まれている2つのデータセットはどれか？」を問う設問です。 ✅ 正解理由：MobileConnect & MobilePush はスターターバンドルの一部 Salesforce の Marketing Cloud Starter Data Bundle に含まれるデータセットは、以下のような 基本的なチャネルアクティビティ情報です。 ▶ 主に含まれるのは以下： Email（送信、開封、クリックなど） MobileConnect（SMS送信、受信、応答など） MobilePush（プッシュ通知の配信、受信など） これらは、Data Cloudでのエンゲージメント分析・セグメント作成に使用される。 ❌ 他の選択肢の誤り： 選択肢 評価 説明 A. パーソナライゼーション ❌ 不正解 Einstein Personalization（旧Interaction Studio） に関するデータであり、Starter Bundleには含まれない B. モバイルコネクト（MobileConnect） ✅ 正解 SMSチャネルのデータであり、Starter Bundleの一部 C. ロイヤリティ管理 ❌ 不正解 Marketing Cloud Loyalty Managementは別プロダクトで、Starter Bundleには含まれない D. モバイルプッシュ（MobilePush） ✅ 正解 Push通知チャネルのデータであり、Starter Bundleの一部 | J39: Salesforce.Data-Cloud-Consultant-JPN.v2025-03-28.q66 | K39: - | M39: *
B40: 62 | C40: ◯ | D40: 02_Data Cloud の設定と管理 | E40: 組織は、在庫レベルを在庫管理システムからデータ クラウドに、高速かつスケーラブルでほぼリアルタイムの方法でストリーミングするには何を使用する必要がありますか? A. クラウド ストレージ コネクタ B. コマース クラウド コネクタ C. 取り込み API D. Marketing Cloud パーソナライゼーション コネクタ | F40: C | G40: Ingestion API は、あらゆるソースからデータを Data Cloud に高速かつスケーラブルにストリーミングできる RESTful API です。Ingestion API を使用すると、在庫管理システムから JSON オブジェクトとしてデータを Data Cloud に送信し、その在庫データに基づいて Data Cloud でデータモデル、セグメント、インサイトを作成できます。Ingestion APIはバッチモードとストリーミングモードの両方をサポートし、秒間最大100,000件のレコードを処理できます。Ingestion APIは、データ検証、暗号化、圧縮、リトライメカニズムなどの機能を提供し、データ品質とセキュリティを確保します。参照： Ingestion API開発者ガイド、Data Cloudへのデータインジェスト | H40: C | I40: ◾ 問題の要点： 組織は以下のニーズを持っています： 在庫管理システムからデータを Data Cloud に対して 高速かつスケーラブル ほぼリアルタイムでストリーミング → この条件を満たす最適なデータ連携手段は何か？という設問です。 ✅ 正解理由：「取り込み API（Ingestion API）」はリアルタイムかつスケーラブルなデータ受信のための標準機構 ▶ 特徴： JSON形式のHTTP POSTリクエストを使って、外部システムから直接Data Cloudにデータを送信可能 ミリ秒～秒単位のスピードで処理される イベントドリブン型や IoT、在庫変動など変化が激しいデータ連携に最適 ❌ 他の選択肢の誤り： 選択肢 評価 理由 A. クラウドストレージコネクタ ❌ 不正解 Amazon S3 などのバッチファイルベース取り込み用であり、リアルタイム性に欠ける B. コマースクラウドコネクタ ❌ 不正解 Salesforce B2C Commerce 専用であり、在庫管理システムからの汎用連携には使えない C. 取り込み API（Ingestion API） ✅ 正解 リアルタイム / ストリーミング / スケーラブル / 任意の外部ソース対応のすべてに合致 D. Marketing Cloud パーソナライゼーション コネクタ ❌ 不正解 Marketing Cloudとのパーソナライズデータの同期用途で、在庫データ用途ではない | J40: Salesforce.Data-Cloud-Consultant-JPN.v2025-03-28.q66 | K40: - | M40: *
B41: 65 | C41: ◯ | D41: 02_Data Cloud の設定と管理 | E41: Salesforce CRM コネクタが設定され、ケース オブジェクト データ ストリームが設定されます。その後、Salesforce CRM の Case オブジェクトに Business Priority という名前の新しいカスタム項目が作成されます。ただし、新しいフィールドをデータ ストリームに追加しようとしても、そのフィールドは使用できません。 この問題の原因を説明しているのはどれですか? A. Salesforce 統合ユーザーには、新しく作成されたフィールドに対する Rad 権限がありません。 B. デスクトップから一括アップロードを実行するには、Salesforce Data Loader アプリケーションを使用する必要があります。 C. Case オブジェクトのカスタム フィールドは、Data Cloud への取り込みがサポートされていません。 D. 24 時間後にデータ ストリームが更新されると、Salesforce CRM に追加された新しいフィールドが自動的に含まれます。 | F41: A | G41: Salesforce CRM コネクタは、Salesforce CRM 組織のデータにアクセスするために Salesforce 統合ユーザーを使用します。統合ユーザーは、データ ストリームに含まれるフィールドに対して読み取り権限を持っている必要があります。統合ユーザーが新規に作成されたフィールドに対して読み取り権限を持っていない場合、そのフィールドはデータ ストリームの設定で選択できません。この問題を解決するには、管理者は統合ユーザー プロファイルまたは権限セットに新規フィールドの読み取り権限を割り当てる必要があります。参照： Salesforce CRM データ ストリームの作成、データ ストリームの編集、Salesforce Data Cloud フル リフレッシュ（CRM、SFMC、またはインジェスト API データ ストリーム） | H41: A | I41: ◾ 問題の背景： Salesforce CRM コネクタを使用して、Caseオブジェクトのデータを Data Cloud にストリーミングしている。 CRM側で新しいカスタム項目 Business Priority を作成したが、Data Cloud 側でこの項目がデータストリームに追加できない。 ✅ 正解理由：「統合ユーザーに Read 権限がない」と、Data Cloud 側でそのフィールドは検出できない Salesforce Data Cloud は、統合ユーザー（Integration User）を通じてCRMデータを取得しています。 このユーザーが、新しく追加されたフィールドに対するアクセス権限（Read）がないと： データストリームのフィールド一覧にそのフィールドが表示されず 結果として Data Cloud 側で追加できない ✅ 解決策： Salesforce CRM で該当フィールド（例：Business Priority）に対し 統合ユーザーが属する **プロファイルまたは権限セットに「Read 権限」**を付与する データストリーム画面でフィールド一覧を再読み込み → 選択できるようになる ❌ 他の選択肢の誤り： 選択肢 評価 誤りの理由 A. 統合ユーザーに Read 権限がない ✅ 正解 最も一般的な原因。CRM側のアクセス制御が原因で、Data Cloud にフィールドが表示されない B. Data Loaderを使う必要がある ❌ 不正解 Data Loader は CRM 内部の一括更新用ツールであり、Data Cloud ストリーミングとは無関係 C. Case のカスタム項目は取り込み不可 ❌ 不正解 完全に誤り。どの標準/カスタム項目も原則取り込み可能（権限があれば） D. 24時間後に自動的に取り込まれる ❌ 不正解 フィールドの追加は 手動でデータストリームを再設定・再同期する必要がある（自動追加されない） | J41: Salesforce.Data-Cloud-Consultant-JPN.v2025-03-28.q66 | K41: - | M41: *
B42: 72 | C42: × | D42: 02_Data Cloud の設定と管理 | E42: 組織は、在庫管理システムからデータ クラウドに在庫レベルを高速かつスケーラブルに、ほぼリアルタイムでストリーミングするために何を使用すればよいでしょうか。 A. 取り込みAPI B. クラウド ストレージ コネクタ C. コマースクラウドコネクタ D. マーケティング クラウド パーソナライゼーション コネクタ | F42: A | G42: Ingestion API は、あらゆるソースからデータを Data Cloud に高速かつスケーラブルにストリーム送信できる RESTful API です。Ingestion API を使用すると、在庫管理システムから JSON オブジェクトとしてデータを Data Cloud に送信し、その在庫データに基づいて Data Cloud でデータモデル、セグメント、インサイトを作成できます。Ingestion API はバッチモードとストリーミングモードの両方をサポートし、最大 100,000件/秒の処理が可能です。Ingestion APIは、データ検証、暗号化、圧縮、リトライメカニズムなどの機能を提供し、データ品質とセキュリティを確保します。 参照： Ingestion API開発者ガイド、Data Cloudへのデータインジェスト | H42: A | I42: ◾ 問題の背景： 組織は、在庫管理システムから Salesforce Data Cloud に対して： 高速かつスケーラブル ほぼリアルタイムで 在庫データをストリーミングしたい という要件を持っています。 ✅ 正解理由：「取り込み API」はリアルタイムデータ連携に最適 ▶ Ingestion API とは？ Salesforce Data Cloud にデータを送信するための HTTPベースのAPI REST API 経由で、リアルタイム or 近リアルタイムのデータ取り込みが可能 使い方：在庫システムから JSON データを POST するだけで送信完了 ▶ 特徴： 特性 内容 ⏱ スピード ミリ秒～秒単位の取り込みを実現（ほぼリアルタイム） ⚙ 拡張性 イベントドリブン、IoT、POS、在庫更新など様々なユースケースに対応 📡 汎用性 在庫管理システムのような外部システムとの連携に最適 ❌ 他の選択肢の誤り： 選択肢 評価 理由 A. 取り込み API ✅ 正解 リアルタイムでの柔軟なデータ取り込みをサポートする最適な方法 B. クラウド ストレージ コネクタ ❌ 不正解 S3 や Azure など バッチ処理用であり、リアルタイム性に欠ける C. コマースクラウドコネクタ ❌ 不正解 Salesforce B2C Commerce専用で、在庫管理システムとの直接連携には向かない D. Marketing Cloud パーソナライゼーション コネクタ ❌ 不正解 キャンペーンパーソナライズ用のデータ連携であり、在庫更新には不適 | J42: Salesforce.Data-Cloud-Consultant-JPN.v2024-09-12.q66 | K42: 62 | M42: *
B43: 88 | C43: ◯ | D43: 02_Data Cloud の設定と管理 | E43: Data Cloud の新規ユーザーは、取り込まれたデータの個々の行を確認し、リンクされたデータ モデル オブジェクトに正常にモデル化されていることを検証することのみが必要です。必要に応じて、ユーザーも変更を加える必要があります。 このユースケースに対応するために必要な最小限の権限セットは何ですか? A. マーケティング スペシャリスト向けのデータ クラウド B. データ クラウド管理者 C. データクラウドユーザー D. マーケティング データ認識スペシャリスト向けデータ クラウド | F43: C | G43: データ クラウド ユーザー パーミッション セットは、このユースケースに対応するために必要な最小限のパーミッション セットです。データ クラウド ユーザー パーミッション セットは、データ エクスプローラー 機能へのアクセスを許可します。この機能により、ユーザーは取り込まれたデータの個々の行を確認し、そのデータが関連付けられたデータ モデル オブジェクトに正しくマッピングされていることを検証できます。ユーザーはまた、データ モデル オブジェクトのフィールドに対して変更を加えることもできます。例えば、フィールドの追加や削除、フィールド タイプの変更、または数式フィールドの作成などが可能です。データクラウド ユーザー パーミッション セットは、データストリームの作成、セグメントの作成、アクティベーションの作成、またはユーザーの管理など、他のデータクラウド機能やタスクへのアクセスを許可しません。他のパーミッション セットは、このユースケースには制限が厳しすぎたり、許可範囲が広すぎたりします。データクラウド マーケティング スペシャリスト パーミッション セットはセグメンテーションとアクティベーション機能へのアクセスを許可しますが、データ エクスプローラー機能へのアクセスは許可しません。Data Cloud Admin 権限セットは、Data Explorer 機能を含むすべての Data Cloud 機能とタスクへのアクセスを許可しますが、ユーザーが必要とする範囲を超えています。Data Cloud for Marketing Data Aware Specialist 権限セットは、Data Explorer 機能へのアクセスを許可しますが、このユースケースでは不要なセグメンテーションとアクティベーション機能へのアクセスも許可します。参照： Data Cloud 標準権限セット、Data Explorer、Data Cloud ユニットの設定 | H43: C | I43: ◾ 問題の背景： 新規ユーザーは、次のことだけを行いたい： 取り込まれたデータの個々の行（レコード）を確認 それが正しくデータモデル（DMO）にマッピングされているかを検証 必要に応じて小さな変更も可能にする → つまり、閲覧＋軽微な編集だけを行いたいユーザーに必要な**「最小限の権限セット」**を問う設問です。 ✅ 正解理由：「データクラウドユーザー」は基本的な作業を行える最小権限セット ▶ Data Cloud User 権限とは？ Data Cloud の標準機能にアクセス可能（例：データの確認、セグメントのプレビューなど） データの取り込み結果の確認や DMO モデルの検証が可能 一部編集も可能で、完全な管理者権限は不要 ❌ 他の選択肢の誤り： 選択肢 評価 誤りの理由 A. マーケティング スペシャリスト向けのデータクラウド ❌ 不適 セグメント・アクティベーションなど マーケ施策用に特化しており、モデル検証に過剰 B. データクラウド管理者 ❌ 不適 すべての権限を含む管理者権限。検証作業だけでは 不要かつ過剰 C. データクラウドユーザー ✅ 正解 最小限の権限で、取り込みデータの閲覧・確認・検証が可能 D. マーケティング データ認識スペシャリスト向けデータクラウド ❌ 不適 Consent管理・同意関連に特化した権限。この用途には合わない | J43: Salesforce.Data-Cloud-Consultant-JPN.v2024-09-12.q66 | K43: 17 | M43: *
B44: 90 | C44: ◯ | D44: 02_Data Cloud の設定と管理 | E44: コンサルタントはトランザクション データを含むデータ ストリームを設定しています。 コンサルタントは、確実に優れたフィールド タイプを選択する必要があります。 発注書番号のゼロは保持されますか? A. テキスト B. 数値 C. 10 進数 D. シリアル | F44: A | G44: フィールドタイプ「テキスト」を選択することで、購入注文番号の先頭のゼロが保持されます。 これは、テキストフィールドがアルファベットと数字を文字列として保存し、先頭や末尾の文字を削除しないためです。一方、数値、小数、シリアルフィールドは数値を数値として保存し、データを表示またはエクスポートする際、先頭のゼロを自動的に削除します123。したがって、購入注文番号、郵便番号、電話番号など、元の形式を保持する必要があるデータを格納するには、テキストフィールドが適しています。参照： * フィールドの先頭のゼロがデータエクスポートで省略される * CSVファイルをインポートする際、最初の『0』を保持する * ゼロで始まるまたはプラス記号を含む住所フィールドのインポートとエクスポート | H44: A | I44: ◾ 問題の焦点： コンサルタントは「発注書番号（例：00012345）」のように ゼロで始まる識別子を Data Cloud に取り込もうとしています。 → 「ゼロが保持される」データ型はどれか？ を問う設問です。 ✅ 正解理由：「テキスト型」で取り込めば、先頭のゼロはそのまま保持される ▶ テキスト型（Text）フィールドの特性： 文字列として扱われるため、数値変換が行われない 00012345 のような値も “文字列としてそのまま” 保存・表示される 識別子やコード、番号の管理には最適 ❌ 他の選択肢の誤り： 選択肢 評価 理由 A. テキスト ✅ 正解 ゼロ始まりでも文字列として 変化せず保持される B. 数値（Number） ❌ 不正解 00012345 → 12345 に変換されてしまい、先頭ゼロが消える C. 10進数（Decimal） ❌ 不正解 小数点付きの数値型 → ゼロが削除される＋余計な変換が発生する D. シリアル（Serial） ❌ 不正解 自動採番的な用途で使われる特殊フィールド → 明示的に値を指定するには不適 | J44: Salesforce.Data-Cloud-Consultant-JPN.v2024-09-12.q66 | K44: 56 | M44: *
B45: 94 | C45: ◯ | D45: 02_Data Cloud の設定と管理 | E45: ノーザン トレイル アウトフィッターズは、Marketing Cloud スターター データ バンドルを使用して、Marketing Cloud データを Data Cloud に取り込みます。 Marketing Cloud スターター データ バンドルで利用可能な 2 つのデータセットは何ですか? 2 つの答えを選択してください A. パーソナライゼーション B. モバイルコネクト C. ロイヤリティ管理 D. モバイルプッシュ | F45: B, D | G45: マーケティングクラウド スターター データ バンドルは、マーケティングクラウドからデータ クラウド1にデータを簡単に取り込むことができる事前定義されたデータ バンドルです。マーケティングクラウド スターター データ バンドルで利用可能なデータセットは、Email、MobileConnect、および MobilePush2 です。これらのデータセットには、メール、SMS、プッシュ通知2 などのマーケティングクラウドのチャネルから収集されたエンゲージメント イベントとメトリクスが含まれています。これらのデータセットを使用することで、マーケティングクラウドのデータでデータクラウドのデータモデルを強化し、マーケティングキャンペーンやジャーニーに基づいてセグメントやアクティベーションを作成できます1。他のオプションは、マーケティングクラウド スターター データ バンドルで利用可能なデータセットではないため、正答ではありません。オプションAは誤りです。なぜなら、パーソナライゼーションはデータセットではなく、Marketing Cloudの機能であり、オーディエンスに合わせてコンテンツやメッセージをカスタマイズする機能です3。オプションCは誤りです。なぜなら、Loyalty Managementはデータセットではなく、Marketing Cloudの製品であり、顧客向けのロイヤルティプログラムを作成・管理する機能です4。参照：Data Cloud内のMarketing Cloud Starter Data Bundles、データソースの接続、Marketing Cloudでのパーソナライゼーション、Marketing CloudでのLoyalty Management | H45: B, D | I45: ◾ 背景： Marketing Cloud のデータを Salesforce Data Cloud に統合するためには、「Marketing Cloud スターター データバンドル（Starter Data Bundle）」を使うのが一般的です。 このバンドルは Marketing Cloud の標準チャネルにおけるユーザー行動・エンゲージメントデータの取り込みを可能にします。 ✅ 正解理由： Marketing Cloud スターターバンドルに含まれる代表的なデータセットは以下のとおり： データセット名 含まれているか 説明 ✅ モバイルコネクト（MobileConnect） ✔️ SMS の送信・受信・配信状況など ✅ モバイルプッシュ（MobilePush） ✔️ モバイルアプリ通知関連のデータ ❌ パーソナライゼーション ✖️ **別製品（Marketing Cloud Personalization）**で、別コネクタが必要 ❌ ロイヤリティ管理 ✖️ 標準バンドルには含まれない。外部統合またはカスタム実装が必要 ❌ 他の選択肢の誤り： 選択肢 評価 理由 A. パーソナライゼーション ❌ **Personalization（旧 Interaction Studio）**は別コネクタで統合。スターターバンドルには含まれない B. モバイルコネクト ✅ SMS関連のデータを取り込む代表的データセット C. ロイヤリティ管理 ❌ 標準では提供されない。ロイヤリティ系は外部カスタム連携が多い D. モバイルプッシュ ✅ モバイル通知関連データとして標準で含まれる | J45: Salesforce.Data-Cloud-Consultant-JPN.v2024-09-12.q66 | K45: 59 | M45: *
B46: 97 | C46: ◯ | D46: 02_Data Cloud の設定と管理 | E46: Data Cloud は、前日のすべての e コマース トランザクションのファイルを毎晩受信します。 いくつかのセグメントとアクティベーションは、顧客のスケジュールされたキャンペーン メッセージの正確性を維持するために、更新されたデータから計算された洞察に依存します。 スケジュールされたアクティベーションごとに e コマース データを確実に使用できるようにするには、コンサルタントは何をすべきでしょうか? A. フローを使用して e コマース データの変更データ イベントをトリガーし、アクティベーションの実行がスケジュールされる前に、計算された分析情報とセグメントを更新します。 B. 計算された分析情報が 1 時間ごとに発生するように更新スケジュールを設定します。 C. アクティベーションが増分アクティベーションに設定されていることを確認し、1 時間ごとに自動的に公開します。 D. セグメントが高速パブリッシュに設定され、1 時間ごとに更新されるように設定されていることを確認します。 | F46: A | G46: コンサルタントが、各スケジュールされたアクティベーションにおいてECデータが使用可能な状態を確保するために取るべき最良のオプションはA. Flowを使用してECデータに対して変更データイベントをトリガーし、アクティベーションが実行される前に計算されたインサイトとセグメントをリフレッシュする。このオプションにより、コンサルタントはData CloudのFlow機能を利用でき、イベントやスケジュールに基づいてデータ処理タスクの自動化とオーケストレーションを実現できます。Flowは、ECデータに対して変更データイベントをトリガーするために使用できます。このイベントは、データが更新または変更されたことを示すイベントの一種です。このイベントは、ECデータに依存する計算済みインサイトとセグメントの更新をトリガーし、最新のデータを反映するようにします。計算済みインサイトとセグメントの更新は、アクティベーションがスケジュールされた実行前に完了するため、顧客のスケジュールされたキャンペーンメッセージが正確で関連性のあるものになります。 他のオプションはオプションAほど優れていません。オプションBは誤りです。計算されたインサイトの更新スケジュールを1時間ごとに設定しても、十分または効率的でない可能性があります。更新スケジュールがアクティベーションスケジュールと一致しない場合、古いまたは一貫性のないデータが生じる可能性があります。また、ECデータが1時間ごとに変更されない場合、更新スケジュールは不要なリソースや時間を消費する可能性があります。オプションCは誤りです。アクティベーションを「Incremental Activation」に設定し、自動的に毎時間公開するようにしても、問題が解決しない可能性があります。Incremental Activationは、セグメント内の新しいまたは変更されたレコードのみをアクティベートする機能で、アクティベーションの時間とサイズを削減します。ただし、この機能は、セグメントデータがECデータに基づいて更新またはリフレッシュされることを保証しません。アクティベーションスケジュールがECデータ更新スケジュールと一致しない場合、不正確または関連性のないキャンペーンメッセージが送信される可能性があります。オプションDは正しくない理由は、セグメントをRapid Publishに設定し、1時間ごとにリフレッシュするように設定しても、最適または効果的ではない可能性があるためです。Rapid Publishは、重複レコードのチェックや無効な値の検証などの一部の検証ステップをスキップすることで、セグメントを迅速に公開する機能です。ただし、この機能はセグメントデータの品質や正確性を損なう可能性があり、すべてのユースケースに適しているとは限りません。リフレッシュスケジュールもオプションBと同様の問題を抱える可能性があります。ECデータ更新スケジュールやアクティベーションスケジュールと同期しないため、古いまたは一貫性のないデータが生じる可能性があります。参考文献： Salesforce Data Cloud Consultant Exam Guide、Flow、Change Data Events、Calculated Insights、Segments、［Activation］ | H46: A | I46: ◾ 問題の背景： Data Cloud は毎晩、前日の eコマーストランザクションデータを受信しています。 一部のセグメントやアクティベーションはその 更新データをもとに計算されたインサイト（例：購入金額合計、最近の購入日時など）に依存。 正確なキャンペーン実行のためには、「最新のデータを反映した状態でセグメントとアクティベーションを行う」必要があります。 ✅ 正解理由： ▶ A. フローによるトリガーと順序制御が最も確実 Salesforce Flow や Data Cloud のワークフロー機能を用いて： eコマースデータが取り込まれた「変更イベント（Change Data Event）」をトリガーとし、 それに連動して「計算されたインサイト」「セグメント」「アクティベーション」の更新・順序実行を設定する これにより、常に最新データに基づいたアクティベーションが保証され、 スケジュール誤差やズレによる 古い情報での配信を防げる。 ❌ 他の選択肢の誤り： 選択肢 評価 理由 A. フローで更新を制御する ✅ 最新データが確実に使われるよう、順序と依存関係を制御できる最善手段 B. 計算された分析を1時間ごとに更新 ❌ 更新タイミングが不確実で、eコマースデータ取り込みのタイミングと合わない可能性 C. 増分アクティベーションを1時間ごとに自動実行 ❌ アクティベーションだけ更新しても、計算インサイトやセグメントが更新されていなければ意味がない D. 高速パブリッシュを1時間ごとに更新 ❌ 同様に、インサイトや基礎データが更新されていなければ不正確なままでリスクあり | J46: Salesforce.Data-Cloud-Consultant-JPN.v2024-09-12.q66 | K46: - | M46: *
B47: 124 | C47: ◯ | D47: 02_Data Cloud の設定と管理 | E47: 組織は、在庫レベルを在庫管理システムからデータ クラウドに、高速かつスケーラブルでほぼリアルタイムの方法でストリーミングするには何を使用する必要がありますか? A. クラウド ストレージ コネクタ B. コマース クラウド コネクタ C. 取り込み API D. Marketing Cloud パーソナライゼーション コネクタ | F47: C | G47: Ingestion API は、あらゆるソースからデータを Data Cloud に高速かつスケーラブルにストリーム送信できる RESTful API です。Ingestion API を使用すると、在庫管理システムからデータを JSON オブジェクトとして Data Cloud に送信し、その後 Data Cloud を使用して在庫データに基づくデータモデル、セグメント、インサイトを作成できます。Ingestion API はバッチモードとストリーミングモードの両方をサポートし、最大 100,000件/秒の処理が可能です。Ingestion APIは、データ検証、暗号化、圧縮、リトライメカニズムなどの機能を提供し、データ品質とセキュリティを確保します。 参照： Ingestion API開発者ガイド、Data Cloudへのデータインジェスト | H47: C | I47: ◾ 問題の背景： 組織は、在庫管理システムからData Cloudに対して、 高速（リアルタイム性） スケーラブル（大量データ対応） な方法で在庫レベルのデータをストリーミングしたいと考えています。 ✅ 正解理由： ▶ C. 取り込み API（Ingestion API） Salesforce Data Cloud の Ingestion API は、構造化データをリアルタイムまたはニアリアルタイムでストリーミング取り込みするための公式手段です。 外部システム（今回のように在庫管理システム）から直接、スケーラブルにデータを送信する用途に最適です。 イベント駆動やバッチではなく、即時性が求められる在庫情報の更新に対して有効です。 ❌ 他の選択肢の誤り： 選択肢 評価 理由 A. クラウド ストレージ コネクタ ❌ 主にS3やGoogle Cloud Storageなどのファイルベースの一括取り込みに使われる。リアルタイムではない。 B. コマース クラウド コネクタ ❌ Salesforce Commerce Cloud 専用のデータ連携用で、在庫管理システム一般とは無関係。 D. Marketing Cloud パーソナライゼーション コネクタ ❌ パーソナライズのためのユーザービヘイビアデータ取り込みに使うもので、在庫レベルのストリーミングとは無関係。 | J47: Salesforce.Data-Cloud-Consultant-JPN.v2024-09-12.q66 | K47: 62 | M47: *
B48: 131 | C48: ◯ | D48: 02_Data Cloud の設定と管理 | E48: Data Cloud の Web およびモバイル アプリケーション コネクタに関する記述のうち、正しいものはどれですか? A. イベント、プロファイル、トランザクション データを含む標準スキーマは、コネクタの構成時に作成されます。 B. テナント固有のエンドポイントは、コネクタの設定時に Data Cloud で自動生成されます。 C. コネクタに関連付けられたデータ ストリームは、データ クラウド セットアップからアプリを削除すると自動的に削除されます。 D. コネクタ スキーマを更新して、既存のフィールドを削除できます。 | F48: B | G48: Webとモバイル アプリコネクタを使用すると、ウェブサイトとモバイル アプリからデータをData Cloudにインポートできます。このコネクタを使用するには、Data CloudでTenant Specific Endpoint（TSE）を設定する必要があります。TSEは、Data Cloud組織を識別する一意のURLです。TSEは、Data Cloud設定でコネクタアプリを作成する際、自動的に生成されます。TSE を使用して、ウェブサイトとモバイルアプリの SDK を設定できます。これにより、TSE 経由でデータが Data Cloud に送信されます。参照： Web とモバイル アプリケーション コネクタ、ウェブサイトとモバイル アプリを接続する、Web またはモバイル アプリ データ ストリームを作成する | H48: B | I48: ◾ Web およびモバイル アプリケーション コネクタとは： Salesforce Data Cloud における Web およびモバイル アプリケーション コネクタは、**リアルタイムイベント（例：ページビュー、クリック、アプリ内行動など）**を Data Cloud に取り込むための仕組みです。 これにより、行動データをプロファイルに紐付けて、パーソナライズやセグメンテーションに活用できます。 ✅ 正解理由： ▶ B. テナント固有のエンドポイントは、コネクタの設定時に Data Cloud で自動生成されます。 Web / モバイルアプリケーションコネクタを設定すると、**Salesforceが自動的にユニークなテナント専用のエンドポイント URL（Ingestion Endpoint）**を生成します。 このエンドポイントは、JavaScript SDK やモバイル SDK からのイベント送信先になります。 これにより、他の組織のデータと混同されることなく、自社の環境だけにイベントデータが取り込まれます。 ❌ 他の選択肢の誤り： 選択肢 評価 理由 A. 標準スキーマはコネクタ構成時に作成される ❌ スキーマは事前に設計されたテンプレートが提供されるが、構成時に自動生成されるわけではない。 C. アプリを削除するとデータ ストリームも削除される ❌ データストリームは手動で削除する必要がある。アプリ削除とストリーム削除は連動しない。 D. コネクタスキーマを更新して既存のフィールドを削除できる ❌ 一度作成したフィールドは削除できない仕様。新規フィールドの追加は可能だが、削除は不可。 | J48: Salesforce.Data-Cloud-Consultant-JPN.v2024-09-12.q66 | K48: - | M48: *
B49: 150 | C49: × | D49: 02_Data Cloud の設定と管理 | E49: Data Cloud の新規ユーザーは、取り込んだデータの個々の行を確認し、リンクされたデータ モデル オブジェクトに正常にモデル化されていることを検証できれば十分です。ユーザーは必要に応じて変更を加える必要もあります。 このユースケースに対応するために必要な最小限の権限セットは何ですか? A. マーケティングスペシャリスト向けデータクラウド B. データクラウド管理者 C. データクラウドユーザー D. マーケティング データ アウェア スペシャリスト向けデータ クラウド | F49: C | G49: Data Cloud ユーザー権限セットは、このユースケースに対応するために必要な最小限の権限セットです。Data Cloud ユーザー権限セットは、Data Explorer 機能へのアクセスを許可します。これにより、ユーザーは取り込んだデータの個々の行を確認し、リンクされたデータ モデル オブジェクトに正常にモデル化されていることを検証できます。また、ユーザーは、フィールドの追加や削除、フィールド タイプの変更、数式フィールドの作成など、データ モデル オブジェクト フィールドに変更を加えることもできます。Data Cloud ユーザー権限セットは、データ ストリームの作成、セグメントの作成、アクティベーションの作成、ユーザーの管理など、他の Data Cloud 機能やタスクへのアクセスを許可しません。他の権限セットは、このユースケースには制限が厳しすぎるか、または制限が厳しすぎます。Data Cloud for Marketing Specialist 権限セットは、セグメンテーション機能とアクティベーション機能へのアクセスのみを許可し、Data Explorer 機能へのアクセスは許可しません。Data Cloud 管理者権限セットは、Data Explorer 機能を含むすべての Data Cloud 機能とタスクへのアクセスを許可しますが、ユーザーの必要以上のものです。 Data Cloud for Marketing Data Aware Specialist 権限セットは、データ エクスプローラー機能へのアクセスを許可しますが、このユース ケースに必要のないセグメンテーション機能とアクティベーション機能へのアクセスも許可します。参照: Data Cloud 標準権限セット、データ エクスプローラー、Data Cloud ユニットの設定 | H49: C | I49: ◾ 背景： このシナリオでは、新規ユーザーが必要とする機能は以下のとおりです： 取り込んだデータの各行（レコード）を確認する データが正しくリンクされたデータモデルオブジェクト（DMO）にマッピングされているかを検証する 必要に応じて変更（例：マッピング調整やデータ確認）を加える このような基本的なデータ確認とモデル検証作業を実施するには、フル管理権限までは不要ですが、Data Cloud の主要機能へのアクセス権は必要です。 ✅ 正解理由： ▶ C. データクラウドユーザー（Data Cloud User） Data Cloud User 権限セットは、以下のような機能にアクセスできる「最小限かつ実用的なユーザー権限」です： データストリームの参照と確認 DMO（データモデルオブジェクト）へのアクセス データインスペクション（レコード表示） セグメントや計算された洞察の確認（作成は不可） このレベルの権限で、取り込んだデータの検証および簡単な変更作業に対応可能です。 ❌ 他の選択肢の誤り： 選択肢 評価 理由 A. マーケティングスペシャリスト向けデータクラウド ❌ Marketing Cloud との連携・パーソナライズ用途向けの限定的権限であり、データ確認やDMO検証には不十分。 B. データクラウド管理者（Admin） ❌ フルアクセス可能だが、「最小限の権限」を求めるユースケースには過剰。 D. マーケティング データ アウェア スペシャリスト向けデータ クラウド ❌ 特定のアクティベーション作業（マーケキャンペーン用）に特化した権限であり、データモデル検証には不適。 | J49: Salesforce.Data-Cloud-Consultant.v2024-12-02.q93 | K49: 17 | M49: *
B50: 169 | C50: ◯ | D50: 02_Data Cloud の設定と管理 | E50: Data Cloud の Web およびモバイル アプリケーション コネクタに関する正しい記述はどれですか? A. コネクタが構成されると、イベント、プロファイル、およびトランザクション データを含む標準スキーマが作成されます。 B. コネクタを設定すると、テナント固有のエンドポイントが Data Cloud で自動生成されます。 C. Data Cloud セットアップからアプリを削除すると、コネクタに関連付けられているすべてのデータ ストリームが自動的に削除されます。 D. コネクタ スキーマを更新して、既存のフィールドを削除できます。 | F50: B | G50: Web およびモバイル アプリケーション コネクタを使用すると、Web サイトやモバイル アプリから Data Cloud にデータを取り込むことができます。このコネクタを使用するには、Data Cloud でテナント固有のエンドポイント (TSE) を設定する必要があります。これは、Data Cloud 組織を識別する一意の URL です。TSE は、Data Cloud セットアップでコネクタ アプリを作成すると自動的に生成されます。その後、TSE を使用して Web サイトやモバイル アプリの SDK を構成し、TSE 経由で DataCloud にデータを送信できます。参照: Web およびモバイル アプリケーション コネクタ、Web サイトとモバイル アプリの接続、Web またはモバイル アプリのデータ ストリームの作成 | H50: B | I50: ◾ Web およびモバイル アプリケーション コネクタとは？ Salesforce Data Cloud における Web やモバイルアプリからのイベントデータの取り込みを可能にするコネクタです。 これにより、ユーザーの閲覧行動・クリック・トランザクションなどをリアルタイムで Data Cloud に送信・統合できます。 ✅ 正解理由： ▶ B. コネクタを設定すると、テナント固有のエンドポイントが Data Cloud で自動生成されます。 コネクタをセットアップすると、そのData Cloud組織に固有のREST APIエンドポイントが作成されます。 このエンドポイントは、Web／モバイルSDKなどからイベントデータを送信するために利用されます。 データ形式や認証情報も含めて、構成ウィザードから一貫して提供される点が特徴です。 ❌ 他の選択肢の誤り： 選択肢 評価 誤りの内容 A. 標準スキーマが作成される ❌ スキーマ（DMOやDLO）は自動生成されず、ユーザーがイベントタイプごとに定義する必要があります。 C. アプリ削除でストリームも削除される ❌ アプリ削除はコネクタ情報のみを削除し、データストリーム（接続構成）は手動で削除が必要です。 D. コネクタスキーマで既存フィールドを削除可能 ❌ 一度保存したスキーマから既存のフィールドは削除不可です。拡張（追加）は可能ですが、削除には制限があります。 | J50: Salesforce.Data-Cloud-Consultant.v2024-12-02.q93 | K50: 131 | M50: *
B51: 178 | C51: ◯ | D51: 02_Data Cloud の設定と管理 | E51: 組織は、在庫管理システムからデータ クラウドに在庫レベルを高速かつスケーラブルに、ほぼリアルタイムでストリーミングするために何を使用すればよいでしょうか。 A. クラウド ストレージ コネクタ B. コマースクラウドコネクタ C. 取り込みAPI D. マーケティング クラウド パーソナライゼーション コネクタ | F51: C | G51: Ingestion APIは、あらゆるソースからデータを高速かつスケーラブルにデータクラウドにストリーミングできるRESTful APIです。Ingestion APIを使用して、在庫管理システムからJSONオブジェクトとしてデータクラウドにデータを送信し、データクラウドを使用して在庫データに基づいてデータモデル、セグメント、およびインサイトを作成できます。Ingestion APIはバッチモードとストリーミングモードの両方をサポートしており、最大で 100,000件/秒のレコード。Ingestion APIは、データ検証、暗号化、圧縮、再試行メカニズムなどの機能も提供し、データの品質とセキュリティを確保します。参考資料: Ingestion API開発者ガイド、データクラウドへのデータの取り込み | H51: C | I51: ◾ 質問の要点： 「在庫管理システムから在庫レベルを リアルタイムかつスケーラブルに Data Cloud に連携するには？」 つまり、頻繁に更新されるデータ（在庫数量など）を即座に Data Cloud に送り込む仕組みが必要です。 ✅ 正解理由： ▶ 取り込み API（Ingestion API） Salesforce Data Cloud の リアルタイムストリーミングAPI のひとつ。 特徴： 高速かつスケーラブルなイベント/レコード取り込みが可能 カスタムアプリケーションや外部システム（在庫管理システムなど）から直接呼び出してデータを送信可能 バッチ処理不要 → ほぼリアルタイム反映 例：在庫が減った瞬間にその情報を即時に Data Cloud に送り、関連セグメントやアクションに反映できる。 ❌ 他の選択肢の誤り： 選択肢 理由 A. クラウド ストレージ コネクタ ❌ S3やAzure Blobなどに保存されたファイルバッチを定期的に取り込む方式。リアルタイム性はない。 B. コマースクラウドコネクタ ❌ Salesforce Commerce Cloud 専用。在庫管理システムとは直接関係がない。 D. マーケティング クラウド パーソナライゼーション コネクタ ❌ 顧客の行動データなどにフォーカスしており、在庫情報の取り込み用途には適さない。 | J51: Salesforce.Data-Cloud-Consultant.v2024-12-02.q93 | K51: 62 | M51: *
B52: 181 | C52: ◯ | D52: 02_Data Cloud の設定と管理 | E52: コンサルタントはトランザクションデータを含むデータストリームを設定しています。 コンサルタントは、どのフィールドタイプを選択すべきでしょうか？ 注文番号のゼロは保持されますか? A. テキスト B. 数値 C. 10進数 D. シリアル | F52: A | G52: 発注番号の先頭のゼロが保持されるようにするには、フィールド タイプとしてテキストを選択する必要があります。 これは、テキスト フィールドでは英数字が文字列として保存され、先頭または末尾の文字が削除されないためです。一方、数値、小数点、シリアル フィールドでは数値が数値として保存され、データの表示またはエクスポート時に先頭のゼロが自動的に削除されます123。したがって、テキスト フィールドは、発注書番号、郵便番号、電話番号など、元の形式を維持する必要があるデータを保存するのに適しています。参考資料: * フィールドの先頭のゼロはデータエクスポートで省略されるようです * CSV ファイルをインポートするときに最初の '0' を保持する * ゼロで始まる、またはプラス記号を含む住所フィールドをインポートおよびエクスポートします | H52: A | I52: ◾ 質問の背景： コンサルタントは、**注文番号（Order Number）**を含むトランザクションデータを Data Cloud に取り込もうとしています。 ここで問われているのは： 「注文番号の ゼロ（0） を保持するために適切なフィールドタイプはどれか？」 ✅ 正解理由： ▶ 注文番号は ID（識別子）扱い であり、計算には使わない 例：00012345 や 0123456789 数値型で扱うと、先頭のゼロは削除される → 12345 に変換されてしまう ▶ これを避けるために最も適切なのが テキスト型（文字列） 文字列として扱えば、先頭ゼロもそのまま保持される また、IDやコード、識別子として使うデータは 常にテキスト型を推奨 ❌ 他の選択肢の誤り： 選択肢 評価 誤りの理由 B. 数値 ❌ 先頭のゼロが削除される（例：000123 → 123） C. 10進数 ❌ 同上、数値処理されるためゼロが失われる D. シリアル ❌ Salesforce Data Cloud における標準フィールドタイプではない or 該当なし | J52: Salesforce.Data-Cloud-Consultant.v2024-12-02.q93 | K52: 56 | M52: *
B53: 193 | C53: ◯ | D53: 02_Data Cloud の設定と管理 | E53: Data Cloud の Web およびモバイル アプリケーション コネクタに関する次の記述のうち正しいものはどれですか。 A. コネクタが構成されると、イベント、プロファイル、およびトランザクション データを含む標準スキーマが作成されます。 B. コネクタを設定すると、テナント固有のエンドポイントが Data Cloud で自動生成されます。 C. Data Cloud セットアップからアプリを削除すると、コネクタに関連付けられているすべてのデータ ストリームが自動的に削除されます。 D. コネクタ スキーマを更新して、既存のフィールドを削除できます。 | F53: B | G53: Web およびモバイル アプリケーション コネクタを使用すると、Web サイトやモバイル アプリから Data Cloud にデータを取り込むことができます。このコネクタを使用するには、Data Cloud でテナント固有のエンドポイント (TSE) を設定する必要があります。これは、Data Cloud 組織を識別する一意の URL です。TSE は、Data Cloud セットアップでコネクタ アプリを作成すると自動的に生成されます。その後、TSE を使用して Web サイトやモバイル アプリの SDK を構成し、TSE 経由で Data Cloud にデータを送信できます。参照: Web およびモバイル アプリケーション コネクタ、Web サイトとモバイル アプリの接続、Web またはモバイル アプリのデータ ストリームの作成 | H53: B | I53: ◾ Web およびモバイル アプリケーション コネクタとは？ Salesforce Data Cloud の Web & モバイルアプリケーションコネクタは、ウェブやモバイルアプリからリアルタイムでイベント・データを取り込むための仕組みです。 これらのコネクタを設定する際に、テナント（組織）固有のエンドポイントURL が自動的に作成され、それを通じてイベント（例：ページ閲覧、クリック、ログインなど）を送信します。 ✅ 正解の理由： ▶ B. コネクタを設定すると、テナント固有のエンドポイントが Data Cloud で自動生成されます。 ✅ コネクタの構成完了時に、自社専用のイベント受信用 API エンドポイントが生成され、開発者がそれを使用してイベントデータを送信できます。 ❌ 他の選択肢の誤り： 選択肢 評価 理由 A. 標準スキーマが作成される ❌ 自動的に作成されるのはスキーマではなくエンドポイント。スキーマは手動構成または送信データに基づいてマッピングが必要です。 C. アプリを削除するとデータストリームも削除される ❌ アプリの削除はデータストリームを自動削除しません。手動での管理が必要です。 D. 既存のフィールドを削除できる ❌ 一度作成されたフィールドは削除できず、新しいバージョンを作る必要があります。 | J53: Salesforce.Data-Cloud-Consultant.v2024-12-02.q93 | K53: 131 | M53: *
B54: 194 | C54: ◯ | D54: 02_Data Cloud の設定と管理 | E54: Data Cloud は、前日のすべての電子商取引トランザクションのファイルを夜間に受信します。 顧客のスケジュールされたキャンペーン メッセージの正確性を維持するために、いくつかのセグメントとアクティベーションは、更新されたデータから計算された洞察に依存します。 スケジュールされたアクティベーションごとに電子商取引データが使用可能であることを確認するために、コンサルタントは何をする必要がありますか? A. アクティベーションの実行がスケジュールされる前に、Flow を使用して e コマース データの変更データ イベントをトリガーし、計算されたインサイトとセグメントを更新します。 B. 計算された分析情報が 1 時間ごとに更新されるスケジュールを設定します。 C. アクティベーションが増分アクティベーションに設定され、1 時間ごとに自動的に公開されることを確認します。 D. セグメントが Rapid Publish に設定され、1 時間ごとに更新されるように設定されていることを確認します。 | F54: A | G54: コンサルタントが、スケジュールされた各アクティベーションで e コマース データが使用可能であることを確認するために実行する必要がある最善のオプションは、A です。アクティベーションの実行がスケジュールされる前に、フローを使用して e コマース データの変更データ イベントをトリガーし、計算されたインサイトとセグメントを更新します。このオプションにより、コンサルタントは Data Cloud のフロー機能を使用できます。この機能により、イベントまたはスケジュールに基づいてデータ処理タスクの自動化とオーケストレーションが可能になります。フローを使用して、e コマース データの変更データ イベントをトリガーできます。これは、データが更新または変更されたことを示すイベント タイプです。その後、このイベントによって、e コマース データに依存する計算されたインサイトとセグメントの更新がトリガーされ、最新のデータが反映されます。計算されたインサイトとセグメントの更新は、アクティベーションの実行がスケジュールされる前に完了できるため、顧客のスケジュールされたキャンペーン メッセージが正確で関連性のあるものになります。 他のオプションは、オプション A ほど良くありません。オプション B は、計算されたインサイトの更新スケジュールを 1 時間ごとに設定しても十分または効率的ではない可能性があるため、正しくありません。更新スケジュールがアクティベーション スケジュールと一致しない場合があり、その結果、データが古くなったり一貫性がなくなったりする可能性があります。また、e コマース データは 1 時間ごとに変更されない可能性があるため、更新スケジュールによって必要以上に多くのリソースと時間が消費される可能性があります。オプション C は、アクティベーションが増分アクティベーションに設定され、1 時間ごとに自動的に公開されるようにしても、問題が解決しない可能性があるため、正しくありません。増分アクティベーションは、セグメント内の新規または変更されたレコードのみをアクティブ化できる機能であり、アクティベーション時間とサイズを削減します。ただし、この機能では、セグメント データが e コマース データに基づいて更新または更新されることは保証されません。アクティベーション スケジュールが e コマース データの更新スケジュールと一致しない場合もあり、その結果、キャンペーン メッセージが不正確または無関係になります。オプション D は、セグメントが Rapid Publish に設定され、1 時間ごとに更新されるようにすることが最適または効果的ではない可能性があるため、正しくありません。 Rapid Publish は、重複レコードや無効な値のチェックなどの検証手順を省略することで、セグメントをより速く公開できる機能です。ただし、この機能はセグメント データの品質や精度を損なう可能性があり、すべてのユース ケースに適しているとは限りません。更新スケジュールもオプション B と同じ問題が発生する可能性があります。e コマース データの更新スケジュールやアクティベーション スケジュールと同期しない可能性があるため、データが古くなったり、一貫性がなくなったりする可能性があります。参考資料: Salesforce Data Cloud Consultant 試験ガイド、フロー、データ変更イベント、計算されたインサイト、セグメント、[アクティベーション] | H54: A | I54: ◾ 背景： Data Cloud は、前日の eコマース取引データを夜間にバッチで受信します。 このデータを元にした 計算されたインサイト（Calculated Insights） を使用して、 セグメントとアクティベーションが動作している（→ スケジュールされたメッセージ配信に使用）。 ❗このような場合、データ更新 → 計算 → セグメント更新 → アクティベーション の順で確実に処理される必要があります。 ✅ 正解理由： ▶ A. Flow（フロー）で順序制御 Salesforce Data Cloud の Flow（Data Cloud Flow） を活用することで、 eコマースデータの変更を検知（Change Data Event） → 計算されたインサイトを再計算 → セグメントの再評価 → アクティベーションのトリガー この一連の流れを 時間軸と順序に沿って自動化することが可能。 ❌ 他の選択肢の誤り： 選択肢 評価 理由 B. 計算されたインサイトを1時間ごとに更新 ❌ 頻度の設定だけでは データとの同期タイミングの保証ができない。不正確なセグメントが使われる可能性あり C. 増分アクティベーションを使う ❌ アクティベーションの種類の問題ではなく、前提データの準備が揃っていないことが課題 D. Rapid Publish に設定する ❌ Rapid Publish は 更新頻度の問題には対応しても、インサイト更新タイミングとは連動しない | J54: Salesforce.Data-Cloud-Consultant.v2024-12-02.q93 | K54: 97 | M54: *
B55: 200 | C55: ◯ | D55: 02_Data Cloud の設定と管理 | E55: Data Cloud は、前日のすべての電子商取引トランザクションのファイルを夜間に受信します。 顧客のスケジュールされたキャンペーン メッセージの正確性を維持するために、いくつかのセグメントとアクティベーションは、更新されたデータから計算された洞察に依存します。 スケジュールされたアクティベーションごとに電子商取引データが使用可能であることを確認するために、コンサルタントは何をする必要がありますか? A. アクティベーションの実行がスケジュールされる前に、Flow を使用して e コマース データの変更データ イベントをトリガーし、計算されたインサイトとセグメントを更新します。 B. 計算された分析情報が 1 時間ごとに更新されるスケジュールを設定します。 C. アクティベーションが増分アクティベーションに設定され、1 時間ごとに自動的に公開されることを確認します。 D. セグメントが Rapid Publish に設定され、1 時間ごとに更新されるように設定されていることを確認します。 | F55: A | G55: コンサルタントが、スケジュールされた各アクティベーションで e コマース データが使用可能であることを確認するために実行する必要がある最善のオプションは、A です。フローを使用して、e コマース データで変更データ イベントをトリガーし、アクティベーションの実行がスケジュールされる前に、計算されたインサイトとセグメントを更新します。このオプションにより、コンサルタントは Data Cloud のフロー機能を使用できます。この機能により、イベントまたはスケジュールに基づいてデータ処理タスクの自動化とオーケストレーションが可能になります。フローを使用して、e コマース データで変更データ イベントをトリガーできます。これは、データが更新または変更されたことを示すイベント タイプです。その後、このイベントにより、e コマース データに依存する計算されたインサイトとセグメントの更新がトリガーされ、最新のデータが反映されます。計算されたインサイトとセグメントの更新は、アクティベーションの実行がスケジュールされる前に完了できるため、顧客のスケジュールされたキャンペーン メッセージが正確で関連性のあるものになります。 他のオプションは、オプション A ほど良くありません。オプション B は、計算されたインサイトの更新スケジュールを 1 時間ごとに設定しても十分または効率的ではない可能性があるため、正しくありません。更新スケジュールがアクティベーション スケジュールと一致しない場合があり、その結果、データが古くなったり一貫性がなくなったりする可能性があります。また、e コマース データは 1 時間ごとに変更されない可能性があるため、更新スケジュールによって必要以上に多くのリソースと時間が消費される可能性があります。オプション C は、アクティベーションが増分アクティベーションに設定され、1 時間ごとに自動的に公開されるようにしても、問題が解決しない可能性があるため、正しくありません。増分アクティベーションは、セグメント内の新規または変更されたレコードのみをアクティブ化できる機能であり、アクティベーション時間とサイズを削減します。ただし、この機能では、セグメント データが e コマース データに基づいて更新または更新されることは保証されません。アクティベーション スケジュールが e コマース データの更新スケジュールと一致しない場合もあり、その結果、キャンペーン メッセージが不正確または無関係になります。オプション D は、セグメントが Rapid Publish に設定され、1 時間ごとに更新されるようにすることが最適または効果的ではない可能性があるため、正しくありません。 Rapid Publish は、重複レコードや無効な値のチェックなどの検証手順を省略することで、セグメントをより速く公開できる機能です。ただし、この機能はセグメント データの品質や精度を損なう可能性があり、すべてのユース ケースに適しているとは限りません。更新スケジュールもオプション B と同じ問題が発生する可能性があります。e コマース データの更新スケジュールやアクティベーション スケジュールと同期しない可能性があるため、データが古くなったり、一貫性がなくなったりする可能性があります。参考資料: Salesforce Data Cloud Consultant 試験ガイド、フロー、データ変更イベント、計算されたインサイト、セグメント、[アクティベーション] | H55: A | I55: ◾ 背景： 前日の電子商取引データ（トランザクション）が夜間バッチでData Cloudに取り込まれる。 この更新データに基づいて、計算されたインサイト（CI）やセグメントが更新され、 **スケジュールされたアクティベーション（メッセージ配信）**の精度に直結する。 つまり、アクティベーション時に最新データを元にしたセグメント／CIが使われていることが重要。 ✅ 正解理由： ▶ Flowと変更データイベント（CDE）の活用： Flow（データクラウドの自動実行ロジック）を用いることで、 新しいデータファイルの取り込みをトリガーとして、CIやセグメントの再計算を即時実行可能。 この仕組みにより、「アクティベーション前に」CIとセグメントが最新化されることが保証される。 → よって、夜間バッチでデータ取り込みが完了したタイミングで即座に更新処理が走り、キャンペーンの精度が維持される。 ❌ 他の選択肢の誤り： 選択肢 評価 理由 B. CIを1時間ごとに更新 ❌ 時間ベースの定期更新では、データ取り込み完了との同期が保証されないため、誤差や不整合が発生しうる。 C. 増分アクティベーションの自動公開 ❌ アクティベーションの頻度の話であり、元となるデータ（セグメント／CI）が最新でなければ意味がない。 D. Rapid Publishの設定 ❌ Rapid Publishはセグメントの早期反映には有効だが、CIやデータの取り込みトリガーではないため、目的に合わない。 🔧 補足： **Flow + CDE（Change Data Event）**の組み合わせは、特定イベントに連動した処理の実行が可能。 バッチデータが取り込まれた直後にCI・セグメントを更新 → それを使ってアクティベーション、という理想的なデータ連携フローを構築できる。 | J55: Salesforce.Data-Cloud-Consultant.v2024-12-02.q93 | K55: 97 | M55: *
B56: 50 | C56: ◯ | D56: 02_Data Cloud の設定と管理 | E56: データ ストリームを取り込むときに数式を作成する理由は何ですか? A. データストリームから重複したデータ行を削除する B. 既存のルールセットに一意の外部識別子を追加する C. ファイルを連結して正しい順序で取り込まれるようにする D. 日付時刻フィールドをデータマッピングで使用するためにデールフィールドに変換します | F56: D | G56: - | H56: D | I56: ◾ 問題の要点： 「データストリームを取り込むときに数式（Formula）を作成する理由は何か？」 Salesforce Data Cloud では、データストリーム取り込み時に「ストリーミングまたはバッチ変換」機能を使って、数式（formula）フィールドを定義できます。 これは主に、取り込み元データの整形・標準化・変換を目的としています。 ✅ なぜ「D」が正解なのか？ 日付／時刻に関して、Salesforce Data Cloud のデータマッピングでは以下の点が重要です： 一部の処理（特に セグメント作成 や 時間ベースのフィルタ）では、「Date（年月日）」型のフィールドが必要。 しかし多くの外部システム（例：JSON, CSV, APIなど）から取り込まれるのは 「Datetime（タイムスタンプ）」型の値。 このとき、Datetime → Date に変換する数式フィールドを定義することで、後続の処理で使えるようになる。 例： sql コピーする 編集する DATE(TIMESTAMP("2024-01-30T14:56:00Z")) → "2024-01-30" ❌ 他の選択肢の誤り： 選択肢 評価 誤りの理由 A. 重複データ行の削除 ❌ 不正解 これは数式ではなく、ID解決や主キー制御で対処すべき内容 B. ルールセットに識別子を追加 ❌ 不正解 IDルールセットは、ID解決設定で制御するもので、数式とは関係ない C. ファイルを連結して正しい順序で取り込む ❌ 不正解 ファイルの順序や結合はファイル設計・取り込み設定で制御され、数式での制御ではない D. 日付時刻→日付に変換する ✅ 正解 セグメンテーションやCIなど後続処理で使うために必須な前処理である | J56: Salesforce.Data-Cloud-Consultant-JPN.v2025-03-28.q66 | K56: - | M56: *
B57: 67 | C57: ◯ | D57: 02_Data Cloud の設定と管理 | E57: Cloud Kicks は、既存のデータ ストリームの 1 つとその基盤となるデータ レイク オブジェクト (DLO) を完全に削除する予定です。 データ ストリームを削除する前にコンサルタントは何を考慮すべきでしょうか? A. 基礎となる DLO はデータ変換で使用できます。 B. 基になる DLO をデータ モデル オブジェクトにマップできません。 C. データ ストリームはデータ キットに関連付ける必要があります。 D. 基になる DLO を暗黙的に削除せずにデータ ストリームを削除できます。 | F57: A | G57: データ ストリームとDLOs： Salesforce Data Cloudでは、データ ストリームを使用してデータを取得し、そのデータはData Lake Objects （DLOs） に格納されます。 削除時の考慮事項： データ ストリームを削除する前に、その基盤となるDLOの依存関係と使用状況を必ず確認してください。 データ変換の使用： * 削除の影響：基盤となるDLOがデータ変換で使用されている場合、データストリームを削除すると、そのDLOに依存するすべての変換に影響を与えます。 * 依存関係の確認：DLOが削除により中断される可能性のあるアクティブなデータ変換やプロセスの一部ではないことを確認してください。 参照： * Salesforce Data Cloud ドキュメント：データストリーム * Salesforce Data Cloud ドキュメント：データ変換 | H57: A | I57: Data Cloud コンサルタントがデータ ストリームとその基盤となるデータ レイク オブジェクト (DLO) を削除する前に考慮すべき事項として、ソースに基づくと以下の点が考えられます。 • データ ストリームはデータレイク・オブジェクト (DLO) を自動的に作成します。 • データレイク・オブジェクト (DLO) は、データ変換（ハーモナイゼーション）のプロセスで使用され、データモデル・オブジェクト (DMO) にマッピングされます。 • データ ストリームを削除すると、それによって作成された DLO も影響を受けると考えられ、その DLO を入力として使用しているデータ変換やその後のプロセス（計算済みインサイト、セグメント、アクティベーションなど）は影響を受けます。 提示された選択肢の中で、削除の前に考慮すべき妥当な影響を最もよく示唆しているのは、**A. 基礎となる DLO はデータ変換で使用できます。**という点です。これは、削除によってデータ変換が影響を受ける可能性があることを示唆しており、コンサルタントはその影響範囲を事前に確認する必要があります。 正解は A. 基礎となる DLO はデータ変換で使用できます。 | J57: Salesforce.Data-Cloud-Consultant-JPN.v2024-09-12.q66 | K57: 38 | M57: *
B58: 71 | C58: ◯ | D58: 02_Data Cloud の設定と管理 | E58: コンサルタントは、 携帯電話番号を含むプロファイル情報を含むデータ ストリームの取り込みを計画しています。 今後の SMS キャンペーンで電話番号を使用できるようにするには、電話番号フィールドが適切な E164 電話番号形式であることを確認する必要があります。ただし、ファイル内の電話番号の形式はさまざまであるようです。 さまざまな電話番号形式が標準化されていることを保証する最も効率的な方法は何ですか? A. 数式フィールドを作成して形式を標準化します。 B. Data Cloud に送信する前に、ソース システム内のデータを編集および更新します。 C. データ ストリームの作成時に PhoneNumber フィールド タイプを割り当てます。 D. 取り込み後に計算された分析情報を作成します。 | F58: C | G58: 電話番号のさまざまな形式を標準化するための最も効率的な方法は、データストリームを作成する際、PhoneNumber フィールドタイプを割り当てることです。PhoneNumber フィールドタイプは、電話番号を国際標準の E164 形式に自動的に変換する特別なフィールドタイプです。E164 形式は、プラス記号 （+）、国コード、および国内番号から構成されます。例えば、 +1-202-555-1234 は米国の電話番号のE164形式です。PhoneNumberフィールドタイプを使用することで、コンサルタントは電話番号の一貫性を確保し、今後のSMSキャンペーンで利用可能にできます。他のオプションは、より時間がかかったり、手動での介入が必要だったり、フォーマットの問題を解決しないものです。参照： データストリームフィールドタイプ、E164電話番号形式、Salesforce Data Cloud試験問題 | H58: C | I58: ◾ 問題の要点： コンサルタントは、携帯電話番号を含むプロファイル情報の取り込みを計画中。 **SMS キャンペーンで使用可能な形式（＝E.164形式）**である必要がある。 しかし、ソースデータ内の電話番号形式がバラバラで、統一されていない。 → 最も効率的にフォーマットを標準化できる方法はどれか？ ✅ 正解理由：PhoneNumber フィールドタイプは自動で E.164 形式を適用・検証する ▶ PhoneNumber 型とは？ Data Cloud のデータストリーム作成時に、カラムに「PhoneNumber」型を割り当てると： Salesforce側で E.164形式への変換とバリデーションが自動的に行われる 例：(415) 555-1234 → +14155551234 などに変換 不正な番号は取り込み時にエラーまたは無効として処理される ▶ メリット： ソース形式がバラバラでも、一括で統一された形式に変換される 設定はデータストリーム作成時のみで済むため、他の手法に比べて効率的 ❌ 他の選択肢の誤り： 選択肢 評価 理由 A. 数式フィールドで標準化 ❌ 不正解 数式では 文字列変換のロジックが煩雑かつ保守負荷が高い。PhoneNumber型の方が確実かつ簡単 B. ソース側で編集する ❌ 不効率 データソースが多数ある場合や外部管理されている場合は、非現実的・スケーラブルでない C. PhoneNumber フィールドタイプを割り当てる ✅ 正解 最も効率的で一括変換・検証可能な手段。推奨ベストプラクティス D. 取り込み後に計算された分析情報を作成 ❌ 不適切 CIは集計・分析目的であり、データの変換・正規化処理には不向き | J58: Salesforce.Data-Cloud-Consultant-JPN.v2024-09-12.q66 | K58: - | M58: *
B59: 75 | C59: ◯ | D59: 02_Data Cloud の設定と管理 | E59: アウトドア・ライフスタイル衣料品ブランドのノーザン・トレイル・アウトフィッターズ（NTO）は最近、新たな事業を開始した。この新事業はグルメなキャンプ料理に特化しています。ビジネス上の理由とセキュリティ上の理由から、NTO にとって、すべての Data Cloud データをブランドごとに分離しておくことが重要です。 データをブランドごとに分離したいという NTO の要望を最もよくサポートする機能はどれですか? A. 各ブランドのデータ ストリーム B. 各ブランドのデータ モデル オブジェクト C. 各ブランドのデータスペース D. 各ブランドのデータソース | F59: C | G59: データスペースは、ブランド、地域、製品、または事業部門などの異なる基準でデータを分離し整理するための論理的なコンテナです1。データスペースは、データアクセス、セキュリティ、ガバナンスの管理を支援し、クロスクラウドデータ統合と活用を可能にします2。NTOの場合、データスペースはブランドごとにデータを分離するニーズをサポートし、アウトドアライフスタイル衣料品とグルメキャンプ食品事業それぞれに異なるデータモデル、ルール、洞察を実現できます。データスペースは、NTOが異なるブランドに適用されるデータプライバシーとセキュリティ規制に準拠するのを支援します3。他のオプションは、データスペースと同じレベルのデータ分離と組織化を提供しないため、正しくないです。データストリームは、異なるソースからデータをデータクラウドに取り込むために使用されますが、ブランドごとにデータを分離しません4。データモデルオブジェクトは、データの構造と属性を定義するために使用されますが、ブランドごとにデータを隔離しません5。データソースは、データの起源と種類を特定するために使用されますが、ブランドごとにデータを分割しません。参照：データスペースの概要、データスペースの作成、データクラウドにおけるデータプライバシーとセキュリティ、データストリームの概要、データモデルオブジェクトの概要、［データソースの概要］ | H59: C | I59: ◾ 問題の背景： NTO は複数ブランド（例：アウトドアアパレル事業 ＋ グルメキャンプ事業）を展開しており、 ビジネス的・セキュリティ的な理由で、ブランド間のデータを完全に分離して管理したい。 → つまり、データの完全な分離管理（データスコープ、アクセス制御、リソース管理）を実現するにはどの機能が最適か？ ✅ 正解理由：「データスペース（Data Spaces）」はブランド単位でデータを完全分離できる仕組み ▶ データスペースとは？ Salesforce Data Cloud における**「ブランド・部門・地域ごとにデータやオブジェクトの境界を分ける」**機能 各データスペースには： 独立したデータストリーム 独立した DMO（データモデルオブジェクト） 独立したセグメント、アクティベーション、CI ユーザー権限もデータスペース単位で制御可能（例：Brand A の担当者は Brand B のデータにアクセス不可） ▶ なぜ Data Spaces が最適か？ 完全な論理分離を保証 セキュリティや管理要件に適合（PIIのブランド間共有も防げる） スケーラビリティもあり、大規模な組織におけるマルチブランド展開に最適 ❌ 他の選択肢の誤り： 選択肢 評価 誤りの理由 A. 各ブランドのデータストリーム ❌ 不十分 ストリームを分けても、内部では同じデータスペースに流れ込むため、完全な分離にならない B. 各ブランドのデータモデルオブジェクト ❌ 不十分 DMOを分けても、セキュリティスコープの分離ができない C. 各ブランドのデータスペース ✅ 正解 ブランド単位での完全なデータ境界とアクセス制御を提供する唯一の方法 D. 各ブランドのデータソース ❌ 不正解 データソース（例：SalesforceやS3）は単なる入力元であり、セキュリティ的な分離はできない | J59: Salesforce.Data-Cloud-Consultant-JPN.v2024-09-12.q66 | K59: - | M59: *
B60: 77 | C60: ◯ | D60: 02_Data Cloud の設定と管理 | E60: Cumulus Financial は、Data Cloud ユーザーのために国に基づいて Salesforce CRM アカウント データを分離したいと考えています。 これを達成するためにコンサルタントは何をすべきでしょうか? A. ストリーミング変換を使用して、国に基づいてアカウント データをフィルターし、それに応じて別のデータ モデル オブジェクトにマッピングします。 B. データ スペース機能を使用し、国に基づいてアカウント データ レイク オブジェクトにフィルターを適用します。 C. 取引先オブジェクトの Salesforce 共有ルールを使用して、国に基づいてレコードをフィルタリングおよび分離します。 D. アカウントの国フィールドに基づいて数式フィールドを使用して、受信レコードをフィルターします。 | F60: B | G60: データスペースは、データクラウドユーザーがフィルターと権限に基づいてデータのサブセットを作成できる機能です。データスペースは、地理、事業部門、製品ラインなど、異なる基準に基づいてデータを分離するために使用できます。この場合、コンサルタントはデータスペース機能を使用し、アカウントデータレイクオブジェクトに対して国を基準にフィルタリングを適用できます。これにより、データクラウドユーザーは各自の所属する国に属するアカウントデータのみにアクセスできます。参照： データスペース、データスペースの作成 | H60: B | I60: ◾ 問題の背景： Cumulus Financial は、国別に Salesforce CRM のアカウント（取引先）データを分離したい。 → つまり、Data Cloud 上で「国ごとに完全にデータを区切りたい」＝スコープ分離・セキュリティ・運用の境界を明確にしたいという要件です。 ✅ 正解理由：「データスペース（Data Spaces）」は国単位の分離に最適な仕組み ▶ Data Spaces の特徴： Salesforce Data Cloud の機能で、 ブランド 国・地域 部門 などの論理的区分でデータを分離できる 各データスペースは： 独立したデータストリーム・DLO・DMOを持てる ユーザーごとにアクセス制限を設定可能（例：米国担当者は米国データのみ閲覧可） ❌ 他の選択肢の誤り： 選択肢 評価 誤りの理由 A. ストリーミング変換で国ごとにDMOを分ける ❌ 技術的には可能だが不適切 フィルターやマッピングでは「完全な論理的分離」ができない（UI上は共存してしまう） B. データスペース機能を使用してDLOを国別に分離 ✅ 正解 完全にデータをスコープ単位で分離可能で、要件（国別分離）に最適 C. Salesforceの共有ルールを使う ❌ 不正解 これはCRM内の制御方法であり、Data Cloudのスコープ分離には関係しない D. 数式フィールドで国ごとにフィルタ ❌ 不正解 フィルターは可能でも、論理的な分離（セキュリティ、運用レベル）には不十分 | J60: Salesforce.Data-Cloud-Consultant-JPN.v2024-09-12.q66 | K60: - | M60: *
B61: 80 | C61: ◯ | D61: 02_Data Cloud の設定と管理 | E61: データ ストリームの削除を妨げる 2 つの依存関係はどれですか? 2 つの答えを選択してください A. 基盤となるデータ レイク オブジェクトがアクティブ化に使用されます。 B. 基礎となるデータ レイク オブジェクトはデータ変換で使用されます。 C. 基礎となるデータ レイク オブジェクトはデータ モデル オブジェクトにマップされます。 D. 基礎となるデータ レイク オブジェクトはセグメンテーションで使用されます。 | F61: B, C | G61: データクラウドでデータストリームを削除するには、その基盤となるデータレイクオブジェクト（DLO）が他のオブジェクトやプロセスへの依存関係や参照を持っていない必要があります。以下の2つの依存関係がデータストリームの削除を妨げます1： * データ変換： これは、取り込まれたデータをデータモデル用の標準化された形式と構造に変換するプロセスです。データ変換は、1つ以上のDLOを入力または出力として使用できます。データ変換でDLOが使用されている場合、データ変換が削除または変更されるまで、そのDLOは削除できません2。 * データモデルオブジェクト： これは、データモデル内のエンティティの種類や関係を表現するオブジェクトです。データモデルオブジェクトは、1つ以上のDLOにマッピングされてその属性と値を定義できます。DLOがデータモデルオブジェクトにマッピングされている場合、マッピングが削除または変更されるまで削除できません3。 参照： * 1： Salesforce Helpの「データストリームの削除」記事 * 2： Trailheadの「Data Cloudにおけるデータ変換」セクション * 3： Trailheadの「Data Cloudにおけるデータモデル」セクション | H61: B, C | I61: 選択肢とソース情報を照らし合わせると： • A. 基盤となるデータ レイク オブジェクトがアクティベーションに使用されます。 ◦ ソース は、活性化はセグメント（DMO を使用して作成される）をエンゲージメントプラットフォームに公開することであり、DMO を使用すると述べています。DLO が直接アクティベーションに使用されるという記述はソースに見当たりません。 • B. 基礎となるデータ レイク オブジェクトはデータ変換で使用されます。 ◦ ソース は、DLO がデータ変換プロセスで使用されることを示しています。例えば、ストリーミング変換はソースデータレイクオブジェクトを読み取り、レコードデータを再形成してターゲットデータレイクオブジェクトに書き込む と説明されています。バッチ変換も DLO または DMO を用いる とあります。DLO が変換の入力として使用されることは、強い依存関係となります。 • C. 基礎となるデータ レイク オブジェクトはデータ モデル オブジェクトにマップされます。 ◦ ソース は、データを取り込んだ後、データレイクオブジェクト (DLO) をデータモデルオブジェクト (DMO) にマッピングするプロセスを説明しています。ソース は、DLO を DMO にマッピングしなければならない と述べており、DLO が DMO の元データとして使用されるという重要な依存関係があります。 • D. 基礎となるデータ レイク オブジェクトはセグメンテーションで使用されます。 ◦ ソース は、セグメンテーションは DMO を使用すると述べています。DLO が直接セグメンテーションに使用されるという記述はソースに見当たりません。 Data Cloud のデータ処理フローを考えると、データ ストリームを削除するとその DLO が失われるため、その DLO に依存するプロセスは実行できなくなります。ソース情報から、DLO はデータ変換の入力として使用され、DMO へのマッピングの元データとなる ことが明確に示されています。これらのプロセスは、セグメンテーションや活性化を行うための DMO を作成する上で不可欠です。したがって、これらの依存関係がある場合にデータ ストリームの削除が妨げられる可能性が高いです。 Data Cloud においては、データを取り込み (データストリーム)、DLO を生成し、それを変換し、DMO にマッピングするというプロセスを経ることで、データがセグメンテーションや活性化に利用可能になります。この流れから、DLO がデータ変換や DMO マッピングの基盤となっていることがわかります。 したがって、データ ストリームの削除を妨げる 2 つの依存関係として、ソースの情報から最も直接的に支持されるのは以下の 2 つです。 • B. 基礎となるデータ レイク オブジェクトはデータ変換で使用されます。 • C. 基礎となるデータ レイク オブジェクトはデータ モデル オブジェクトにマップされます。 これらのプロセスが存在する場合、関連するデータ ストリームを削除することは、後続のデータ処理パイプラインを壊すことになるため、通常は許可されないか、依存関係を解消する必要があると考えられます。 | J61: Salesforce.Data-Cloud-Consultant-JPN.v2024-09-12.q66 | K61: - | M61: *
B62: 84 | C62: ◯ | D62: 02_Data Cloud の設定と管理 | E62: コンサルタントは、セグメント化したい従業員のリストを人事データベースから取り込んでいます。 このデータを取り込むときにコンサルタントはどのデータ ストリーム カテゴリを選択する必要がありますか? A. プロファイルデータ B. 連絡先データ C. その他のデータ D. エンゲージメントデータ | F62: C A | G62: データストリームのカテゴリ： * プロフィールデータ： 顧客のプロフィールとデモグラフィック情報。 * 連絡先データ： メールアドレスや電話番号などの連絡先情報。 * その他のデータ： 他のカテゴリに該当しない多様なデータ。 * エンゲージメントデータ： インタラクションデータと行動データ。 コンサルタントが人事データベースから従業員のリストをデータクラウドに取り込んでセグメント化する場合、取り込む際に選択すべきデータ ストリームのカテゴリは、プロファイルデータです。 ソースによると、Data Cloud において、データ ストリームは以下の3つのカテゴリのいずれかとして保存されます: • プロファイル: セグメント指定のデータセットに使用され、セグメンテーションの開始母集団として使用されるソースグループを含みます。 • エンゲージメント: 時系列指向のデータセットです。イベント時間フィールドはセットアップの一部であり、後で変更することはできません。もしそうでなければ、レコードが重複してしまう可能性があります。 • その他: プロファイルまたはエンゲージメントデータに関連するデータセットです。時系列フィールドを持たない時系列データを含みます。 人事データベースからの従業員リストは、個々の従業員に関する情報（例：氏名、従業員ID、部門など）を含むデータであり、これは個人の属性を表すプロファイルデータとして最も適切に分類されます。このデータは、従業員を対象としたセグメントを作成するために使用される可能性が高いと考えられ、ソースではプロファイルデータがセグメントに使用されると明確に述べられています。 データストリームを保存する際、データカテゴリ（プロファイル、エンゲージメント、その他）を慎重に選択する必要があり、保存した後に変更することはできません。したがって、従業員リストのような個人の属性情報は「プロファイル」カテゴリとして取り込むのが適切です。 | H62: A | I62: ◾ 問題の背景： コンサルタントは **人事データベース（HR DB）から「従業員のリスト」**を取り込もうとしています。 目的は、「セグメント化＝条件に応じた従業員の抽出・分類」。 → このような 個人の属性（氏名、部署、役職など）に基づくデータは、Data Cloud における「どのカテゴリのデータ」として取り込むべきか？を問う設問です。 ✅ 正解理由：個人の静的な属性情報は「プロファイルデータ」として扱うのが正解 ▶ プロファイルデータとは？ Data Cloud における データストリームカテゴリの1つ で： 個人（従業員、顧客、会員など）に関する 静的・属性的な情報 を取り込むためのカテゴリ 例：名前、役職、所属部門、勤務地、社員ID、生年月日など このような「状態としての人物情報」に関してはすべて「プロファイルデータ」に該当します。 ❌ 他の選択肢の誤り： 選択肢 評価 理由 A. プロファイルデータ ✅ 正解 従業員の静的な属性情報をセグメント化したい場合の正しいカテゴリ B. 連絡先データ ❌ 不正解 「連絡先情報（電話・メール）」は 連絡手段の詳細を補足する目的で使われる。リスト全体の属性管理には不向き C. その他のデータ ❌ 不正解 このカテゴリは プロファイル・エンゲージメントのどちらにも当てはまらないログデータなどに使う D. エンゲージメントデータ ❌ 不正解 「行動履歴」（例：ログイン、クリック、購入など）に使うカテゴリ。HRデータには不適 | J62: Salesforce.Data-Cloud-Consultant-JPN.v2024-09-12.q66 | K62: - | M62: *
B63: 99 | C63: ◯ | D63: 02_Data Cloud の設定と管理 | E63: ノーザン トレイル アウトフィッターズ (NTO) は、B2C Commerce データを Data Cloud に接続し、2 年間のトランザクション履歴を Data Cloud に取り込みたいと考えています。 これを達成するには、NTO は何を使用する必要がありますか? A. B2C Commerce スターター バンドル B. 直接販売注文エンティティの取り込み C. 直販製品エンティティの取り込み D. B2C Commerce スターター バンドルとカスタム抽出 | F63: D | G63: B2C Commerce スターター バンドルは、B2C Commerce から注文データと製品データを Data Cloud に取り込む事前定義されたデータ ストリームです。ただし、スターター バンドルはデフォルトで直近 90 日分のデータのみを取り込みます。2 年分の取引履歴を取り込むには、NTO は B2C Commerce から履歴データを含むカスタム抽出を作成し、データ ストリームのソースとしてこのカスタム抽出を設定する必要があります。他のオプションではこの要件を満たせない理由は以下の通りです： * A. B2C Commerce スターター バンドルはデフォルトで直近90日分のデータのみをインポートします。 * B. 直接販売注文エンティティのインポートは、B2C Commerce データを Data Cloud に接続するためのサポートされていない方法です。 * Data Cloud は B2C Commerce データへの直接アクセス接続を提供せず、データインポートのみをサポートしています。 * C. Direct Sales Productエンティティのインジェストは、B2C CommerceデータをData Cloudに接続するためのサポートされていない方法です。Data CloudはB2C Commerceデータへの直接アクセス接続を提供せず、データインジェストのみをサポートしています。参照： B2C Commerce Data Bundleの作成 - Salesforce、B2C Commerce Connector - Salesforce、Salesforce B2C Commerce 料金プランとコスト | H63: D | I63: ◾ 問題の背景： NTO は B2C Commerce（旧 Salesforce Commerce Cloud）と連携し、2年間分のトランザクション履歴（注文データ）を Salesforce Data Cloud に取り込みたい。 Data Cloud の B2C Commerce スターター バンドルは、あくまで「最近の標準データセット（通常は過去30日〜最大90日）」しか自動では取り込めない仕様です。 ✅ 正解理由： ▶ 標準のスターター バンドルでは「2年分」はカバーできない 通常の B2C Commerce Starter Bundle は以下のような制限があります： デフォルトで取り込めるのは 最大90日程度の履歴データ リアルタイム or 以降のデータに最適化されており、長期の履歴（過去2年）には非対応 ▶ 解決策：「B2C Commerce スターター バンドル」＋「カスタム抽出」 B2C Commerce スターター バンドルを用いて： 今後の新規注文やリアルタイムデータは自動取り込み カスタム抽出を用いて： 旧データ（過去2年）を一括で抽出・整形し、Data Cloud にインポート ❌ 他の選択肢の誤り： 選択肢 評価 誤りの理由 A. スターター バンドルのみ ❌ 長期履歴（2年）には不十分。新規・短期データしかカバーできない B. 直接販売注文エンティティの取り込み ❌ Salesforce標準機能では、Commerce Cloudからの直接取り込みは不可。API or バンドルが必要 C. 直販製品エンティティの取り込み ❌ 製品情報のみで注文情報は含まれないため、目的に合わない D. スターター バンドル + カスタム抽出 ✅ 短期と長期の両方を正しくカバーできる唯一の正解 | J63: Salesforce.Data-Cloud-Consultant-JPN.v2024-09-12.q66 | K63: - | M63: *
B64: 195 | C64: ◯ | D64: 02_Data Cloud の設定と管理 | E64: コンサルタントは、セグメント化したい従業員のリストを人事データベースから取り込んでいます。 このデータを取り込むときにコンサルタントはどのデータ ストリーム カテゴリを選択する必要がありますか? A. プロファイルデータ B. 連絡先データ C. その他のデータ D. エンゲージメントデータ | F64: C A | G64: データ ストリームのカテゴリ: * プロファイル データ: 顧客プロファイルと人口統計情報。 * 連絡先データ: 電子メールや電話番号などの連絡先。 * その他のデータ: 他のカテゴリに当てはまらないさまざまなデータ。 * エンゲージメント データ: インタラクションと行動データ。 コンサルタントが人事データベースから従業員のリストをデータクラウドに取り込んでセグメント化する場合、取り込む際に選択すべきデータ ストリームのカテゴリは、プロファイルデータです。 ソースによると、Data Cloud において、データ ストリームは以下の3つのカテゴリのいずれかとして保存されます: • プロファイル: セグメント指定のデータセットに使用され、セグメンテーションの開始母集団として使用されるソースグループを含みます。 • エンゲージメント: 時系列指向のデータセットです。イベント時間フィールドはセットアップの一部であり、後で変更することはできません。もしそうでなければ、レコードが重複してしまう可能性があります。 • その他: プロファイルまたはエンゲージメントデータに関連するデータセットです。時系列フィールドを持たない時系列データを含みます。 人事データベースからの従業員リストは、個々の従業員に関する情報（例：氏名、従業員ID、部門など）を含むデータであり、これは個人の属性を表すプロファイルデータとして最も適切に分類されます。このデータは、従業員を対象としたセグメントを作成するために使用される可能性が高いと考えられ、ソースではプロファイルデータがセグメントに使用されると明確に述べられています。 データストリームを保存する際、データカテゴリ（プロファイル、エンゲージメント、その他）を慎重に選択する必要があり、保存した後に変更することはできません。したがって、従業員リストのような個人の属性情報は「プロファイル」カテゴリとして取り込むのが適切です。 | H64: A | I64: ◾ 背景： コンサルタントは、従業員のリストを人事データベースから Data Cloud に取り込むというケースに対応しています。 この従業員データは、**個人ごとの属性情報（氏名、部署、職種など）**で構成されており、イベント履歴やトランザクションではない点が重要です。 ✅ 正解理由： ▶ プロファイルデータカテゴリとは？ 顧客または個人に関する静的な属性情報（例：氏名、生年月日、職種、所属など）を管理するためのカテゴリ 従業員も「1人の個人」としてセグメント対象にするなら、このカテゴリで取り込むのが適切 ▶ 従業員データもプロファイル情報に相当： 従業員 = 個人（Individual）オブジェクトとして扱うことが多く、 それに紐づく属性は セグメントやCIの対象になる静的情報です。 ❌ 他の選択肢の誤り： 選択肢 評価 理由 B. 連絡先データ ❌ メール・電話番号など**連絡手段（Contact Point）**に特化したカテゴリ。従業員属性全体のマッピングには不向き。 C. その他のデータ（Other） ❌ 構造が不明なログや補助情報に使うカテゴリ。セグメント対象にしたいなら避けるべき。 D. エンゲージメントデータ ❌ 行動履歴（ログイン・クリック・購入など）に使うカテゴリ。プロファイル情報ではない。 | J64: Salesforce.Data-Cloud-Consultant.v2024-12-02.q93 | K64: 84 | M64: *
B65: 198 | C65: ◯ | D65: 02_Data Cloud の設定と管理 | E65: Cumulus Financial は、Data Cloud ユーザー向けに、Salesforce CRM アカウント データを国別に分離したいと考えています。 これを達成するためにコンサルタントは何をすべきでしょうか? A. ストリーミング変換を使用して、国に基づいてアカウント データをフィルターし、それに応じて個別のデータ モデル オブジェクトにマップします。 B. データ スペース機能を使用し、国に基づいてアカウント データ レイク オブジェクトにフィルターを適用します。 C. アカウント オブジェクトで Salesforce 共有ルールを使用して、国に基づいてレコードをフィルタリングおよび分離します。 D. アカウントの国フィールドに基づく数式フィールドを使用して、受信レコードをフィルタリングします。 | F65: B | G65: データ スペースは、データ クラウド ユーザーがフィルターと権限に基づいてデータのサブセットを作成できるようにする機能です。データ スペースを使用すると、地理、事業部門、製品ラインなどのさまざまな基準に基づいてデータを分離できます。この場合、コンサルタントはデータ スペース機能を使用して、国に基づいてアカウント データ レイク オブジェクトにフィルターを適用できます。これにより、データ クラウド ユーザーは、それぞれの国に属するアカウント データにのみアクセスできます。参照: データ スペース、データ スペースの作成 | H65: B | I65: ◾ 背景： Cumulus Financial は、国ごとにアカウントデータを分離（データの論理的分割）したいと考えています。 これは以下のような要件に対応する典型例です： 地域ごとのデータ可視性制限（例：EU圏のデータはEU内のみで閲覧） ビジネス部門やリージョン単位でのデータ管理ポリシー ✅ 正解理由： ▶ データスペース（Data Spaces）とは？ Salesforce Data Cloud で提供されている、論理的なデータ分離機能。 同じオブジェクト構造のまま、条件（例：国コード）に基づいて分離されたビュー／管理単位を作成できる。 これにより： 物理的にデータを複製せず、 **国別などの条件でフィルターされたセグメント化されたデータレイクオブジェクト（DLO）**を扱える。 したがって「国ごとに分離」したいという要件に対して、Data Spacesが最も適切なアプローチとなる。 ❌ 他の選択肢の誤り： 選択肢 評価 理由 A. ストリーミング変換 + DMO 分割 ❌ ストリーミング変換は主にデータの整形や変換用途。DLOを国ごとに分けるような論理分離の役割は担わない。またDMO（データモデルオブジェクト）を国ごとに複数作る設計は保守性が低く非推奨。 C. Salesforce 共有ルール ❌ これはSalesforce CRM（Sales Cloud）内のアクセス制御に関する話で、Data Cloudにおけるデータ分離要件には直接関係しない。 D. 数式フィールドによるフィルター ❌ 数式フィールドは値の生成には使えるが、データの論理的な分離や制御には適さない。可視性や組織単位の管理には不十分。 | J65: Salesforce.Data-Cloud-Consultant.v2024-12-02.q93 | K65: 77 | M65: *
B66: 199 | C66: ◯ | D66: 02_Data Cloud の設定と管理 | E66: Salesforce CRM コネクタが構成され、ケース オブジェクト データ ストリームがセットアップされます。その後、Salesforce CRM のケース オブジェクトに Business Priority という名前の新しいカスタム フィールドが作成されます。ただし、新しいフィールドをデータ ストリームに追加しようとしても使用できません。 この問題の原因を説明している記述はどれですか? A. Salesforce 統合ユーザーには、新しく作成されたフィールドに対する Rad 権限がありません。 B. デスクトップから一括アップロードを実行するには、Salesforce Data Loader アプリケーションを使用する必要があります。 C. Case オブジェクトのカスタムフィールドは、Data Cloud への取り込みにはサポートされていません。 D. 24 時間後にデータ ストリームが更新されると、Salesforce CRM に追加された新しいフィールドが自動的に含まれるようになります。 | F66: A | G66: Salesforce CRM コネクタは、Salesforce 統合ユーザーを使用して Salesforce CRM 組織のデータにアクセスします。統合ユーザーには、データ ストリームに含まれるフィールドに対する読み取り権限が必要です。統合ユーザーに新しく作成されたフィールドに対する読み取り権限がない場合、そのフィールドはデータ ストリーム構成で選択できません。この問題を解決するには、管理者が新しいフィールドに対する読み取り権限を統合ユーザー プロファイルまたは権限セットに割り当てる必要があります。参照: Salesforce CRM データ ストリームの作成、データ ストリームの編集、Salesforce Data Cloud の CRM、SFMC、または Ingestion API データ ストリームの完全更新 | H66: A | I66: ◾ 背景： Salesforce CRM と Data Cloud のCRM コネクタを利用してデータ連携している状況。 ケース（Case）オブジェクトに新しくカスタム項目（Business Priority）を追加したにもかかわらず、Data Cloud 側のデータストリームにその項目が表示されない。 ✅ 正解理由： ▶ 最も一般的な原因： CRM コネクタは統合ユーザー（Integration User）を通じてデータにアクセスします。 そのため、**統合ユーザーが新しいフィールドにアクセスできない（Read権限がない）**場合、 データストリーム設定画面にそのフィールドが現れない／選択できないという事象が発生します。 → このケースでは、新フィールド作成後に統合ユーザーの権限セットが更新されていないことが原因です。 ❌ 他の選択肢の誤り： 選択肢 評価 理由 B. Data Loader アプリが必要 ❌ Data Loader は主にCRMデータのインポート／エクスポート用ツール。Data Cloudのストリーム設定には無関係。 C. Caseオブジェクトのカスタムフィールドは非対応 ❌ 誤り。Case含むあらゆる標準／カスタムオブジェクトのカスタム項目も対応可能。制限は存在しない。 D. 自動的に24時間後に反映される ❌ 一部の設定は定期的に更新されることもあるが、新フィールドの認識には明示的な再取得や権限確認が必要。自動追加はされない。 🔧 対応方法： Salesforce CRM側で該当フィールドの「Read権限」を統合ユーザーに付与 → 権限セットやプロファイルを見直す Data Cloud に戻り、データストリームを再編集して新しいフィールドを確認・追加 | J66: Salesforce.Data-Cloud-Consultant.v2024-12-02.q93 | K66: 65 | M66: *
B67: 12 | C67: ◯ | D67: 03_データ取得とデータモデリング | E67: ノーザン トレイル アウトフィッターズは毎日、過去 24 時間の店舗トランザクションの概要を Amazon S3 バケット内の新しいファイルにアップロードし、7 日より古いファイルは自動的に削除されます。各ファイルには、標準化された命名規則に従ってタイムスタンプが含まれています。 このデータ ストリームを取り込むときにコンサルタントが構成する必要がある 2 つのオプションはどれですか? 2 つの答えを選択してください A. 古いファイルの削除が有効になっていることを確認します。 B. 更新モードが「Upsert」に設定されていることを確認します。 C. タイムスタンプを収容するために、ファイル名にワイルドカードが含まれていることを確認してください。 D. リフレッシュ モードが「フル リフレッシュ」に設定されていることを確認します。 | F67: B, C | G67: Amazon S3 バケットからデータを取得する際、コンサルタントは以下のオプションを設定する必要があります： リフレッシュモードを「Upsert」に設定します。これにより、新しいレコードや更新されたレコードはData Cloudに追加または更新され、既存のレコードは保持されます。これにより、データは常に最新かつソースと一貫性が保たれます。 ファイル名にはタイムスタンプに対応するためのワイルドカードを含める必要があります。つまり、ファイル名パターンにはタイムスタンプ形式に一致する可変部分を含める必要があります。例えば、ファイル名がstore_transactions_2023-12-18.csvの場合、ワイルドカードはstore_transactions_*.csvとなります。これにより、インジェストプロセスが毎日正しいファイルを識別して処理できるようになります。 以下のオプションは、このシナリオでは必要ありません： 古いファイルの削除は、Amazon S3 バケットの機能であり、Data Cloud のインジェストプロセスには含まれません。Data Cloud はソースからファイルを削除せず、インジェスト後にソースファイルを削除する必要もありません。 フルリフレッシュは、Data Cloud内の既存のすべてのレコードを削除し、ソースファイルのレコードで置き換えるリフレッシュモードです。このシナリオでは適していません。特に、ソースファイルが過去24時間の取引の要約のみを含む場合、データ損失や不一致が発生する可能性があります。参照：Amazon S3からのデータ取り込み、リフレッシュモード | H67: B, C | I67: 🔍 解説の更新： ▶ C. ワイルドカードの必要性（正解） 毎日ファイル名が異なる（例：transactions_20240501.csv, transactions_20240502.csv）ため、 データストリームで ワイルドカード（例：transactions_*.csv） を指定しないと取り込みに失敗します。 この点は前回の説明通りで、確実に必要な設定です。 ▶ B. Upsert が正解である理由（Dではない理由） Amazon S3 からのファイル取り込みにおいて、新しいファイルが毎日追加される構成であるなら、 通常は **「前日のファイル＋本日の新規ファイル」**というように 累積的にデータが届く前提で動きます。 この場合、Data Cloud では 新しいレコードを追加し、既存のキーと一致するレコードは上書きする（= Upsert） のが望ましい。 ❗ 重要： **Dの「フルリフレッシュ」**は、毎回“全件再取り込み＆データを上書き”する挙動。 しかしこの設問の前提では、「1日ごとに新しいファイル（＝増分）」が届く構成なので、 Data Cloud 側で ファイル単位にUpsert対応し、最新レコードだけを反映させるのが適切。 ❌ なぜ D（フルリフレッシュ）は不適か？ 7日分の履歴ファイルがS3上に残っているなら、フルリフレッシュにすると毎回全期間分を取り込むことになり、非効率かつ不要です。 増分ファイルだけを毎日処理するなら Upsert の方が正しい運用設計です。 🔁 結論（修正版）： 選択肢 評価 理由 B. Upsert ✅ 正解 毎日届くファイルのデータを累積または上書きする用途に合致 C. ワイルドカード ✅ 正解 タイムスタンプ付きの毎日異なるファイル名を処理するために必須 A. 古いファイル削除 ❌ S3 側の設定であり、Data Cloud の構成項目ではない D. フルリフレッシュ ❌ このケースでは非効率かつ意図と異なる動作になる可能性が高い | J67: Salesforce.Data-Cloud-Consultant-JPN.v2025-03-28.q66 | K67: - | M67: *
B68: 139 | C68: ◯ | D68: 03_データ取得とデータモデリング | E68: Northern Trail Outfitters は毎日、過去 24 時間の店舗取引の概要を Amazon S3 バケット内の新しいファイルにアップロードし、7 日以上経過したファイルは自動的に削除されます。各ファイルには、標準化された命名規則に従ってタイムスタンプが含まれています。 このデータ ストリームを取り込むときにコンサルタントが設定する必要がある 2 つのオプションはどれですか。 2つの回答を選択してください A. 古いファイルの削除が有効になっていることを確認します。 B. 更新モードが「Upsert」に設定されていることを確認します。 C. タイムスタンプに対応するために、ファイル名にワイルドカードが含まれていることを確認します。 D. 更新モードが「完全更新」に設定されていることを確認します。 | F68: B, C | G68: Amazon S3 バケットからデータを取り込む場合、コンサルタントは次のオプションを設定する必要があります。 * 更新モードは「Upsert」に設定する必要があります。これは、既存のレコードは保持され、新しいレコードと更新されたレコードが Data Cloud に追加または更新されることを意味します。これにより、データは常に最新の状態になり、ソースと一致します。 * ファイル名には、タイムスタンプに対応するワイルドカードを含める必要があります。つまり、ファイル名パターンには、タイムスタンプ形式と一致する変数部分を含める必要があります。たとえば、ファイル名が store_transactions_2023-12-18.csv の場合、ワイルドカードは store_transactions_*.csv になります。これにより、取り込みプロセスで毎日正しいファイルを識別して処理できるようになります。 その他のオプションは、このシナリオでは不要または関連がありません。 * 古いファイルの削除は Amazon S3 バケットの機能であり、Data Cloud の取り込みプロセスではありません。Data Cloud はソースからファイルを削除しません。また、取り込み後にソース ファイルを削除する必要もありません。 * フルリフレッシュは、データクラウド内の既存のレコードをすべて削除し、ソースファイルのレコードに置き換えるリフレッシュモードです。特にソースファイルに過去 24 時間のトランザクションの概要のみが含まれている場合は、データの損失と不整合が発生するため、このシナリオには適していません。参照: Amazon S3 からのデータの取り込み、リフレッシュモード | H68: B, C | I68: ◾ 背景： Northern Trail Outfitters は次のような設定で店舗取引データを Amazon S3 に保存しています： 毎日1ファイルずつアップロード ファイル名にタイムスタンプを含む 7日後に古いファイルは削除 1ファイルあたり過去24時間のデータ このようなタイムスタンプ付きファイルの取り込みには、Data Cloud 側で特定の設定が必要です。 ✅ 正解理由： ▶ B. 更新モードが「Upsert」に設定されていることを確認します。 「Upsert（更新＋挿入）」は、識別子（例：取引IDなど）を使って既存レコードを更新し、なければ新規挿入する動作。 日次で新しいデータが追加されるような取引データの取り込みに最適です。 「完全更新（Full Refresh）」を選ぶと、既存データが上書きされてしまう可能性があり不適切。 ▶ C. タイムスタンプに対応するために、ファイル名にワイルドカードが含まれていることを確認します。 ファイル名に日付が埋め込まれている場合（例：transactions_20240501.csv）、ワイルドカード（例：transactions_*.csv）を使って毎日の新しいファイルを自動検出する必要があります。 ❌ 他の選択肢の誤り： 選択肢 理由 A. 古いファイルの削除が有効になっていることを確認します。 ❌ S3 側のライフサイクルポリシーで制御されるため、Data Cloud 側の設定ではない。 D. 更新モードが「完全更新」に設定されていることを確認します。 ❌ 完全更新（Full Refresh）は、毎回全レコードを削除・再取り込みする方式であり、日次追加型の取引データには不向き。 | J68: Salesforce.Data-Cloud-Consultant.v2024-12-02.q93 | K68: 12 | M68: *
B69: 35 | C69: ◯ | D69: 03_データ取得とデータモデリング | E69: セグメンテーションまたはアクティベーションを実行するとき、データの公開と更新にどのタイムゾーンが使用されますか? A. アクティビティの作成時に指定されたタイムゾーン B. アクティビティを作成しているユーザーのタイムゾーン C. データクラウド管理者ユーザーのタイムゾーン D. Salesforce Data Cloud 組織によって設定されたタイムゾーン | F69: D | G69: セグメンテーションまたはアクティベーションを実施する際、データを公開および更新する際に使用されるタイムゾーンはDです。このタイムゾーンは、Salesforce Data Cloud組織で設定されたものです。このタイムゾーンは、Data Cloudがプロビジョニングされた際に組織設定で設定され、Data Cloud内のすべてのユーザーおよびアクティビティに適用されます。このタイムゾーンは、セグメントの更新スケジュールとアクティベーションの公開スケジュールを決定します。したがって、セグメンテーションとアクティベーションの戦略を計画する際は、Data Cloud 組織と目的のシステムまたはチャネルのタイムゾーンの差を考慮することが重要です。参照： Salesforce Data Cloud コンサルタント試験ガイド、セグメンテーション、アクティベーション | H69: D | I69: ◾ 問題の要点： セグメンテーションやアクティベーションの 実行タイミング（スケジュール）や日付フィルターに関して、 どのタイムゾーンが基準として使用されるか？ ✅ 正解理由（D）： Salesforce Data Cloud では、全体的なデータ処理・スケジュール実行・公開の基準となるタイムゾーンは： 🔹 「Data Cloud 組織のデフォルトタイムゾーン」 によって制御されます。 このタイムゾーンは、Salesforceの組織単位で一元的に設定されるものであり、 ユーザー個別やアクティビティ個別の設定は 影響しません。 たとえば： セグメントの「過去24時間以内のイベント」などの条件 アクティベーションスケジュール「毎日AM2時」などの実行時間 → すべて Data Cloud組織のタイムゾーンに従って処理されます ❌ 他の選択肢の誤り： 選択肢 評価 理由 A. アクティビティ作成時に指定されたタイムゾーン ❌ 不正解 タイムゾーンをアクティビティごとに指定する設定は存在しない B. 作成ユーザーのタイムゾーン ❌ 不正解 ユーザーの個別タイムゾーンは UI表示には影響するが、処理の実行タイミングには無関係 C. 管理者ユーザーのタイムゾーン ❌ 不正解 特定の管理者ユーザーのタイムゾーンが適用されることはない D. Data Cloud 組織に設定されたタイムゾーン ✅ 正解 セグメンテーション・アクティベーション両方に対する処理基準となる | J69: Salesforce.Data-Cloud-Consultant-JPN.v2025-03-28.q66 | K69: - | M69: *
B70: 68 | C70: ◯ | D70: 03_データ取得とデータモデリング | E70: データの取り込みとアクティベーション用に個別の Amazon S3 バケットをサポートする構成はどれですか? A. データ クラウド設定の専用 S3 データ ソース B. データ クラウド設定内の複数の S3 コネクタ C. アクティベーション設定の専用 S3 データ ソース D. データ ストリームとアクティベーション ターゲットの個別のユーザー資格情報 | F70: A B | G70: Amazon S3 バケットをデータ取り込みとアクティベーション用に分離してサポートするには、Data Cloud の設定で専用の S3 データソースを構成する必要があります。データソースは、Data Cloud に取り込むデータの起源と種類を識別するために使用されます1。取り込みまたはアクティベーションに使用する各 S3 バケットに対して異なるデータソースを作成し、バケット名、リージョン、およびアクセス資格情報を指定できます2。これにより、ブランド、地域、製品、またはビジネスユニットなどの異なる基準でデータを分離して整理できます。他のオプションは、データ取り込みとアクティベーション用に別々のS3バケットをサポートしないため正しくないです。Data Cloud設定では、S3コネクタは1つしか利用できないため、複数のS3コネクタは有効な構成ではありません。アクティベーション設定における専用のS3データソースも有効な構成ではありません。アクティベーション設定ではデータソースではなく、アクティベーションターゲットが必要だからです5。データストリームとアクティベーションターゲット用の別々のユーザー資格情報は、別々のS3バケットをサポートするには不十分です。各データソースに対してバケット名とリージョンを指定する必要があるためです2。参照：データソースの概要、Amazon S3ストレージコネクタ、データスペースの概要、データストリームの概要、データアクティベーションの概要 | H70: B | I70: ◾ 問題の背景： ユーザーは以下の構成を希望しています： Amazon S3 バケットを 2つ使いたい 1つは データの取り込み用（インジェスト） もう1つは アクティベーション結果の出力用 → この要件を実現するData Cloudの構成方法はどれか？ ✅ 正解理由：「複数のS3コネクタをData Cloud設定内で作成可能」 Salesforce Data Cloud では： 設定画面から 複数の Amazon S3 コネクタ を作成できる それぞれのコネクタは： 取り込み用コネクタ → データストリームと紐づけ アクティベーション用コネクタ → アクティベーションターゲットと紐づけ このように、目的ごとに異なるS3バケットを利用できる構成がサポートされています。 ❌ 他の選択肢の誤り： 選択肢 評価 理由 A. データ クラウド設定の専用 S3 データ ソース ❌ 不正確 「データソース」という概念は抽象的すぎて、S3の入出力分離を具体的にサポートしない B. 複数の S3 コネクタ ✅ 正解 取り込みとアクティベーションで異なるS3バケットを明示的に分離できる唯一の方法 C. アクティベーション設定の専用 S3 データ ソース ❌ 不完全 アクティベーション側だけでは不十分。取り込み側のバケットも必要 D. ストリームとアクティベーションターゲットの個別ユーザー資格情報 ❌ 間違い 資格情報ではなく、コネクタ（接続設定）自体の分離が必要 | J70: Salesforce.Data-Cloud-Consultant-JPN.v2024-09-12.q66 | K70: - | M70: *
B71: 108 | C71: ◯ | D71: 03_データ取得とデータモデリング | E71: Northern Trail Outfitters のコンサルタントが、Salesforce CRM の連絡先オブジェクトから、yyyy-mm-dd と yyyy-mm-dd hh:mm:ss の両方の値を含むフィールドを取り込もうとしています。ターゲット フィールドは Date データ型に設定されています。 この状況では、どの記述が正しいでしょうか? A. ターゲット フィールドはエラーをスローし、null 値を格納します。 B. ターゲット フィールドは両方のタイプの値を保持できます。 C. ターゲット フィールドには時刻部分のみが保持され、日付部分は無視されます。 D. ターゲット フィールドには日付部分のみが保持され、時刻部分は無視されます。 | F71: D | G71: フィールドのデータ型： Salesforce CRMの連絡先オブジェクトのフィールドは、さまざまな形式でデータを格納できます。Salesforce Data Cloudにデータをインポートする際、ターゲットフィールドのデータ型が、データの処理と格納方法を決めることになります。 日付データ型： Data Cloudのターゲットフィールドが日付データ型に設定されている場合、時刻情報を含まない日付値を格納するように設計されています。 混合形式の値： 日付 （yyyy-mm-dd） と日時 （yyyy-mm-dd hh：mm：ss） の値を含むフィールドを日付データ型フィールドにインポートする場合： * 日付フィールドは、日時部分 （hh：mm：ss） を無視し、日付部分 （yyyy-mm-dd） のみを抽出・保存します。 結果： * 日付値： yyyy-mm-dd の値はそのまま格納されます。 * 日付時刻値： yyyy-mm-dd hh：mm：ss の値は yyyy-mm-dd に切り詰められ、時刻部分は無視されます。 参照： * Salesforce Data Cloud フィールド マッピング * Salesforce データ型 | H71: D | I71: ◾ 問題の背景： Salesforce CRM から取り込むデータに含まれるフィールドには、 yyyy-mm-dd（日付のみ） yyyy-mm-dd hh:mm:ss（日付＋時刻） の両方の形式が存在している。 Data Cloud 側の ターゲットフィールドは Date 型に設定されている。 ✅ 正解理由： ▶ Data Cloud の Date データ型の挙動 Date 型は 日付（年月日）のみを扱うデータ型 であり、 yyyy-mm-dd hh:mm:ss のような 時刻情報が含まれる値が渡された場合でも、 時刻部分（hh:mm:ss）は自動的に無視され、日付（yyyy-mm-dd）部分のみが保持されます。 ❌ 他の選択肢の誤り： 選択肢 評価 解説 A. エラーをスローして null を格納 ❌ 日付＋時刻形式は正しくパースされ、日付部分のみ抽出されるため null にはならない B. 両方のタイプを保持できる ❌ 保持できるのは「日付部分のみ」。時刻を保持するには DateTime 型が必要 C. 時刻のみ保持される ❌ Date 型では日付が本体で、時刻は切り捨てられるため誤り D. 日付のみ保持、時刻は無視される ✅ 正確な動作。仕様通りの処理がなされる | J71: Salesforce.Data-Cloud-Consultant-JPN.v2024-09-12.q66 | K71: - | M71: *
B72: 156 | C72: ◯ | D72: 03_データ取得とデータモデリング | E72: セグメンテーションまたはアクティベーションを実行するときに、データの公開と更新にはどのタイムゾーンが使用されますか? A. アクティビティ作成時に指定されたタイムゾーン B. アクティビティを作成したユーザーのタイムゾーン C. データクラウド管理者ユーザーのタイムゾーン D. Salesforce Data Cloud 組織によって設定されたタイムゾーン | F72: D | G72: セグメンテーションまたはアクティベーションを実行するときにデータを公開および更新するために使用されるタイムゾーンは、Salesforce Data Cloud 組織によって設定される D タイムゾーンです。このタイムゾーンは、Data Cloud がプロビジョニングされるときに組織設定で設定されるもので、Data Cloud 内のすべてのユーザーとアクティビティに適用されます。このタイムゾーンによって、セグメントの更新スケジュールとアクティベーションの公開スケジュールが決まります。したがって、セグメンテーションとアクティベーションの戦略を計画するときは、Data Cloud 組織と宛先システムまたはチャネル間のタイムゾーンの違いを考慮することが重要です。参考資料: Salesforce Data Cloud コンサルタント試験ガイド、セグメンテーション、アクティベーション | H72: D | I72: ◾ 背景： Salesforce Data Cloud での**セグメンテーション（Segment Publication）やアクティベーション（Activation Schedule）**は、スケジュールベースで実行できます。 このスケジュールの**基準となるタイムゾーン（何時に実行されるか）**がどこで決まるのか？ というのが本設問のテーマです。 ✅ 正解理由： ▶ D. Salesforce Data Cloud 組織によって設定されたタイムゾーン Data Cloud のスケジュール設定や公開・更新処理は、その Data Cloud 組織全体に設定されたデフォルトタイムゾーンに基づいて実行されます。 これは通常、組織設定または初期構成時に管理者が定義するものであり、ユーザー個別のタイムゾーンやアクティビティ作成時には影響されません。 ❌ 他の選択肢の誤り： 選択肢 理由 評価 A. アクティビティ作成時に指定されたタイムゾーン ❌ アクティビティの作成時に個別にタイムゾーンを設定する機能はありません。 B. アクティビティを作成したユーザーのタイムゾーン ❌ スケジューリングや実行処理は個人の設定とは無関係です。 C. データクラウド管理者ユーザーのタイムゾーン ❌ 管理者のタイムゾーン設定も実行タイミングに影響しません。 | J72: Salesforce.Data-Cloud-Consultant.v2024-12-02.q93 | K72: 35 | M72: *
B73: 201 | C73: ◯ | D73: 03_データ取得とデータモデリング | E73: セグメンテーションまたはアクティベーションを実行するときに、データの公開と更新にはどのタイムゾーンが使用されますか? A. アクティビティ作成時に指定されたタイムゾーン B. アクティビティを作成したユーザーのタイムゾーン C. データクラウド管理者ユーザーのタイムゾーン D. Salesforce Data Cloud 組織によって設定されたタイムゾーン | F73: D | G73: セグメンテーションまたはアクティベーションを実行するときにデータを公開および更新するために使用されるタイムゾーンは、Salesforce Data Cloud 組織によって設定される D タイムゾーンです。このタイムゾーンは、Data Cloud がプロビジョニングされるときに組織設定で設定されるもので、Data Cloud 内のすべてのユーザーとアクティビティに適用されます。このタイムゾーンによって、セグメントの更新スケジュールとアクティベーションの公開スケジュールが決まります。したがって、セグメンテーションとアクティベーションの戦略を計画するときは、Data Cloud 組織と宛先システムまたはチャネル間のタイムゾーンの違いを考慮することが重要です。参考資料: Salesforce Data Cloud コンサルタント試験ガイド、セグメンテーション、アクティベーション | H73: D | I73: ◾ 背景： Salesforce Data Cloud では、セグメントの公開スケジュールやアクティベーションの実行タイミングは、指定された時刻に基づいて自動処理されます。 この処理の**時間解釈（基準となるタイムゾーン）**は、ユーザー個別のタイムゾーンではなく、Data Cloud組織レベルで統一されたタイムゾーン設定に依存します。 ✅ 正解理由： ▶ 組織の標準タイムゾーンに基づく運用： Data Cloud ではセグメントやアクティベーションのスケジュール実行の正確性が求められるため、 統一されたタイムゾーン基準が必要。 このため、Data Cloud 組織レベルで設定されたタイムゾーンが、 公開タイミングや更新スケジュールの基準として使用されます。 ❌ 他の選択肢の誤り： 選択肢 評価 理由 A. アクティビティ作成時の指定タイムゾーン ❌ セグメントやアクティベーション作成時に個別にタイムゾーン指定はできない。 B. アクティビティ作成者のタイムゾーン ❌ ユーザー単位のタイムゾーンは表示用途のみで、スケジュール処理には使われない。 C. Data Cloud 管理者のタイムゾーン ❌ 管理者ユーザーに依存したスケジュール処理はされない。組織全体に統一された設定がある。 | J73: Salesforce.Data-Cloud-Consultant.v2024-12-02.q93 | K73: 35 | M73: *
B74: 1 | C74: ◯ | D74: 03_データ取得とデータモデリング | E74: ノーザン トレイル アウトフィッターズは B2C Commerce を使用しており、顧客とそのすべての注文トランザクションを統一的に把握するために Data Cloud の実装を検討しています。 B2C Commerce Order Bundle を使用して注文データを取り込む履歴データに関して、コンサルタントはどのようなことに留意する必要がありますか? A. B2C Commerce Order Bundle は、12 か月分の履歴データを取り込みます。 B. B2C Commerce Order Bundle は 6 か月分の履歴データを取り込みます。 C. B2C Commerce Order Bundle は履歴データを取り込まず、その時点以降の新しい注文のみを取り込みます。 D. B2C Commerce Order Bundle は 30 日間の履歴データを取り込みます。 | F74: C D | G74: B2C Commerce オーダー バンドルは、B2C Commerce インスタンスから Data Cloud へ注文データを送信するデータ ストリームを作成するデータ バンドルです。ただし、このデータ バンドルは過去のデータをインポートせず、データ ストリームが作成された時点以降の新しい注文のみをインポートします。したがって、コンサルタントが過去の注文データをインポートしたい場合は、B2C Commerceからデータをエクスポートし、CSVファイル12を使用してData Cloudにインポートするなどの別の方法を使用する必要があります。参照： B2C Commerce データバンドルの作成 B2C Commerce および Commerce Marketplace のデータアクセスとエクスポート 提供された資料に基づくと、ノーザン トレイル アウトフィッターズが B2C Commerce Order Bundle を使用して注文データを取り込む際の履歴データに関して、コンサルタントが留意すべき点として以下の情報が示されています。 Salesforce 接続ソースの詳細を示すスライド では、B2C コマースについて「バンドル注文可能」とあり、含まれるエンティティとして「注文 (カスタム属性を含む)」が挙げられています。このスライドの注意書きとして、**「注文トランザクションの履歴ロードは 30日間 のみ」**と明記されています。 また、「データ収集のタイミング」に関するスライド の表においても、B2C コマースのソースに対して、ルックバック ウィンドウが 30日 と記載されており、配信方法がバッチであることが示されています。レイテンシーとリフレッシュモードは、「セールスオーダー時間単位のアップサート セールスオーダー履歴全1時間ごとの完全更新毎日更新」となっています。 これらのソース情報から、B2C Commerce Order Bundle を使用した場合の注文データの履歴ロードには制限があり、その期間は 30 日であることが明確に示されています。 したがって、コンサルタントは以下の点に留意する必要があります。 • B2C Commerce Order Bundle は、過去 30 日間の注文トランザクションの履歴データを取り込みます。 • これより古い履歴データを取り込む場合は、別の方法（例えば、追加のデータストリーム設定やインジェストAPIの利用など、資料には直接記載されていませんが、可能性として考えられます）を検討する必要があるかもしれません。 選択肢の中で、このソース情報と一致するのは以下の記述です。 D. B2C Commerce Order Bundle は 30 日間の履歴データを取り込みます。 他の選択肢はソース情報と異なります。 • A. B2C Commerce Order Bundle は、12 か月分の履歴データを取り込みます。 と矛盾します。 • B. B2C Commerce Order Bundle は 6 か月分の履歴データを取り込みます。 と矛盾します。 • C. B2C Commerce Order Bundle は履歴データを取り込まず、その時点以降の新しい注文のみを取り込みます。 ソースでは「履歴ロード」が可能であることが示されているため、この記述は異なります。 以上のことから、提供されたソース資料に基づいて最も適切な回答は D です。 | H74: A D | I74: ◆ B2C Commerce Order Bundleとは？ Salesforce Data Cloud における「データバンドル（Data Bundle）」の一種。 B2C Commerce との接続を前提に、注文（Order）、注文商品（Order Item）、顧客（Customer）などの標準的なオブジェクトを自動的にマッピング・取り込みできる仕組み。 ノーザン トレイル アウトフィッターズのような B2C ブランドが、顧客360ビュー（360 Customer View） を実現するために活用されます。 ◆ 履歴データの取り込み仕様 公式情報によると： "Up to 12 months of order history is automatically ingested when using the B2C Commerce Order Bundle in Data Cloud." つまり： 自動で過去12か月分の注文履歴が取り込まれます。 追加のETLや履歴の再加工は不要（ただし、必要に応じてカスタマイズ可能）。 ◆ 留意点 12か月分の履歴が自動で対象になることは、導入初期のデータギャップを防ぐ重要な仕様。 履歴データの網羅性は顧客セグメンテーションや傾向分析に大きく影響する。 B2C CommerceとData Cloudの連携設定を間違えると履歴が正常に取り込まれない可能性があるため、設計と初期同期を慎重に行う必要があります。 | J74: Salesforce.Data-Cloud-Consultant-JPN.v2025-03-28.q66 | K74: - | M74: *
B75: 3 | C75: ◯ | D75: 03_データ取得とデータモデリング | E75: 顧客の組織、個人、またはメンバーに対してどのデータ モデル サブジェクト領域を使用する必要があるか 360度データモデル? A. エンゲージメント B. メンバーシップ C. パーティー D. グローバルアカウント | F75: C | G75: 顧客360データモデルにおいて、組織、個人、またはメンバーに適用されるデータモデル主体領域は「Party主体領域」です。Party主体領域は、顧客、見込み客、パートナー、サプライヤーなど、ビジネス取引や関係に参画するエンティティを定義します。Party主体領域には、以下のデータモデルオブジェクト（DMOs）が含まれます： 組織：会社、部門、支店など、法的な实体または事業部門を表すDMOs。 個人：顧客、連絡先、ユーザーなど、人を表すDMOs。 メンバー：従業員、顧客、パートナーなど、個人と組織の関係を表すDMOs。 その他のオプションは、Customer 360 データモデルにおける組織、個人、メンバーに使用すべきデータモデル主題領域ではありません。エンゲージメント主題領域は、クリック、閲覧、購入など、人が行うアクションを定義します。メンバーシップ主題領域は、ロイヤルティプログラム、クラブ、コミュニティなど、人がグループとの間で持つ関係を定義します。グローバルアカウント主題領域は、親-子、子会社など、組織間の階層関係を定義します。 参照： データモデルの対象領域 当事者対象領域 Customer 360 データモデル | H75: C | I75: ◾ 問題の要点： 顧客の「組織、個人、またはメンバー」に対して、Data Cloud の 360度データモデル でどの サブジェクト領域（Subject Area） を使うか？ これは、「顧客を一意に識別し、属性や関係性を統一して表現するためのコアオブジェクトは何か？」という問いです。 ◾ パーティー（Party）とは？ Data Cloud（旧Salesforce CDP）の標準データモデルにおいて、**「顧客」**を中心に構築された基盤。 「個人（Individual）」「組織（Organization）」「関係者（Household/Group）」といった様々な形態を一貫して管理するために使われる。 いわば、360度ビューの中心的存在。 ■ まとめ： Data Cloud の 360 度データモデルにおいて「顧客（組織・個人・メンバー）」を扱うなら、必ず『パーティー（Party）』サブジェクト領域を使用します。 この「Party」を中心に、購買履歴、Web閲覧、ロイヤルティ情報、住所、デバイス情報などがリンクされ、360°ビューが完成します。 | J75: Salesforce.Data-Cloud-Consultant-JPN.v2025-03-28.q66 | K75: - | M75: *
B76: 4 | C76: ◯ | D76: 03_データ取得とデータモデリング | E76: Northern Trail Outfitters は、コンサルタントに、Track My Run モバイル アプリからランナーのプロフィールとアクティビティ ログを抽出し、Data Cloud に読み込むように依頼しました。マーケティング部門は、過去 90 日間の履歴データが必要であり、今後利用可能になった新しいデータと更新されたデータをすべて入手したいとも述べています。 ベストプラクティスとして、コンサルタントはこのリクエストを実行するためにどのアクションのシーケンスを使用する必要がありますか? A. 一括取り込みを使用して、まず過去 90 日間のデータを読み込み、その後、将来のデータが利用可能になったときに一括取り込みを使用して同期します。 B. ストリーミング取り込みを使用して、まず過去 90 日間のデータを読み込み、その後もストリーミング取り込みを使用して、将来のデータが利用可能になったときに同期します。 C. ストリーミング取り込みを使用して、まず過去 90 日間のデータを読み込み、次にバルク取り込みを使用して、将来のデータが利用可能になったときに同期します。 D. 最初に一括取り込みを使用して過去 90 日間のデータを読み込み、次にストリーミング取り込みを使用して将来のデータが利用可能になったときに同期します。 | F76: D | G76: * 初期データ読み込み： 過去90日分のランナープロファイルやアクティビティログなど、大量の履歴データを一括で読み込むには、一括読み込みが最も効率的な方法です。これにより、高スループットのデータ転送が可能です。 一括読み込み： Salesforce Data Cloudの一括読み込みツールを使用して、履歴データを迅速かつ効率的に読み込みます。 * 継続的なデータ同期： Track My Runモバイルアプリで利用可能になった新しいレコードや変更されたレコードをData Cloudに反映させるため、ストリーミングインジェストが適しています。これにより、ほぼリアルタイムでのデータ更新が保証されます。 ストリーミングインジェスト： モバイルアプリから新しいデータや更新されたデータを継続的にData Cloudに反映させるため、ストリーミングインジェストを設定します。 * 作業手順： ステップ1： 過去90日分の履歴データをData Cloudにインポートするため、一括インジェストを実行します。 ステップ2： ストリーミングインジェストを設定し、継続的な更新と新しいデータを取得できるようにします。 * ベストプラクティス： このアプローチにより、初期の大規模なデータロードを効率的に処理し、継続的な更新をほぼリアルタイムで処理できます。これにより、マーケティング部門は最も最新のデータを利用できます。 * 参照： Salesforce Data Cloud インジェスト方法 Salesforce バルクデータインジェスト Salesforce ストリーミングデータインジェスト | H76: D | I76: ◾ 問題の要点 Track My Run モバイルアプリから 過去90日分の履歴データ（初期ロード） かつ 今後追加・更新されるデータも継続的に取得（リアルタイムまたは準リアルタイム） が必要。 このようなケースでは、履歴データの初期ロードには「一括取り込み（バルクインジェスト）」、 **新しいデータの継続的な受信には「ストリーミング取り込み」**を使用するのがSalesforce Data Cloudにおけるベストプラクティスです。 | J76: Salesforce.Data-Cloud-Consultant-JPN.v2025-03-28.q66 | K76: - | M76: *
B77: 7 | C77: ◯ | D77: 03_データ取得とデータモデリング | E77: データ クラウド コンサルタントは最近、新しいデータ ソースを追加し、セグメントの作成に使用する新しいカスタム データ モデル オブジェクト (DMO) にデータの一部をマッピングしました。ただし、新しいセグメントを作成しようとすると、新しく作成された DMO を表示できません。 この問題の原因は何ですか? A. データは DMO に取り込まれていません。 B. 新しい DMO はプロファイル カテゴリではありません。 C. 新しい DMO は個々の DMO と関係がありません D. セグメンテーションは、個別 DMO および統合個別 DMO でのみサポートされます。 | F77: B | G77: この問題の原因は、新しいカスタムデータモデルオブジェクト（DMO）が「Profile」カテゴリに属していないためです。カテゴリは、DMOの目的と機能をData Cloud内で定義するプロパティです。DMOには3つのカテゴリがあります：Profile、Event、およびOther。Profile DMOは、個人またはエンティティの属性（名前、メールアドレス、住所など）を格納するために使用されます。Event DMOは、個人またはエンティティのアクションやインタラクション（購入、クリック、訪問など）を格納するために使用されます。Other DMOは、ProfileまたはEventカテゴリに該当しないその他の種類のデータを格納するために使用されます（例：製品、場所、カテゴリなど）。セグメントの作成にはプロファイル DMOs のみが使用可能です。セグメントは個人またはエンティティの属性に基づいて作成されるためです。したがって、新しいカスタム DMO がプロファイル カテゴリに属さない場合、セグメンテーション キャンバスに表示されません。他のオプションは正しくない理由は、これらが問題の原因ではないためです。データ インジェストはセグメント作成の必須条件ではありません。データ モデル スキーマに基づいて、実際のデータがなくてもセグメントを作成できます。新しいDMOは、個々のDMOとの関係を必要としません。セグメントは、他のDMOとの関係に関わらず、任意のProfile DMOに基づいて作成できます。セグメンテーションは、IndividualおよびUnified Individual DMOに限定されません。任意のProfile DMO（カスタムDMOを含む）に基づいてセグメントを作成できます。参照：既存のデータモデルオブジェクトからカスタムデータモデルオブジェクトを作成する、Data Cloudでセグメントを作成する、データモデルオブジェクトのカテゴリ | H77: B | I77: ◾ 問題の要点： 新しいデータソース → 新しいカスタムDMOにマッピング済み だが、セグメント作成時にそのDMOが表示されない これは 「セグメンテーション画面に表示されるDMOの条件」 に関する典型的な問題です。 ■ 正解の理由： ▶ セグメント作成時に使えるDMOの条件 Salesforce Data Cloud では、セグメントを作成する際に利用できるオブジェクト（DMO）は、以下のような条件を満たす必要があります： そのDMOが「プロファイルカテゴリ（Profile Category）」に属していること 「個人（Individual DMO）」に関連付けられていること 特に、プロファイルカテゴリに分類されていないDMOはセグメンテーションUIに表示されません。 | J77: Salesforce.Data-Cloud-Consultant-JPN.v2025-03-28.q66 | K77: - | M77: *
B78: 25 | C78: ◯ | D78: 03_データ取得とデータモデリング | E78: 顧客は、データ ウェアハウスのトランザクション データを Data Cloud で使用したいと考えています。 SFTP サイト経由でのみデータをエクスポートできます。 ファイルをデータクラウドにどのように取り込む必要がありますか? A. SFTP コネクタを使用してファイルを取り込みます。 B. Cloud Storage コネクタ経由でファイルを取り込みます。 C. データ インポート ウィザードを使用してファイルを手動でインポートします。 D. Salesforce のデータローダー アプリケーションを使用して、デスクトップから一括アップロードを実行します。 | F78: A | G78: SFTP コネクタは、Data Cloud が SFTP サーバーからデータを取得するためのデータソースコネクタです。顧客は SFTP コネクタを使用して、エクスポートしたファイルからデータストリームを作成し、Data Cloud にデータレイクオブジェクトとして取り込むことができます。他のオプションは、ファイルを Data Cloud に取り込む最適な方法ではありません。その理由は以下の通りです： B . Cloud Storage Connectorは、Amazon S3、Azure Storage、Google Cloud Storageなどのクラウドストレージサービスからデータをインポートするためのデータソースコネクタです。顧客はこれらのサービスにデータを格納しておらず、SFTPサイトにのみデータを保有しています。 C . データインポートウィザードは、アカウント、連絡先、リード、ソリューション、キャンペーンメンバーなど、多くの標準Salesforceオブジェクトのデータを読み込むためのツールです。SFTPサイトからのデータ読み込みやData Cloudのカスタムオブジェクトに対応していません。 D . Dataloader は、Salesforce レコードの挿入、更新、削除、またはエクスポートを行うアプリケーションです。SFTP サイトからデータを取り込むことや、Data Cloud へのデータ取り込みには設計されていません。参照： SFTP Connector - Salesforce、Data Cloud で SFTP Connector を使用してデータストリームを作成する - Salesforce、Data Import Wizard - Salesforce、Salesforce Data Loader | H78: A | I78: ◾ 問題の要点： 顧客は データウェアハウスのトランザクションデータを Data Cloud で活用したい。 SFTP（Secure File Transfer Protocol）経由のみでエクスポート可能という制約がある。 → つまり、SFTP 経由で自動的に Data Cloud に取り込める方法が必要。 ✅ 正解理由： Salesforce Data Cloud は SFTP を正式なデータソースとしてサポートしており、 「SFTP コネクタ」を使えば： SFTP サーバー上のファイル（CSVやParquetなど）を 定期的に スケジュール or トリガーによって自動取り込みできる つまり、顧客の「SFTPしか使えない」という制限を満たしつつ、Data Cloudへのデータ統合が可能です。 ■ 他の選択肢の検討： 選択肢 評価 理由 A. SFTPコネクタを使用 ✅ 正解 唯一、要件（SFTP経由）に合致した公式の取り込み手段 B. Cloud Storage コネクタ経由 ❌ 不正解 GCS や Azure Blob、Amazon S3 などにしか対応。SFTP は対象外 C. データインポートウィザード ❌ 不正解 主に CRM の Leads, Accounts などの手動インポート用UI。Data Cloud では使用しない D. Salesforce データローダー ❌ 不正解 Core Salesforce 向けであり、Data Cloudとは非連携。しかもSFTP経由ではない | J78: Salesforce.Data-Cloud-Consultant-JPN.v2025-03-28.q66 | K78: - | M78: *
B79: 29 | C79: ◯ | D79: 03_データ取得とデータモデリング | E79: Northern Trail Outfitters には、Data Cloud に取り込んでセグメンテーションに使用する次の顧客データがあります。 1. 購入傾向 2. アクティブな会員である 3. 仕事用のメールアドレス このデータを取り込むときにコンサルタントはどのデータ型を使用する必要がありますか? A. パーセント、数値、メール B. 数値、ブール値、テキスト C. パーセント、ブール値、電子メール D. 数値、テキスト、URL | F79: B C | G79: - | H79: C | I79: ◾ 問題のデータ内容と対応すべきデータ型： データ項目 内容 適切なデータ型 1. 購入傾向 たとえば「購入頻度」や「支出割合」などのスコア。通常は 0〜100％の割合で表されることが多い ✅ パーセント（Percent） 2. アクティブな会員である Yes/No または True/False で表される論理値 ✅ ブール値（Boolean） 3. 仕事用のメールアドレス 明確なフォーマットを持つ文字列（aaa@bbb.com） ✅ 電子メール（Email） ✅ C の選択肢は、3つすべてのデータ項目に正しく対応しているため、完全に合致します。 ❌ 他の選択肢の誤り： 選択肢 評価 誤りの理由 A. パーセント、数値、メール ❌ 「アクティブ会員」が数値ではなくブール値なので不適切 B. 数値、ブール値、テキスト ❌ 「購入傾向」がパーセント（比率）である可能性が高く、数値より精度が落ちる。メールもテキストより専用型が望ましい D. 数値、テキスト、URL ❌ どれもこのユースケースにはフィットしない | J79: Salesforce.Data-Cloud-Consultant-JPN.v2025-03-28.q66 | K79: - | M79: *
B80: 33 | C80: ◯ | D80: 03_データ取得とデータモデリング | E80: Data Cloud コンサルタントは、整理されたクリーンなデータを扱っています。ただし、さまざまなスキーマがユーザー、連絡先、サブスクライバーなど複数の名前で人物を参照しているため、標準的なマッピングが必要です。 これらのさまざまなスキーマ ポイントを標準データ モデルにマッピングするプロセスを説明する用語はどれですか。 A. セグメント B. 調和する C. 統合 D. 変換 | F80: B | G80: * データ調和の基礎： データ調和とは、異なるソースから取得したデータを統合し、一貫性を持たせるプロセスです。 参照： * 異なるスキーマポイントのマッピング： データクラウドでは、異なるスキーマが同じエンティティを異なる名前（例： ユーザー、連絡先、サブスクライバー）で参照する場合があります。 調和とは、これらの異なる用語を単一の一貫したスキーマに標準化することです。 * 調和のプロセス： バリエーションの特定： スキーマ間で同じエンティティを指す異なる名前やフィールドを認識します。 標準マッピング： 標準データモデルを作成し、さまざまなスキーマポイントをこのモデルにマッピングします。 例： 「ユーザー」「連絡先」「サブスクライバー」を「顧客」という単一の標準エンティティにマッピングします。 * データ調和のステップ： 標準データモデルを定義します。 異なるスキーマのフィールドをこの標準モデルにマッピングします。 データエコシステム全体での一貫性を確保します。 | H80: B | I80: ◾ 問題の状況： 整理されたクリーンなデータを扱っているが、 「ユーザー」「連絡先」「サブスクライバー」など、異なるスキーマで"人物"を表現している この 異なるスキーマ表現を標準のデータモデル（DMO）にマッピングしたい ✅ このプロセスを表す正しい用語は 「調和（Harmonization）」 ▶ Data Cloudにおける「データ調和（Harmonization）」とは： 複数のデータソースや異なるスキーマで表現された同一の概念（例：人物、顧客、注文など）を、標準化されたデータモデルにマッピングするプロセス たとえば： 「user_id」「contact_id」「subscriber_id」 → 全て Individual DMO の Individual ID に統合 異なる呼び名や構造を 1つの統一構造へ整理 ❌ 他の選択肢の誤り： 選択肢 評価 理由 A. セグメント（Segment） ❌ 不正解 セグメントはフィルタリングによる人のグルーピング。スキーマのマッピングではない B. 調和する（Harmonize） ✅ 正解 異なるスキーマの属性を標準データモデルに統一マッピングする行為そのもの C. 統合（Unification） ❌ 不正解 同一人物の複数レコードを1つにまとめるプロセス（ID解決）。マッピングではない D. 変換（Transform） ❌ 不正解 値の形式変換（例：日付形式変換、文字列切り出し）など。スキーママッピングではない | J80: Salesforce.Data-Cloud-Consultant-JPN.v2025-03-28.q66 | K80: - | M80: *
B81: 36 | C81: ◯ | D81: 03_データ取得とデータモデリング | E81: コンサルタントは、データ クラウド コンポーネントを 1 つからパッケージ化する必要があります。 組織を別の組織に。 コンサルタントがデータクラウドコンポーネントに含めるべき 2 つのデータクラウドコンポーネントはどれですか? この目標を達成するためのデータキットは? 2 つの答えを選択してください A. データ モデル オブジェクト B. セグメント C. 計算された洞察 D. ID 解決ルールセット | F81: A, D | G81: データクラウドのコンポーネントを組織間でパッケージ化するには、コンサルタントはデータキットに以下のコンポーネントを含める必要があります： データモデルオブジェクト： これらはデータクラウドのデータモデルを定義するカスタムオブジェクトです。例えば、Individual、Segment、Activityなどがあります。これらのオブジェクトは、さまざまなソースから取り込まれたデータを格納し、統一されたプロファイルやセグメントの作成を可能にします1。 アイデンティティ解決ルールセット： 異なるソースからのデータを照合し統合して統一されたプロファイルを作成するためのルールです。アイデンティティ解決の基準、論理、優先順位を指定します2。参照： 1： Data Cloud におけるデータモデルオブジェクト 2： Data Cloud におけるアイデンティティ解決ルールセット | H81: A, D | I81: ◾ 背景： Salesforce Data Cloud では、「データキット（Data Kit）」という仕組みを使って、 ある組織（Org）から別の組織へ構成済みのデータクラウドコンポーネントをパッケージとしてエクスポート/インポートすることができます。 ✅ 正解理由： ▶ A. データ モデル オブジェクト（DMO） DMO は、データ構造（オブジェクトとフィールド）を定義するコア要素であり、あらゆるセグメントやインサイトの基礎になります。 Data Kit での移行対象としてサポートされており、組織間の構成の一貫性を保つために重要です。 ▶ D. ID 解決ルールセット Identity Resolution のルール（マッチング条件、リンク、調整など）も Data Kit の構成対象です。 組織間で同一のID解決ロジックを再利用したい場合、Data Kitでエクスポート/インポートが可能です。 ❌ 他の選択肢の誤り： 選択肢 評価 誤りの理由 B. セグメント ❌ セグメントは現在、Data Kitのエクスポート対象外です。セグメントはローカルで再作成が必要です。 C. 計算された洞察（Calculated Insights） ❌ 計算された洞察も Data Kit では直接移行できません（クエリ定義の手動再作成が必要）。 📝 補足：Data Kit に含められる主なコンポーネント コンポーネント名 Data Kitに含められるか ✅ データ モデル オブジェクト ✔️ ✅ ID 解決ルールセット ✔️ ❌ セグメント ✘ 再作成が必要 ❌ 計算された洞察（CI） ✘ 再作成が必要 | J81: Salesforce.Data-Cloud-Consultant-JPN.v2025-03-28.q66 | K81: - | M81: *
B82: 38 | C82: ◯ | D82: 03_データ取得とデータモデリング | E82: Cloud Kicks は、既存のデータ ストリームの 1 つとその基盤となるデータ レイク オブジェクト (DLO) を完全に削除する予定です。 データ ストリームを削除する前にコンサルタントは何を考慮すべきでしょうか? A. 基礎となる DLO はデータ変換で使用できます。 B. 基になる DLO をデータ モデル オブジェクトにマップできません。 C. データ ストリームはデータ キットに関連付ける必要があります。 D. 基になる DLO を暗黙的に削除せずにデータ ストリームを削除できます。 | F82: A | G82: * データ ストリームとDLOs： Salesforce Data Cloudでは、データ ストリームを使用してデータを取得し、その後Data Lake Objects （DLOs）に格納されます。 * 削除時の考慮事項： データ ストリームを削除する前に、その基盤となるDLOの依存関係と使用状況を必ず確認してください。 * データ変換の使用： 削除の影響： 基盤となるDLOがデータ変換で使用されている場合、データストリームを削除すると、そのDLOに依存するすべての変換に影響を与えます。 依存関係の確認： DLOが削除によって中断される可能性のあるアクティブなデータ変換やプロセスの一部ではないことを確認してください。 * 参照： Salesforce Data Cloud ドキュメント： データストリーム Salesforce Data Cloud ドキュメント： データ変換 | H82: A | I82: Data Cloud コンサルタントがデータ ストリームとその基盤となるデータ レイク オブジェクト (DLO) を削除する前に考慮すべき事項として、ソースに基づくと以下の点が考えられます。 • データ ストリームはデータレイク・オブジェクト (DLO) を自動的に作成します。 • データレイク・オブジェクト (DLO) は、データ変換（ハーモナイゼーション）のプロセスで使用され、データモデル・オブジェクト (DMO) にマッピングされます。 • データ ストリームを削除すると、それによって作成された DLO も影響を受けると考えられ、その DLO を入力として使用しているデータ変換やその後のプロセス（計算済みインサイト、セグメント、アクティベーションなど）は影響を受けます。 提示された選択肢の中で、削除の前に考慮すべき妥当な影響を最もよく示唆しているのは、**A. 基礎となる DLO はデータ変換で使用できます。**という点です。これは、削除によってデータ変換が影響を受ける可能性があることを示唆しており、コンサルタントはその影響範囲を事前に確認する必要があります。 正解は A. 基礎となる DLO はデータ変換で使用できます。 | J82: Salesforce.Data-Cloud-Consultant-JPN.v2025-03-28.q66 | K82: - | M82: *
B83: 53 | C83: ◯ | D83: 03_データ取得とデータモデリング | E83: Northern Trail Outfitters のコンサルタントは、Data Cloud を実装し、自社のセグメントのアクティベーション ターゲットを作成しています。 アクティベーション メンバーシップの場合、コンサルタントはどのオブジェクトを選択する必要がありますか? A. データセグメンテーションオブジェクト B. データアクティベーションオブジェクト C. データ モデル オブジェクト D. データレイクオブジェクト | F83: B C | G83: • A. データセグメンテーションオブジェクト: ソースには「セグメンテーション」のプロセスや結果としての「セグメント」については言及がありますが、セグメントのメンバー自体が「データセグメンテーションオブジェクト」という種類のオブジェクトとして存在するという記述はありません。 • B. データアクティベーションオブジェクト: ソースには「アクティベーション」のプロセスやターゲットについては言及がありますが、アクティベーションのメンバーシップが「データアクティベーションオブジェクト」として表現されるという記述はありません。 • C. データ モデル オブジェクト (DMO): Data Cloud におけるデータ統合と顧客の統一ビューの中心であり、セグメントおよびアクティベーションの基盤となります。セグメントのメンバーは、実質的にこの DMO 内のレコードです。 • D. データレイクオブジェクト (DLO): DLO はデータが取り込まれた初期段階のオブジェクトであり、マッピングと ID 解決の前の段階です。セグメントやアクティベーションは通常、より構造化され統合された DMO のデータに対して行われます. したがって、Data Cloud のフローとオブジェクトの役割に基づくと、アクティベーション メンバーシップのソースとなるのはデータモデルオブジェクトが適切です。 | H83: C | I83: ◾ 問題の状況： コンサルタントは Salesforce Data Cloud の導入を担当しており、 セグメントのアクティベーションターゲット（例：Marketing Cloudなど） を構成中。 その際に「アクティベーションメンバーシップのベースにする必要があるオブジェクトはどれか？」という質問です。 ✅ 正解理由：「Data Model Object（DMO）」がアクティベーションの基盤 Data Model Object とは： 顧客やトランザクションなどの意味的な単位で整理された、調和済みの構造データ セグメントは通常、Individual や Contact Point Email などの DMO をベースに構築される アクティベーションは、**「どのDMOからセグメント化されたデータを送信するか」**を指定するため、必ずDMOを基準に構成される アクティベーションメンバーシップの文脈： アクティベーションターゲット（例：Marketing Cloud、Amazon S3など）を構成する際、 **「どの DMO をベースに送信対象を定義するか」**を選択する必要がある そのため、DMO を中心にアクティベーションメンバーシップが設計される ❌ 他の選択肢の誤り： 選択肢 評価 理由 A. データセグメンテーションオブジェクト ❌ 不正解 実在しないオブジェクト名。セグメントはDMOに対して構成される B. データアクティベーションオブジェクト ❌ 不正解 存在しないオブジェクト。アクティベーションはDMOを基準に構成される C. データ モデル オブジェクト（DMO） ✅ 正解 アクティベーションで 送信対象レコードを定義する基本単位 D. データレイクオブジェクト（DLO） ❌ 不正解 DLOは取り込んだ未処理データの格納構造。アクティベーションに直接使用しない | J83: Salesforce.Data-Cloud-Consultant-JPN.v2025-03-28.q66 | K83: - | M83: *
B84: 54 | C84: ◯ | D84: 03_データ取得とデータモデリング | E84: Cumulus Financial は Service Cloud を CRM として使用し、 携帯電話、自宅の電話、職場の電話を顧客の 3 つの個別のフィールドとして連絡先レコードに保存します。同社は、Data Cloud を使用し、CRM コネクタ経由で連絡先オブジェクトを取り込むことを計画しています。 すべてのさまざまな電話番号が適切にマッピングされ、アクティベーションで使用できるようにするために、このデータを取り込むときにコンサルタントがとるべき最も効率的なアプローチは何ですか? A. Contact オブジェクトを取り込み、勤務先の電話、携帯電話、および自宅の電話を Contact データ ストリームから連絡先の電話データ マップ オブジェクトにマッピングします。 B. Contact オブジェクトを取り込み、ストリーミング変換を使用して、Contact データ ストリームからの電話番号を 3 行を含む別の Phone Data Lake オブジェクト (DLO) に正規化し、この新しい DLO を連絡先の電話にマッピングします。データマップオブジェクト。 C. Contact オブジェクトを取り込み、計算された分析情報を作成して電話番号を正規化し、Contact Point Phone データ マップ オブジェクトにマッピングします。 D. Contact オブジェクトを取り込み、電話番号の Contact データ ストリームに数式フィールドを作成し、Contact Point Phone データ マップ オブジェクトにマッピングします。 | F84: B | G84: コンサルタントがこのデータをインジェストする際、すべての異なる電話番号が適切にマッピングされ、アクティベーションで使用可能にするための最も効率的なアプローチはBです。Contactオブジェクトをインジェストし、Contactデータストリームから電話番号を正規化するためにストリーミング変換を使用し、3行を含む別のPhoneデータレイクオブジェクト（DLO）にマッピングします。その後、この新しいDLOをContact Point Phoneデータマップオブジェクトにマッピングします。このアプローチにより、コンサルタントはData Cloudのストリーミング変換機能を活用できます。この機能は、データ取り込み時にデータのマニピュレーションと変換を実行でき、追加の処理やストレージを必要としません。ストリーミング変換は、連絡先データストリームから電話番号を正規化するために使用できます。例えば、スペース、ハイフン、または括弧の削除、必要に応じて国コードの追加などが可能です。正規化された電話番号は、各電話番号の種類（仕事用、自宅用、携帯用）ごとに1行を格納する別のPhone DLOに保存されます。このPhone DLOは、連絡先ポイントに紐付いた電話番号を表す標準オブジェクトであるContact Point Phoneデータマップオブジェクトにマッピングされます。これにより、コンサルタントはすべての電話番号がアクティベーション（例：SMS送信や顧客への通話）に利用可能であることを確認できます。 他のオプションはオプションBほど効率的ではありません。オプションAは不正解です。電話番号を正規化しないため、アクティベーションやアイデンティティ解決に問題が発生する可能性があります。オプションCは、計算されたインサイトを作成する必要があるため不正です。これはストリーミング変換よりもリソースと時間を消費する追加の手順です。オプションDは、連絡先データストリームに式フィールドを作成する必要があるため不正です。これはCRMコネクタでサポートされていない可能性があり、または連絡先オブジェクトの既存のフィールドと衝突する可能性があります。参照：Salesforce Data Cloud Consultant Exam Guide、データインジェストとモデリング、ストリーミング変換、連絡先ポイント電話番号 | H84: B | I84: ◾ 問題の背景： Cumulus Financial のユースケースは： Salesforce Service Cloud の Contact オブジェクトに 📞 携帯電話、📞 自宅電話、📞 勤務先電話 の3フィールドが存在 Salesforce Data Cloud に取り込みたい 目的：すべての電話番号を Contact Point Phone DMO に正しくマッピングし、アクティベーションで使えるようにしたい ✅ なぜ「B」が正解なのか？ ▶ 正規化の必要性： 現在の状態は「1レコードに複数の列（カラム）で電話番号が格納されている」＝ワイド形式（wide format） Data Cloud が期待するのは「各電話番号が1行＝1レコード（long format）」の形で、 そのうえで type = "mobile" などの属性が付与されている構造。 ✅ 「ストリーミング変換」で正規化処理を実施する理由： 複数カラムを「縦持ち」に展開して、行ごとに電話番号＋種別を持つ新しい構造を作成できる たとえば： Contact ID Phone Type Phone Number 001 mobile 080-xxxx-xxxx 001 home 03-xxxx-xxxx 001 work 050-xxxx-xxxx こうして生成された構造を Phone 用の DLO → Contact Point Phone DMO にマッピング可能にする 結果として、Marketing Cloudやその他のアクティベーションで電話番号を正しく利用可能に ❌ 他の選択肢の誤り： 選択肢 評価 理由 A. Contactオブジェクトから直接3つのフィールドをマッピング ❌ 不正解 Contact Point Phone は 1つの電話番号＝1行構造が必要。そのままでは構造が不適切 C. 計算された分析情報で正規化する ❌ 不正解 CI（Calculated Insights）は 集計用であり、データ整形・正規化には不向き D. 数式フィールドで3つを変換してマッピング ❌ 不正解 数式では 複数カラム → 複数行の展開ができない（縦持ち変換不可） B. ストリーミング変換で3行に正規化し、DLO経由でマッピング ✅ 正解 唯一、期待される構造に変換でき、アクティベーションで使えるようにする手法 | J84: Salesforce.Data-Cloud-Consultant-JPN.v2025-03-28.q66 | K84: - | M84: *
B85: 55 | C85: ◯ | D85: 03_データ取得とデータモデリング | E85: クライアントは、同じレコード内に蓄積されたホテル ポイントと航空会社のポイントのポイント残高を含む Salesforce CRM のカスタム オブジェクトからロイヤルティ データを取り込みたいと考えています。クライアントは、追跡と処理を改善するために、これらのポイント システムを 2 つの別々のレコードに分割したいと考えています。 このシナリオでコンサルタントは何を推奨すべきでしょうか? A. データ ソース オブジェクトのクローンを作成します。 B. バッチ変換を使用して 2 番目のデータ レイク オブジェクトを作成します。 C. Salesforce CRM でジャンクション オブジェクトを作成し、取り込み戦略を変更します。 D. データレイク オブジェクトからデータキットを作成し、同じデータクラウド組織にデプロイします。 | F85: B | G85: バッチ変換は、既存のデータレイクオブジェクトを基に新しいデータレイクオブジェクトを作成し、それらに変換を適用する機能です。この機能は、データモデルやビジネス要件に合わせてデータを分割、結合、または再構成するのに役立ちます。この場合、コンサルタントはバッチ変換を使用して、元のロイヤルティデータオブジェクトから航空会社のポイントのみを含む新しいデータレイクオブジェクトを作成できます。元のオブジェクトをホテルポイントのみを含むように変更できます。これにより、クライアントは各ポイントシステムごとに2つの独立したレコードを保持し、それぞれを適切に追跡および処理できます。参照： バッチ変換、バッチ変換の作成 | H85: B | I85: ◾ 問題の背景： クライアントの現状は： Salesforce CRM 上の カスタムオブジェクト1件のレコード内に、ホテルポイントと航空会社ポイントの両方が同居している しかし、Data Cloud では「ホテル用ポイント」「航空用ポイント」を別レコードとして扱いたい → 2レコードに正規化（フラット化）したい ✅ なぜ「B. バッチ変換」が正解か？ ▶ バッチ変換とは： Data Cloud に取り込んだ Data Lake Object（DLO） に対して 行構造を再形成（列→行）する処理 たとえば、1レコード内に存在する hotel_points と airline_points を以下のように変換可能： 元の構造（1レコード） 変換後の構造（2レコード） ID:001 hotel: 500 airline: 300 ID:001, type: hotel, points: 500 ID:001, type: airline, points: 300 ▶ この変換の利点： ポイント種別ごとの集計、分析、セグメントが可能になる アクティベーション時にも明確な「種別別行」が活用できる CRM側のデータ構造をいじらずに実現できる（重要） ❌ 他の選択肢の誤り： 選択肢 評価 理由 A. データソースオブジェクトをクローン ❌ 不正解 クローンしてもデータ構造自体は変わらず、分割は実現できない C. Salesforceにジャンクションオブジェクトを作成 ❌ 非効率 CRM側の構造を変えるのは大きな影響がある。Data Cloud 側での正規化の方が現実的 D. データキットを作成してデプロイ ❌ 不正解 データキットは構成移行のための仕組みであり、正規化や分割には使えない B. バッチ変換を使って2つのレコードを作成 ✅ 正解 **行正規化に対応する唯一の正しい方法。**Data Cloud のベストプラクティスに沿っている | J85: Salesforce.Data-Cloud-Consultant-JPN.v2025-03-28.q66 | K85: - | M85: *
B86: 57 | C86: ◯ | D86: 03_データ取得とデータモデリング | E86: 小売顧客はさまざまなソースから顧客データを取得したいと考えています ID 解決を活用して、 セグメンテーションで使用されます。 これをアクティベーション メンバーシップとしてセグメント化する必要があるのはどのエンティティですか? A. 加入者 B. 統合された個人 C. 統合連絡先 D. 個人 | F86: B | G86: 正しい回答はB、Unified Individualです。Unified Individualは、異なるデータソースにわたる顧客を表現するレコードで、アイデンティティ解決ルールセットを適用して作成されます。アイデンティティ解決ルールセットは、共通属性に基づいて異なるソースからのデータをリンクし統合する方法定義する、一致と整合のルールセットです。Data Cloudはアイデンティティ解決ルールセットを使用して複数のデータソースにわたるデータを解決し、データがどこから来たかに関わらず、各顧客に対して1つのレコードを作成します1。小売業の顧客が、異なるソースから顧客データを統合し、セグメンテーションにアイデンティティ解決を使用したい場合、解決済みかつ統合された顧客データを含む「Unified Individual」エンティティでセグメンテーションを行う必要があります。他のオプションは、異なるソースにわたる解決済み顧客データを表さないため、正しくないです。Subscriberは、マーケティング通信の受信を承諾した顧客を表すレコードです。Unified Contact は、特定のビジネスユニットとの関係を持つ顧客を表すレコードです。Individual は、単一のデータソースからの顧客のプロファイルデータを表すレコードです。参照： アイデンティティ解決ルールセットの処理結果 セグメンテーションにおけるデータの影響を考慮する Salesforce Data Cloud コンサルタント資格の取得準備 AI ベースのアイデンティティ解決： 多様な顧客データのリンク | H86: B | I86: ◾ 問題の要点： 小売顧客は、**複数のソースから顧客データを統合（ID解決）**したうえで、 それを使って セグメントを作成・アクティベーションしたい。 つまり、「アクティベーションメンバーシップのベースにすべきエンティティ」はどれか？という問題です。 ✅ 正解理由：「統合された個人（Unified Individual）」がセグメントとアクティベーションの中核 ▶ Unified Individual（統合個人）とは： Salesforce Data Cloud において、ID解決ルールにより、複数ソースの顧客レコード（個人）を一人のプロファイルに統合したもの たとえば： CRMの「山田太郎（電話あり）」 ECの「Taro Yamada（メールあり）」 → これらを1人のUnified Individualとして扱う ▶ セグメント＆アクティベーションのベースに最適： マーケティング・パーソナライズ・アクティベーションで最も使われる単位 Unified Individual をもとにセグメントを作ることで、複数ソースの情報を統合した顧客単位で施策が可能 ❌ 他の選択肢の誤り： 選択肢 評価 理由 A. 加入者（Subscriber） ❌ 不正解 Marketing Cloud 用語。Data Cloud 上では対象外 C. 統合連絡先（Unified Contact） ❌ 不正解 Salesforce CRMにおける用語。Data Cloudでは「Unified Individual」が正式 D. 個人（Individual） ❌ 一部正解だが不十分 Individual はソースデータの単位。ID解決を経た統合対象ではない B. 統合された個人（Unified Individual） ✅ 正解 ID解決を通じた唯一の「統一顧客」単位で、セグメントとアクティベーションの中心 | J86: Salesforce.Data-Cloud-Consultant-JPN.v2025-03-28.q66 | K86: - | M86: *
B87: 69 | C87: ◯ | D87: 03_データ取得とデータモデリング | E87: 小売顧客はさまざまなソースから顧客データを取得したいと考えています ID 解決を活用して、 セグメンテーションで使用されます。 これをアクティベーション メンバーシップとしてセグメント化する必要があるのはどのエンティティですか? A. 加入者 B. 統合された個人 C. 統合連絡先 D. 個人 | F87: B | G87: 正しい回答はB、Unified Individualです。Unified Individualは、異なるデータソースにわたる顧客を表現するレコードで、アイデンティティ解決ルールセットを適用して作成されます。アイデンティティ解決ルールセットは、共通属性に基づいて異なるソースからのデータをリンクし統合する方法定義する、一致と整合のルールセットです。Data Cloudはアイデンティティ解決ルールセットを使用して複数のデータソースにわたるデータを解決し、データがどこから来たかに関わらず、各顧客に対して1つのレコードを作成します1。小売業の顧客が異なるソースから顧客データを統合し、セグメンテーションにアイデンティティ解決を使用したい場合、統合された顧客データを含む「Unified Individual」エンティティでセグメンテーションを行う必要があります。他のオプションは、異なるソースにわたる解決済みの顧客データを表さないため正しくないです。Subscriberは、マーケティング通信の受信を承諾した顧客を表すレコードです。Unified Contactは、特定のビジネスユニットとの関係を持つ顧客を表すレコードです。Individualは、単一のデータソースからの顧客のプロファイルデータを表すレコードです。参照： * 身分解決ルールセットの処理結果 * セグメンテーションにおけるデータの影響を考慮する * Salesforce Data Cloudコンサルタント資格の取得準備 * AIベースの身分解決： 多様な顧客データのリンク | H87: B | I87: ◾ 問題の背景： 小売顧客は、複数のソースから顧客データを取得し、 **ID 解決（Identity Resolution）**を用いてそれらを1人の顧客として統合したい。 そして、その統合プロファイルをもとにセグメントを作成し、アクティベーション（配信など）を行いたい。 → つまり、「アクティベーション メンバーシップとして使うべきエンティティはどれか？」という設問です。 ✅ 正解理由：「統合された個人（Unified Individual）」がアクティベーションの中核 ▶ Unified Individual（統合された個人）とは？ 複数のソース（CRM、Web行動、モバイルアプリなど）から取り込まれた個別のレコード（Individual）を ID解決のルールによって1人に統合したもの たとえば、「山田太郎」「Taro Yamada」など、名前やメールが一致するものを1人としてまとめた結果 ▶ アクティベーションのベース： Data Cloud では、アクティベーションの単位＝統合プロファイル（Unified Individual） が標準 アクティベーションメンバーシップに使用するセグメントも、この統合単位に対して定義される ❌ 他の選択肢の誤り： 選択肢 評価 誤りの理由 A. 加入者（Subscriber） ❌ 不正解 Marketing Cloud の用語。Data Cloud のセグメンテーション対象ではない B. 統合された個人 ✅ 正解 ID 解決により統合されたプロファイル。セグメントとアクティベーションの両方の中心 C. 統合連絡先 ❌ 存在しない用語 正式なData Cloudのオブジェクト名ではない D. 個人（Individual） ❌ 一部正解だが不十分 ソースごとのレコード単位。ID 解決によって統合されていないため、アクティベーションには不適 | J87: Salesforce.Data-Cloud-Consultant-JPN.v2024-09-12.q66 | K87: 57 | M87: *
B88: 70 | C88: ◯ | D88: 03_データ取得とデータモデリング | E88: コンサルタントは、クエリ API を使用して取得できるセグメント データを Audience DMO に公開する必要があります。 アクティベーション ターゲットを作成するときに、コンサルタントはどのタイプのターゲットを選択する必要がありますか? A. データクラウド B. 外部アクティベーションターゲット C. マーケティングクラウドパーソナライゼーション D. マーケティングクラウド | F88: B | G88: アクティベーション ターゲットの目的： * アクティベーション ターゲットは、セグメント データがさまざまなアプリケーションやプラットフォームで利用される際に、どこにどのように公開されるかを定義します。 | H88: B | I88: Data Cloud が行う活性化は、マッピングされたデータをアクション可能にし、エンゲージメント プラットフォームに配信することです。これらのエンゲージメント プラットフォームは Data Cloud の外部にあるため、「外部アクティベーションターゲット」というタイプが、これらの外部システム全般を指す分類として最も適切であると考えられます。Query API で取得し Audience DMO に公開したセグメント データは、最終的にこれらの外部ターゲットで活用されることになります。 したがって、Query API で取得したセグメント データを Audience DMO に公開し、アクティベーション メンバーシップとして使用する際に、コンサルタントがアクティベーション ターゲットを作成するときに選択すべきタイプのターゲットは、外部のエンゲージメント プラットフォームを指す B. 外部アクティベーションターゲット であると考えられます。 | J88: Salesforce.Data-Cloud-Consultant-JPN.v2024-09-12.q66 | K88: - | M88: *
B89: 74 | C89: ◯ | D89: 03_データ取得とデータモデリング | E89: Data Cloud コンサルタントは、整理されたクリーンなデータを扱っています。ただし、さまざまなスキーマがユーザー、連絡先、サブスクライバーなど複数の名前で人物を参照しているため、標準的なマッピングが必要です。 これらのさまざまなスキーマ ポイントを標準データ モデルにマッピングするプロセスを説明する用語はどれですか。 A. セグメント B. 調和する C. 統合 D. 変換 | F89: B | G89: データ調和の概要： * データ調和とは、異なるソースから取得したデータを統合し、一貫性を持たせるプロセスです。 | H89: B | I89: ◾ 問題の背景： Data Cloud コンサルタントは、以下のような状況に直面しています： 各ソースで「人物」を表す名称が異なる： 例）User, Contact, Subscriber, Customer など この 異なる構造・名称のデータを1つの標準データモデルに合わせる必要がある → このような「意味や形式が異なるデータ構造を標準化して統一する」プロセスを何と呼ぶか？ ✅ 正解理由：「調和（Harmonization）」はまさにそのプロセスを指す ▶ 調和とは？ Data Cloud において、異なるスキーマ・項目名・粒度を持つデータを、共通のデータモデルに合わせるプロセス 例： User.Name, Contact.FullName, Subscriber.DisplayName → Individual.FullName にマッピング この調和（Harmonization）を行うことで： ID解決（Identity Resolution）が機能しやすくなる セグメント・インサイト・アクティベーションが一貫して利用可能になる ❌ 他の選択肢の誤り： 選択肢 評価 理由 A. セグメント ❌ 不正解 「セグメント」は既に統合されたデータを対象に作る条件グループであり、マッピング作業ではない B. 調和する（Harmonize） ✅ 正解 異なるスキーマを標準データモデルにマッピングするプロセスそのもの C. 統合（Integrate） ❌ 不正確 「統合」はより広義。データの結合やID解決後の結果を指す場合が多い D. 変換（Transform） ❌ 一部正解だが不十分 変換は値や形式の加工であり、構造の標準化＝調和の方が適切 | J89: Salesforce.Data-Cloud-Consultant-JPN.v2024-09-12.q66 | K89: 33 | M89: *
B90: 85 | C90: ◯ | D90: 03_データ取得とデータモデリング | E90: データ クラウド コンサルタントは、新しいサービスベースのデータ ソースのデータ ストリームをセットアップ中です。 ケースデータを取り込む場合、どのフィールドをイベント時間フィールドに関連付けることが推奨されますか? A. 最終更新日 B. 解決日 C. エスカレーション日 D. 作成日 | F90: A D | G90: イベント時間フィールドは、データストリーム内のイベントのタイムスタンプをキャプチャする特別なフィールドタイプです。このフィールドは、イベントのchronological order（時系列順）を追跡し、時間ベースのセグメンテーションやアクティベーションを可能にするために使用されます。ケースデータをインジェストする際、イベント時間フィールドと関連付ける推奨フィールドは「最終更新日」フィールドです。このフィールドはケースの最新の更新日時を反映し、ケースの期間、解決時間、顧客満足度を測定するために使用できます。その他のフィールド（解決日、エスカレーション日、作成日など）は、イベント タイム フィールドには適していません。これらのフィールドは、ケースの最新の状態を捕捉しない場合や、すべてのケースに適用できない場合があります。参照： データ ストリーム フィールド タイプ、Salesforce Data Cloud 試験問題 • A. 最終更新日は、ケースが最後に変更された時点であり、ケースの発生時点を示すものではありません。 • B. 解決日は、ケースがクローズされた時点であり、これもケースの発生時点ではありません。 • C. エスカレーション日は、特定の状態変化が発生した時点であり、ケースの発生時点ではありません。 • D. 作成日は、ケースがシステムに最初に登録された時点であり、これはケースレコードが表すイベント（ケースの発生）の開始時点と言えます。 したがって、ソースには直接的な記載がありませんが、Data Cloudにおけるエンゲージメントデータのイベント時間フィールドの目的を考慮すると、ケースデータの作成日をイベント時間フィールドに関連付けることが最も理にかなっていると推測されます。 これはソースの直接的な推奨ではなく、Data Cloudのエンゲージメントデータのイベント時間フィールドの一般的な性質と、ケースデータのフィールドの意味合いに基づいた推測です。 | H90: D | I90: ◾ 問題の背景： Data Cloud コンサルタントは「ケースデータ（例：Service Cloudのケースオブジェクト）」を新しいデータストリームとして取り込んでおり、 その際に「イベント時間フィールド（Event Time Field）」を指定する必要があります。 ✅ 正解理由：「作成日（Created Date）」は、イベントの起点となる基本的な時間情報 ▶ イベント時間フィールドとは？ イベント系データ（例：ケース、購入、クリックなど）において、 「その行動や記録が発生した日時」を表す必須のフィールド これが セグメンテーション や インサイト計算（例：過去30日など） における時系列処理の基準になる ▶ なぜ「作成日」か？ ケースデータでは、「ケースが発生した瞬間」＝作成日（Created Date） このタイミングを起点に、解決までの経過日数や初回応答までの時間などを計算することが多い ❌ 他の選択肢の誤り： 選択肢 評価 理由 A. 最終更新日 ❌ 不適 ケースが何度も更新されると 時系列の一貫性が失われるため不安定 B. 解決日 ❌ 不適 解決されないケースもあるため、イベントの起点として不適切 C. エスカレーション日 ❌ 限定的すぎる すべてのケースに適用されるとは限らない。基準時間として不適 D. 作成日 ✅ 正解 すべてのケースに存在し、イベントの発生起点として信頼性が高い | J90: Salesforce.Data-Cloud-Consultant-JPN.v2024-09-12.q66 | K90: - | M90: *
B91: 89 | C91: ◯ | D91: 03_データ取得とデータモデリング | E91: Northern Trail Outfitters は、コンサルタントに、Track My Run モバイル アプリからランナーのプロフィールとアクティビティ ログを抽出し、Data Cloud に読み込むように依頼しました。マーケティング部門は、過去 90 日間の履歴データが必要であり、今後利用可能になった新しいデータと更新されたデータをすべて入手したいとも述べています。 ベストプラクティスとして、コンサルタントはこのリクエストを実行するためにどのアクションのシーケンスを使用する必要がありますか? A. 一括取り込みを使用して、まず過去 90 日間のデータを読み込み、その後、将来のデータが利用可能になったときに一括取り込みを使用して同期します。 B. ストリーミング取り込みを使用して、まず過去 90 日間のデータを読み込み、その後もストリーミング取り込みを使用して、将来のデータが利用可能になったときに同期します。 C. ストリーミング取り込みを使用して、まず過去 90 日間のデータを読み込み、次にバルク取り込みを使用して、将来のデータが利用可能になったときに同期します。 D. 最初に一括取り込みを使用して過去 90 日間のデータを読み込み、次にストリーミング取り込みを使用して将来のデータが利用可能になったときに同期します。 | F91: D | G91: 初期データ読み込み： 過去90日分のランナープロファイルやアクティビティログなど、大量の履歴データを一括で読み込むには、一括読み込みが最も効率的な方法です。これにより、高スループットのデータ転送が可能です。 * 一括読み込み： Salesforce Data Cloudの一括読み込みツールを使用して、履歴データを迅速かつ効率的に読み込みます。 継続的なデータ同期： Track My Run モバイルアプリで利用可能になった新しいレコードや変更されたレコードをData Cloudに反映させるため、ストリーミングインジェストが適しています。これにより、ほぼリアルタイムでのデータ更新が保証されます。 * ストリーミングインジェスト： モバイルアプリから新しいデータや更新されたデータを継続的にData Cloudに反映させるため、ストリーミングインジェストを設定します。 アクションの順序： * ステップ1： 過去90日分の履歴データをData Cloudにインポートするため、一括インジェストを実行します。 * ステップ2： ストリーミングインジェストを設定し、継続的な更新と新しいデータをリアルタイムで処理するようにします。 ベストプラクティス： このアプローチにより、初期の大容量データロードを効率的に処理し、継続的な更新をリアルタイムに近い状態で処理できます。これにより、マーケティング部門は最も最新のデータを利用できます。 参照： * Salesforce Data Cloud インジェスト方法 * Salesforce バルクデータインジェスト * Salesforce ストリーミングデータインジェスト | H91: D | I91: ◾ 問題の要点： Northern Trail Outfitters（NTO）のマーケティング部門は、以下の2つの要件を持っています： 過去90日分の履歴データを取り込みたい（履歴の一括処理が必要） それ以降は、新規データや更新データをリアルタイムで取り込みたい（継続的な同期が必要） ✅ 正解理由： この2段階の要件に対する Data Cloud のベストプラクティスは： ▶ ① 過去データ → バルク（一括）取り込み 90日分の履歴のように、大量かつ既知の静的データを取り込むには、バルク取り込みが適している CSV などのファイル形式で一括で読み込むことで効率的に初期データロードを行える ▶ ② 以後の新規・更新データ → ストリーミング取り込み モバイルアプリのようにリアルタイムで発生するイベント（ログイン、走行データ更新など）は、 Ingestion APIやストリーミング接続を用いてリアルタイムに取り込むのが理想 ❌ 他の選択肢の誤り： 選択肢 評価 理由 A. 一括 → 一括 ❌ 不適 将来のデータは継続的に発生するため、定期バッチではリアルタイム性が不足 B. ストリーミング → ストリーミング ❌ 不正確 履歴データの初期ロードには不向き。ストリーミングは主に今後のデータ向け C. ストリーミング → バルク ❌ 不自然な順序 時系列的に 履歴をバルク、将来をストリーミングの順が正しい D. バルク → ストリーミング ✅ 正解 最も自然かつ推奨されている手順 | J91: Salesforce.Data-Cloud-Consultant-JPN.v2024-09-12.q66 | K91: 4 | M91: *
B92: 93 | C92: ◯ | D92: 03_データ取得とデータモデリング | E92: ノーザン トレイル アウトフィッターズは、新しい顧客データを毎日 Amazon S3 バケットにアップロードして、データ クラウドに取り込みます。 新しくインポートされたデータを確実に準備して任意のセグメントで使用できるようにするには、各プロセスをどの順序で実行する必要がありますか? A. 計算されたインサイト > データ ストリームの更新 > ID 解決 B. データ ストリームの更新 > 計算された分析情報 > ID 解決 C. ID 解決 > データ ストリームの更新 > 計算された分析情報 D. データ ストリームの更新 > ID 解決 > 計算された分析情報 | F92: D | G92: Amazon S3 バケットから新規にインポートされたデータが、すべてのセグメントで利用可能かつ使用可能な状態になるように、以下のプロセスを以下の順序で実行する必要があります： * データ ストリームの更新： このプロセスは、ソース システムから最新のデータを取得し、Data Cloud内のデータ レイク オブジェクトを更新します。データ ストリームの設定に応じて、自動的に実行するか手動で実行するかを選択できます。 * 設定1. データストリームの更新により、Data CloudはAmazon S3 バケットから最も最新かつ正確なデータを取得します。 * 識別情報解決： このプロセスは、異なるデータストリームから取得したソースプロファイルを、識別情報解決ルールセットに基づいて一致させ統合し、統一された個人プロファイルを作成します。デフォルトでは毎日実行されますが、手動でトリガーすることも可能です2. 識別情報解決により、Data Cloudは異なるデータソースにわたる各顧客の単一ビューを確保します。 * 計算済みインサイト： このプロセスは、データレイクオブジェクトまたはCRMデータに対して計算を実行し、結果を新しいデータオブジェクトとして返します。セグメンテーションや分析目的でメトリクスや指標を作成するために使用できます3. 計算済みインサイトは、パーソナライゼーションやアクティベーションに利用できる派生データをData Cloudに確保します。 参照： * 1： データストリームの更新と頻度の設定 - Salesforce * 2： 識別解決ルールセットの処理結果 - Salesforce * 3： 計算済みインサイト - Salesforce | H92: D | I92: ◾ 問題の背景： Northern Trail Outfitters（NTO）は、毎日 Amazon S3 にアップロードされる新しい顧客データを Data Cloud に取り込んで処理し、 その結果をセグメントで使えるようにしたい。 つまり、取り込みからセグメント活用までの正しい処理ステップ順序を問う問題です。 ✅ 正解の理由： Data Cloud における処理フローは以下の通りです： ▶ ① データ ストリームの更新 S3 からの取り込みをトリガー データレイクオブジェクト（DLO）に格納 ▶ ② ID 解決（Identity Resolution） 取り込んだデータを 個人単位で統合（マージ） メール・電話・氏名などをもとに、ゴールデンプロファイル（統合個人） を生成 ▶ ③ 計算された分析情報（Calculated Insights） 統合済のデータに対してロジックを実行（例：LTV、購入回数など） セグメントやアクティベーションで使える集計・フラグデータを生成 ❌ 他の選択肢の誤り： 選択肢 評価 誤りの理由 A. CI → データ取り込み → ID解決 ❌ 不適切 データがまだ取り込まれてないのに集計は実行できない B. 取り込み → CI → ID解決 ❌ 不正確 CI は統合プロファイル（ID解決後）を元にするのが基本 C. ID解決 → 取り込み → CI ❌ 順序が逆 データがないと ID解決もできないため成立しない D. 取り込み → ID解決 → CI ✅ 正しい順序 最も自然かつ推奨されているステップフロー | J92: Salesforce.Data-Cloud-Consultant-JPN.v2024-09-12.q66 | K92: - | M92: *
B93: 117 | C93: ◯ | D93: 03_データ取得とデータモデリング | E93: Cumulus Financial は、Data Cloud を使用して銀行顧客をセグメント化し、Cloud File Storage アクティベーションを介してダイレクト メール用に顧客をアクティベートします。同社は、過去 2 年以内にこのセグメントに所属していた個人も分析したいと考えています。 どのデータ クラウド コンポーネントがこれを可能にしますか? A. ネストされたセグメント B. セグメントの除外 C. 計算された洞察 D. セグメント メンバーシップ データ モデル オブジェクト | F93: D | G93: セグメントメンバーシップデータモデルオブジェクトは、特定の期間内にセグメントに属していた個人を分析するためのData Cloudコンポーネントです。セグメントメンバーシップデータモデルオブジェクトは、どの個人がどのセグメントに属し、いつセグメントに追加または削除されたかを記録するテーブルです。このオブジェクトは、セグメントサイズ、セグメント期間、セグメントオーバーラップ、セグメントリテンションなどの計算済みインサイトを作成するために使用でき、セグメンテーションやアクティベーション戦略の有効性を測定するのに役立ちます。セグメントメンバーシップデータモデルオブジェクトは、セグメント名、セグメントタイプ、セグメントの日付範囲などのセグメントメンバーシップ基準に基づいて、ネストされたセグメントやセグメント除外を作成するためにも使用できます。他のオプションは正しくない理由は、これらは過去2年間にセグメントに所属していた個人を分析できるData Cloudコンポーネントではないためです。ネストされたセグメントとセグメント除外は、既存のセグメントに基づいてより複雑なセグメントを作成する機能ですが、セグメントメンバーシップの履歴データを提供しません。計算されたインサイトは、データモデルオブジェクトまたはデータレイクオブジェクトから導き出されたカスタムメトリクスまたはメトリクスですが、セグメントメンバーシップ情報を独自に保存しません。参照：セグメントメンバーシップデータモデルオブジェクト、計算されたインサイトの作成、ネストされたセグメントの作成 | H93: D | I93: ◾ 問題の確認： Cumulus Financial は以下を実現したいと考えています： **「過去2年間に特定のセグメントに属していた個人」**を把握し、分析に活用したい。 これは、セグメントの「履歴」や「所属期間」をトラッキングする必要があるという要件です。 ✅ 正解理由： ▶ D. セグメント メンバーシップ DMO（Segment Membership Data Model Object） これは、どの顧客がどのセグメントに、いつ属したかという履歴データを保持するオブジェクトです。 このDMOには、セグメントへの「参加日（Entry Date）」や「離脱日（Exit Date）」などのタイムスタンプ情報が含まれます。 したがって、「過去2年以内にこのセグメントに属していた個人を特定する」という要件に直接対応可能です。 ❌ 他の選択肢の誤り： 選択肢 評価 理由 A. ネストされたセグメント ❌ 他のセグメントを条件に使ったセグメント構築はできるが、過去の履歴は追跡できない。 B. セグメントの除外 ❌ セグメントから誰かを除外するためのロジック指定であり、履歴分析とは無関係。 C. 計算された洞察（Calculated Insights） ❌ 集計指標の生成には使えるが、セグメント所属の履歴そのものは保持していない。 | J93: Salesforce.Data-Cloud-Consultant-JPN.v2024-09-12.q66 | K93: - | M93: *
B94: 119 | C94: ◯ | D94: 03_データ取得とデータモデリング | E94: コンサルタントは、データ クラウド コンポーネントを 1 つからパッケージ化する必要があります。 組織を別の組織に。 コンサルタントがデータクラウドコンポーネントに含めるべき 2 つのデータクラウドコンポーネントはどれですか? この目標を達成するためのデータキットは? 2 つの答えを選択してください A. データ モデル オブジェクト B. セグメント C. 計算された洞察 D. ID 解決ルールセット | F94: A, D | G94: データ クラウド コンポーネントを組織間でパッケージ化するには、コンサルタントはデータ キットに以下のコンポーネントを含める必要があります： * データ モデル オブジェクト： これらは、データ クラウドのデータ モデルを定義するカスタム オブジェクトです。例： Individual、Segment、Activity など。これらのオブジェクトは、さまざまなソースから取り込まれたデータを格納し、統一されたプロファイルやセグメントの作成を可能にします1。 * 身分解決ルールセット： 異なるソースからのデータを一致させて統合し、統一されたプロファイルを作成するためのルールです。身分解決の基準、論理、優先順位を指定します2。参照： * 1： Data Cloud におけるデータモデルオブジェクト * 2： Data Cloud における身分解決ルールセット | H94: A, D | I94: ◾ 背景： Salesforce Data Cloud では、「データキット（Data Kit）」という仕組みを使って、 ある組織（Org）から別の組織へ構成済みのデータクラウドコンポーネントをパッケージとしてエクスポート/インポートすることができます。 ✅ 正解理由： ▶ A. データ モデル オブジェクト（DMO） DMO は、データ構造（オブジェクトとフィールド）を定義するコア要素であり、あらゆるセグメントやインサイトの基礎になります。 Data Kit での移行対象としてサポートされており、組織間の構成の一貫性を保つために重要です。 ▶ D. ID 解決ルールセット Identity Resolution のルール（マッチング条件、リンク、調整など）も Data Kit の構成対象です。 組織間で同一のID解決ロジックを再利用したい場合、Data Kitでエクスポート/インポートが可能です。 ❌ 他の選択肢の誤り： 選択肢 評価 誤りの理由 B. セグメント ❌ セグメントは現在、Data Kitのエクスポート対象外です。セグメントはローカルで再作成が必要です。 C. 計算された洞察（Calculated Insights） ❌ 計算された洞察も Data Kit では直接移行できません（クエリ定義の手動再作成が必要）。 📝 補足：Data Kit に含められる主なコンポーネント コンポーネント名 Data Kitに含められるか ✅ データ モデル オブジェクト ✔️ ✅ ID 解決ルールセット ✔️ ❌ セグメント ✘ 再作成が必要 ❌ 計算された洞察（CI） ✘ 再作成が必要 | J94: Salesforce.Data-Cloud-Consultant-JPN.v2024-09-12.q66 | K94: 36 | M94: *
B95: 121 | C95: ◯ | D95: 03_データ取得とデータモデリング | E95: ノーザン トレイル アウトフィッターズは B2C Commerce を使用しており、顧客とそのすべての注文トランザクションを統一的に把握するために Data Cloud の実装を検討しています。 B2C Commerce Order Bundle を使用して注文データを取り込む履歴データに関して、コンサルタントはどのようなことに留意する必要がありますか? A. B2C Commerce Order Bundle は、12 か月分の履歴データを取り込みます。 B. B2C Commerce Order Bundle は 6 か月分の履歴データを取り込みます。 C. B2C Commerce Order Bundle は履歴データを取り込まず、その時点以降の新しい注文のみを取り込みます。 D. B2C Commerce Order Bundle は 30 日間の履歴データを取り込みます。 | F95: C D | G95: B2C Commerce オーダー バンドルは、B2C Commerce インスタンスから Data Cloud へ注文データを送信するデータ ストリームを作成するデータ バンドルです。ただし、このデータ バンドルは過去のデータをインポートせず、データ ストリームが作成された時点以降の新しい注文のみをインポートします。したがって、コンサルタントが過去の注文データをインポートしたい場合は、B2C Commerceからデータをエクスポートし、CSVファイルを使用してData Cloudにインポートするなどの別の方法を使用する必要があります。12. 参照： * B2C Commerce データバンドルの作成 * B2C Commerce および Commerce Marketplace のデータアクセスとエクスポート 提供された資料に基づくと、ノーザン トレイル アウトフィッターズが B2C Commerce Order Bundle を使用して注文データを取り込む際の履歴データに関して、コンサルタントが留意すべき点として以下の情報が示されています。 Salesforce 接続ソースの詳細を示すスライド では、B2C コマースについて「バンドル注文可能」とあり、含まれるエンティティとして「注文 (カスタム属性を含む)」が挙げられています。このスライドの注意書きとして、**「注文トランザクションの履歴ロードは 30日間 のみ」**と明記されています。 また、「データ収集のタイミング」に関するスライド の表においても、B2C コマースのソースに対して、ルックバック ウィンドウが 30日 と記載されており、配信方法がバッチであることが示されています。レイテンシーとリフレッシュモードは、「セールスオーダー時間単位のアップサート セールスオーダー履歴全1時間ごとの完全更新毎日更新」となっています。 これらのソース情報から、B2C Commerce Order Bundle を使用した場合の注文データの履歴ロードには制限があり、その期間は 30 日であることが明確に示されています。 したがって、コンサルタントは以下の点に留意する必要があります。 • B2C Commerce Order Bundle は、過去 30 日間の注文トランザクションの履歴データを取り込みます。 • これより古い履歴データを取り込む場合は、別の方法（例えば、追加のデータストリーム設定やインジェストAPIの利用など、資料には直接記載されていませんが、可能性として考えられます）を検討する必要があるかもしれません。 選択肢の中で、このソース情報と一致するのは以下の記述です。 D. B2C Commerce Order Bundle は 30 日間の履歴データを取り込みます。 他の選択肢はソース情報と異なります。 • A. B2C Commerce Order Bundle は、12 か月分の履歴データを取り込みます。 と矛盾します。 • B. B2C Commerce Order Bundle は 6 か月分の履歴データを取り込みます。 と矛盾します。 • C. B2C Commerce Order Bundle は履歴データを取り込まず、その時点以降の新しい注文のみを取り込みます。 ソースでは「履歴ロード」が可能であることが示されているため、この記述は異なります。 以上のことから、提供されたソース資料に基づいて最も適切な回答は D です。 | H95: A D | I95: ◾ 問題の背景： ノーザン トレイル アウトフィッターズ（NTO）が B2C Commerce と Salesforce Data Cloud を統合し、顧客と注文トランザクションを統一的に把握したいというユースケースです。 その際に使用するのが： ▶ B2C Commerce Order Bundle： Salesforceが提供する、コネクテッドデータバンドルの一種 B2C Commerce の注文関連データ（例：Order、Order Itemなど）を Data Cloud に自動で取り込むためのテンプレートです。 ✅ 正解理由： B2C Commerce Order Bundle は、初回実行時に最大12か月分の注文履歴データを取り込む仕様です。 その後は定期的に新規データをストリーミング的に同期します（例：1日1回など）。 これにより、過去の注文履歴に基づいたセグメンテーションや分析が可能になります。 ❌ 他の選択肢の誤り： 選択肢 評価 理由 B. 6か月分の履歴データ ❌ 正しくは12か月まで取り込み可能。 C. 履歴データを取り込まない ❌ 初回同期時に履歴データを取り込み可能な点が重要。 D. 30日間の履歴データ ❌ 実際よりも短く、仕様と異なる。 | J95: Salesforce.Data-Cloud-Consultant-JPN.v2024-09-12.q66 | K95: 1 | M95: *
B96: 128 | C96: ◯ | D96: 03_データ取得とデータモデリング | E96: 製品ファミリーごとに機会の収益または数量を定義するデータ モデルのサブジェクト領域はどれですか? A. エンゲージメント B. 製品 C. パーティー D. 販売注文 | F96: D | G96: 販売注文の領域は、顧客が1つまたは複数の製品またはサービスに対して行った注文の詳細を定義します。これには、注文日、ステータス、金額、数量、通貨、支払い方法、配送方法などの情報が含まれます。販売注文の領域では、製品ファミリー（共通の特性や機能を持つ製品のグループ）ごとに、機会における売上高または数量を追跡することもできます。 例えば、注文内の各製品をその製品ファミリーと関連付けるために「販売注文行項目DMO」を使用し、その後「販売注文収益DMO」を使用して、機会内の各製品ファミリーごとの総収益または数量を計算できます。参照：販売注文対象領域、販売注文収益DMOリファレンス | H96: D | I96: ソースの情報に基づくと、製品ファミリーごとに機会の収益または数量を定義するために最も関連性の高いデータモデルのサブジェクト領域は、販売トランザクションに関連するものです。 ソース では、Data Cloud の標準データモデルの対象分野がいくつか分類されています。これには、販売注文データが含まれています。販売注文データには、「販売注文」という項目がリストされています。また、ソース によると、B2C コマースコネクタがサポートするバンドル注文可能なエンティティには、「販売注文 (カスタム属性を含む)」や「製品 (カスタム属性を含む)」が含まれています。さらに、インタラクション・スタジオ/エンゲージメントのイベント項目として「注文項目」が挙げられています。 これらの情報から、販売注文に関連するデータは Data Cloud に取り込まれ、製品がいくつ、いくらで販売されたかといった詳細が含まれていると推測できます。このデータは、製品ファミリーごとの販売数量や収益を集計し、「定義する」ための基礎となります。 セグメントを構築し、分析に活用するためには、 Data Cloud の重要な機能である計算された洞察 (Calculated Insights) を使用して、これらの販売注文データから製品ファミリーごとの収益や数量といったインサイトを導出することが考えられます。ソース および では、Data Cloud User が計算されたインサイトを作成できることが示されており、ソース および にはインサイトとセグメンテーションが Data Cloud の重要なコンポーネントとして挙げられています。 したがって、製品ファミリーごとに機会の収益または数量を定義するためのデータが存在するデータモデルのサブジェクト領域として、最も直接的に関連するのは販売注文です。 | J96: Salesforce.Data-Cloud-Consultant-JPN.v2024-09-12.q66 | K96: - | M96: *
B97: 135 | C97: ◯ | D97: 03_データ取得とデータモデリング | E97: 最近、Data Cloud コンサルタントが新しいデータ ソースを追加し、セグメントの作成に使用する新しいカスタム データ モデル オブジェクト (DMO) にデータの一部をマッピングしました。ただし、新しいセグメントを作成しようとしたときに、新しく作成された DMO を表示できません。 この問題の原因は何ですか? A. データは DMO に取り込まれていません。 B. 新しい DMO はプロファイル カテゴリではありません。 C. 新しいDMOは個々のDMOと関係がありません D. セグメンテーションは、個人 DMO と統合個人 DMO でのみサポートされます。 | F97: B | G97: この問題の原因は、新しいカスタム データ モデル オブジェクト (DMO) がプロファイル カテゴリではないことです。カテゴリは、Data Cloud での目的と機能を定義する DMO のプロパティです。DMO には、プロファイル、イベント、その他の 3 つのカテゴリがあります。プロファイル DMO は、個人またはエンティティの名前、メール、住所などの属性を保存するために使用されます。イベント DMO は、購入、クリック、訪問などの個人またはエンティティのアクションまたはインタラクションを保存するために使用されます。その他の DMO は、製品、場所、カテゴリなど、プロファイルまたはイベント カテゴリに当てはまらないその他のタイプのデータを保存するために使用されます。セグメントは個人またはエンティティの属性に基づいているため、Data Cloud でセグメントを作成するために使用できるのはプロファイル DMO のみです。したがって、新しいカスタム DMO がプロファイル カテゴリではない場合、セグメンテーション キャンバスには表示されません。その他のオプションは、この問題の原因ではないため、正しくありません。データ取り込みはセグメント作成の前提条件ではありません。セグメントは、実際のデータがなくてもデータ モデル スキーマに基づいて作成できます。新しい DMO は、他の DMO との関係に関係なく、任意のプロファイル DMO に基づいてセグメントを作成できるため、個々の DMO との関係を持つ必要はありません。セグメント化は、カスタムのものも含め、任意のプロファイル DMO に基づいて作成できるため、個人 DMO と統合個人 DMO でのみサポートされています。参照: 既存のデータ モデル オブジェクトからカスタム データ モデル オブジェクトを作成する、データ クラウドでセグメントを作成する、データ モデル オブジェクト カテゴリ | H97: B | I97: ご質問ありがとうございます。Data Cloud で新しく作成したカスタム データ モデル オブジェクト (DMO) がセグメント作成時に表示されない問題についてですね。提供された資料に基づいて、この問題の原因として考えられることをご説明します。 Data Cloud では、さまざまなソースからのデータを取り込み、データレイク オブジェクト (DLO) を経由して、データを Data Model Object (DMO) にマッピングします。この DMO が Data Cloud 内でのデータの構造化された表現となります。 スライド 49 では、データ オブジェクト (DMO) が以下のカテゴリに分類されることが示されています。 • プロファイル (Profile): セグメントの対象となるグループを表します。これは、セグメンテーションの開始点として使用される親グループを含みます。 • 婚約 (Engagement): 時系列データセットです。 • その他 (Other): データセットに関連するプロファイルまたはエンゲージメント データです。 セグメンテーションは、これらのカテゴリのうち、プロファイル カテゴリに分類された DMO を基点として行われます。Data Cloud の標準データモデルにおいて、「個人」などの主要な顧客エンティティは「パーティー (Party)」対象分野に属し、これがプロファイル カテゴリの典型的な DMO となります。 したがって、新しく作成したカスタム DMO がセグメント作成時に表示されない原因として、最も直接的に考えられるのは、その DMO がセグメンテーションの基点として使用できる「プロファイル」カテゴリとして設定されていないことです。 各選択肢について検討します。 • A. データは DMO に取り込まれていません。(Data has not been ingested into the DMO.) ◦ データの取り込みは必須プロセスですが、データが取り込まれていない場合でも DMO 自体は存在し、セグメント作成画面で表示されるかどうかは、DMO のカテゴリ設定に依存します。データがなくても DMO がプロファイル カテゴリであれば表示される可能性があり、この選択肢は根本原因ではない可能性が高いです。 • B. 新しい DMO はプロファイル カテゴリではありません。(The new DMO is not a Profile category.) ◦ スライド 49 に明確に記載されているように、セグメンテーションはプロファイル カテゴリの DMO を使用して行われます。新しいカスタム DMO がプロファイル カテゴリとして定義されていない場合、セグメント作成時の基点として選択肢に表示されないと考えられます。これは問題の状況と一致する、最も可能性の高い原因です。 • C. 新しい DMO は個々の DMO と関係がありません (The new DMO has no relationship with the Individual DMO) ◦ DMO 間に関係性がない場合でも、その DMO 自体がプロファイル カテゴリであれば、セグメンテーションの開始点として表示される可能性があります。関係性はセグメント作成時にデータをたどるために重要ですが、DMO が選択肢に表示されるかどうかはカテゴリに依存します。 • D. セグメンテーションは、個別 DMO および統合個別 DMO でのみサポートされます。(Segmentation is only supported on Individual DMO and Unified Individual DMO.) ◦ 資料では、セグメンテーションの基点として「プロファイル カテゴリ」の DMO が使用されると説明されています。標準の「個人」DMO は主要なプロファイル DMO ですが、カスタム DMO もプロファイル カテゴリとして作成・設定することが可能です。したがって、「個別 DMO および統合個別 DMO でのみ」というのは資料の記述 と完全に一致するわけではありません。カスタム DMO がプロファイル カテゴリとして設定されているにも関わらず表示されないのであれば別の原因が考えられますが、プロファイル カテゴリ以外に設定されているのであれば、それが原因です。選択肢 B の「プロファイル カテゴリではない」という説明は、この問題のより直接的な原因を示しています。 したがって、提供された資料に基づくと、この問題の最も考えられる原因は、新しいカスタム DMO がセグメンテーションの基点として機能する「プロファイル」カテゴリとして設定されていないことです。 正解は B. 新しい DMO はプロファイル カテゴリではありません。 です。 | J97: Salesforce.Data-Cloud-Consultant.v2024-12-02.q93 | K97: 7 | M97: *
B98: 141 | C98: ◯ | D98: 03_データ取得とデータモデリング | E98: Cumulus Financial は、Data Cloud を使用して銀行の顧客をセグメント化し、クラウド ファイル ストレージのアクティベーションを介してダイレクト メールをアクティブ化します。同社はまた、過去 2 年以内にセグメントにいた個人を分析したいと考えています。 どの Data Cloud コンポーネントがこれを可能にしますか? A. ネストされたセグメント B. セグメントの除外 C. 計算された洞察 D. セグメントメンバーシップデータモデルオブジェクト | F98: D | G98: セグメント メンバーシップ データ モデル オブジェクトは、特定の期間内にセグメントにいた個人を分析できる Data Cloud コンポーネントです。セグメント メンバーシップ データ モデル オブジェクトは、どの個人がどのセグメントに属しているか、およびいつセグメントに追加または削除されたかに関する情報を格納するテーブルです。このオブジェクトを使用すると、セグメント サイズ、セグメント期間、セグメントの重複、セグメントの保持などの計算されたインサイトを作成できます。これらのインサイトは、セグメンテーションおよびアクティベーション戦略の有効性を測定するのに役立ちます。セグメント メンバーシップ データ モデル オブジェクトは、セグメント名、セグメント タイプ、セグメントの日付範囲などのセグメント メンバーシップ基準に基づいて、ネストされたセグメントまたはセグメント除外を作成するためにも使用できます。その他のオプションは、過去 2 年以内にセグメントにいた個人を分析できる Data Cloud コンポーネントではないため、正しくありません。ネストされたセグメントとセグメント除外は、既存のセグメントに基づいてより複雑なセグメントを作成できる機能ですが、セグメント メンバーシップに関する履歴データは提供されません。計算されたインサイトは、データ モデル オブジェクトまたはデータ レイク オブジェクトから派生したカスタム メトリックまたはメジャーですが、それ自体ではセグメント メンバーシップ情報を保存しません。参照: セグメント メンバーシップ データ モデル オブジェクト、計算されたインサイトの作成、ネストされたセグメントの作成 | H98: D | I98: ◾ 背景： Cumulus Financial は以下のような分析要件を持っています： Data Cloud で作成したセグメントに現在属している人だけでなく、 **「過去2年以内にそのセグメントに属していたことがある人」**も対象として分析したい。 つまり、セグメントへの「過去の所属履歴」＝セグメントのタイムライン情報を追跡したいというニーズです。 ✅ 正解理由： ▶ D. セグメントメンバーシップ DMO（Segment Membership Data Model Object） このオブジェクトは、**「どの個人（Individual）が、いつ、どのセグメントに所属していたか」**という情報を保持する専用データモデルです。 含まれる代表的なフィールド： Individual Id Segment Id Entry Date（セグメントに入った日） Exit Date（セグメントを離脱した日） これにより、「過去にセグメントに属していた期間」や「セグメント滞在履歴の分析」が可能です。 ❌ 他の選択肢の誤り： 選択肢 理由 評価 A. ネストされたセグメント 他のセグメントを条件に利用できるが、「過去に属していたかどうか」の履歴データは保持していない。 ❌ B. セグメントの除外 除外条件を追加する機能であり、過去の所属履歴を取得・分析する用途ではない。 ❌ C. 計算された洞察（Calculated Insights） 集計やスコアリングには使えるが、セグメントへの「過去の所属履歴」そのものは含まれない。 ❌ | J98: Salesforce.Data-Cloud-Consultant.v2024-12-02.q93 | K98: 117 | M98: *
B99: 147 | C99: ◯ | D99: 03_データ取得とデータモデリング | E99: 実装プロジェクト中に、コンサルタントが顧客のすべてのデータ ストリームの取り込みを完了しました。 データをセグメント化して操作する前に、どのような追加構成が必要ですか? A. データのアクティベーション B. 計算された洞察 C. データマッピング D. アイデンティティ解決 | F99: D C | G99: さまざまなソースから Data Cloud にデータを取り込んだ後、そのデータをセグメント化して操作する前に必要な追加の構成は、Identity Resolution です。Identity Resolution は、さまざまなデータ ソースのソース プロファイルを照合および調整し、単一の個人またはエンティティを表す統合プロファイルを作成するプロセスです1。Identity Resolution を使用すると、顧客と見込み客の 360 度ビューを作成し、属性と動作に基づいてセグメント化してアクティブ化できます2。Identity Resolution を構成するには、データの一致ルールと調整ルールを定義するルールセットを作成して展開する必要があります3。その他のオプションは、データをセグメント化して操作する前には必要ないため、正しくありません。Data Activation は、マーケティング、販売、またはサービスの目的で、Data Cloud から他の Salesforce クラウドまたは外部の送信先にデータを送信するプロセスです4。Calculated Insights は、生涯価値、解約リスク、製品アフィニティなど、ソース データまたは統合データに基づいて計算される派生属性です5。Data Mapping は、ソース属性をデータ モデル内の統合属性にマッピングするプロセスです。これらの設定は、データのセグメント化と処理の後で、またはアイデンティティ解決と並行して行うことができますが、前提条件ではありません。参考資料: アイデンティティ解決の概要、データクラウドでのデータのセグメント化とアクティブ化、アイデンティティ解決ルールセットの構成、データアクティブ化の概要、計算されたインサイトの概要、 [データマッピングの概要] | H99: C | I99: ◾ 解説： Salesforce Data Cloud では、データストリームで取り込んだデータはまず「データレイクオブジェクト（DLO）」に保存されます。 しかし、そのままではセグメント化やアクティベーションに使えません。 セグメントや分析を行うためには、次のステップが必要です： データストリームでデータ取り込み（完了済み） ✅ データマッピング（DLO → DMO） ← これが次の必須ステップ セグメント作成、CI（計算された洞察）、ID解決、アクティベーションなどを構成 ✅ 正解理由： データをセグメントや計算、アクティベーションに使うには、「ビジネスロジックに沿った構造（DMO）」として扱う必要があります。 そのためには、DLOの生データをDMOにマッピングする＝データマッピングが必要です。 このステップを経ないと、セグメントビルダーで条件指定する項目すら表示されません。 ❌ 他の選択肢の誤り： 選択肢 評価 理由 A. データのアクティベーション ❌ セグメント完成後に行う「出力処理」。前提条件ではない。 B. 計算された洞察（CI） ❌ DMOベースのクエリ処理であり、マッピングが完了していないと作成すらできない。 D. アイデンティティ解決 ❌ セグメント化に必要な構成ではあるが、マッピング後に行うステップ。まずは構造を整える必要がある。 📝 補足：セグメント利用前の必須ステップ ステップ順 ステップ名 内容 1 データストリーム 外部からDLOにデータを取り込む 2 ✅ データマッピング DLO → DMO へ構造変換、セグメント利用可能に 3 セグメント構成 対象条件を指定して絞り込み 4 CI / ID解決など 分析・統合・アクティベーションなどに拡張可能 | J99: Salesforce.Data-Cloud-Consultant.v2024-12-02.q93 | K99: - | M99: *
B100: 161 | C100: ◯ | D100: 03_データ取得とデータモデリング | E100: 顧客は、データ ウェアハウスのトランザクション データを Data Cloud で使用したいと考えています。 データは SFTP サイト経由でのみエクスポートできます。 ファイルを Data Cloud に取り込むにはどうすればよいでしょうか? A. SFTP コネクタを使用してファイルを取り込みます。 B. Cloud Storage Connector を介してファイルを取り込みます。 C. データ インポート ウィザードを使用してファイルを手動でインポートします。 D. Salesforce の Dataloader アプリケーションを使用して、デスクトップから一括アップロードを実行します。 | F100: A | G100: SFTP コネクタは、Data Cloud が SFTP サーバーからデータを取り込むことを可能にするデータ ソース コネクタです。 お客様は SFTP コネクタを使用して、エクスポートしたファイルからデータ ストリームを作成し、それをデータ レイク オブジェクトとして Data Cloud に取り込むことができます。他のオプションは、次の理由により、ファイルを Data Cloud に取り込む最適な方法ではありません。 * B. クラウド ストレージ コネクタは、Data Cloud が Amazon S3、Azure Storage、Google Cloud Storage などのクラウド ストレージ サービスからデータを取り込むことを可能にするデータ ソース コネクタです。顧客のデータはこれらのサービスには保存されておらず、SFTP サイトにのみ保存されています。 * C. データ インポート ウィザードは、アカウント、取引先責任者、リード、ソリューション、キャンペーン メンバーなど、多くの標準 Salesforce オブジェクトのデータをユーザーがインポートできるようにするツールです。SFTP サイトからデータをインポートしたり、Data Cloud 内のカスタム オブジェクトをインポートしたりするようには設計されていません。 * D. データローダーは、Salesforce レコードの挿入、更新、削除、エクスポートをユーザーが実行できるアプリケーションです。SFTP サイトからデータを取り込んだり、データクラウドにデータを取り込んだりするために設計されたものではありません。参考資料: SFTP コネクタ - Salesforce、データクラウドで SFTP コネクタを使用してデータストリームを作成する - Salesforce、データインポートウィザード - Salesforce、Salesforce データローダー | H100: A | I100: ◾ 背景： 顧客は、データウェアハウスからSFTPサイトを介してのみエクスポート可能なトランザクションデータを、Salesforce Data Cloud に取り込みたいと考えています。 このような場合、Data Cloud 側に自動でデータを連携させるには、SFTP対応の取り込み手段が必要です。 ✅ 正解理由： ▶ A. SFTP コネクタ Salesforce Data Cloud は 標準で「SFTP Connector」 をサポートしており、次のような流れでデータを取り込めます： SFTP サーバのホスト情報・認証情報を指定して接続設定を作成 Data Cloud 側で データストリーム を作成して、SFTP 上のファイル（CSVなど）を定期的に取り込み ファイル名のワイルドカード指定やスケジューリングも可能 この方法により、SFTP 経由でしか出力できない環境でも、完全に自動化された連携が実現します。 ❌ 他の選択肢の誤り： 選択肢 理由 評価 B. Cloud Storage Connector ❌ これは Amazon S3 や Google Cloud Storage などクラウドストレージ向けであり、SFTP には対応していない。 C. データ インポート ウィザード ❌ これは主に Salesforce CRM（Core Cloud）向けの手動インポートツールであり、Data Cloud では使用不可。 D. Dataloader アプリケーション ❌ これも CRMデータ向けのローカルツールであり、Data Cloud の データストリーム処理には非対応。 | J100: Salesforce.Data-Cloud-Consultant.v2024-12-02.q93 | K100: 25 | M100: *
...
